Workbook

Sheet README
A1: WP006 Research Appendix — Retrieval Compression for AI Retrievability
A2: Working Paper No. 006 · Akshay Dahiya · AI Spider Pre-Build Validation Series · 2025-2026
A4: HOW TO USE THIS WORKBOOK
A5: This workbook is the complete research audit trail for WP006. Every number published in the whitepaper is traceable to a specific cell in one of the 22 sheets below.
A6: Ground truth sheets (GT_V1 and GT_V2) contain MANUAL sentence-level labels established before any model was run — this is the most important sheet for an auditor.
A7: Classification sheets (6 sheets, one per model per vertical) contain every sentence as classified by that model — the primary raw data.
A8: Metrics_Calculator derives all four metrics (Fact-to-Claim ratio, Evidence Support ratio, Density, Score) via formula from classification sheet counts.
A9: Colour convention: BLUE text = hardcoded input | BLACK = formula | GREEN = cross-sheet link | AMBER = ground truth reference | RED = flagged divergence from GT.
A11: SHEET INDEX
A12: # | B12: Sheet Name | C12: Purpose | D12: Whitepaper Section | E12: Type
A13: 1 | B13: README | C13: Workbook guide and sheet index | D13: All | E13: Navigation
A14: 2 | B14: Research_Assumptions | C14: Key assumptions and how every headline number was derived | D14: Abstract, Sec 2 | E14: Assumptions
A15: 3 | B15: GT_V1_Semrush | C15: Manual ground truth — V1 Semrush KB page, established BEFORE model runs | D15: Sec 2.4 | E15: Ground truth
A16: 4 | B16: GT_V2_WebFX | C16: Manual ground truth — V2 WebFX homepage, established BEFORE model runs | D16: Sec 2.4 | E16: Ground truth
A17: 5 | B17: Prompt_Template | C17: Full 4-stage prompt used identically across all 3 models | D17: Sec 2.3 | E17: Methodology
A18: 6 | B18: Run_Log | C18: Timestamped log of all 6 model runs (3 models x 2 verticals) | D18: Sec 2.5 | E18: Process log
A19: 7 | B19: Claude_V1_Classification | C19: Sentence-level Fact/Claim/Evidence labels — Claude Sonnet 4.6, V1 Semrush | D19: Sec 3.1 | E19: Raw classification
A20: 8 | B20: ChatGPT_V1_Classification | C20: Sentence-level Fact/Claim/Evidence labels — ChatGPT GPT-5.5, V1 Semrush | D20: Sec 3.1 | E20: Raw classification
A21: 9 | B21: Gemini_V1_Classification | C21: Sentence-level Fact/Claim/Evidence labels — Gemini 3.5 Flash, V1 Semrush | D21: Sec 3.1 | E21: Raw classification
A22: 10 | B22: Claude_V2_Classification | C22: Sentence-level Fact/Claim/Evidence labels — Claude Sonnet 4.6, V2 WebFX | D22: Sec 3.2 | E22: Raw classification
A23: 11 | B23: ChatGPT_V2_Classification | C23: Sentence-level Fact/Claim/Evidence labels — ChatGPT GPT-5.5, V2 WebFX | D23: Sec 3.2 | E23: Raw classification
A24: 12 | B24: Gemini_V2_Classification | C24: Sentence-level Fact/Claim/Evidence labels — Gemini 3.5 Flash, V2 WebFX | D24: Sec 3.2 | E24: Raw classification
... A34: 22 | B34: Limitations | C34: Known limitations and caveats affecting result precision | D34: Sec 6 | E34: Methodology

Sheet Research_Assumptions
A1: Research Assumptions and Key Number Derivations
A2: How every headline figure in WP006 was calculated — the fast-path for any auditor
A4: This sheet answers the question a researcher asks first: where did these numbers come from, and what assumption underlies each one?
A5: All six model-run figures (Facts, Claims, Evidence, Scores) are recorded here with their source and derivation logic.
A6: Ground truth figures are marked AMBER. Model outputs are BLUE inputs. Formula-derived values are BLACK.
A8: SECTION 1 — Core Research Design
A9: Parameter | B9: Value | C9: Derivation / Source | D9: Assumption Made | E9: Verify In
A10: Models tested | B10: 3 (Claude Sonnet 4.6, ChatGPT GPT-5.5, Gemini 3.5 Flash) | C10: Selected from WP001-005 incumbents; Qwen excluded after WP002 | D10: 3 models provide sufficient triangulation for boundary disagreement analysis without excessive runtime | E10: Run_Log, Sec 2.5
A11: Verticals tested | B11: 2 (V1: AI/GEO Tools, V2: Digital Marketing Agency) | C11: V1 = Semrush KB page (low-evidence, carried from WP001-004). V2 = WebFX homepage (high-evidence benchmark) | D11: Two pages chosen to maximise discrimination: one MEDIUM, one HIGH density, allowing the score gap to be measured | E11: GT_V1_Semrush, GT_V2_WebFX, Sec 2.4
A12: Total model runs | B12: 6 (3 models x 2 verticals) | C12: =3*2 -> 6 | D12: Each run is independent — same prompt, fresh context, no conversation history | E12: Run_Log
A13: Prompt version | B13: v1.0 — identical across all 3 models | C13: A single prompt template with embedded classification definitions, no model-specific variants | D13: Identical prompt is the experimental control. Any score difference is attributable to the model, not the prompt | E13: Prompt_Template
A14: Ground truth method | B14: Manual sentence-by-sentence labelling by researcher before model runs | C14: Each significant sentence on both pages was manually classified as Fact, Claim, or Evidence before any model was queried | D14: Manual GT established first to prevent anchoring — researcher labels were locked before any model output was seen | E14: GT_V1_Semrush, GT_V2_WebFX
A15: Key Fact/Claim boundary | B15: Feature descriptions = Claims, not Facts | C15: A sentence like 'benchmarks brand AI visibility' asserts a capability without verifiable specifics = Claim. A sentence like '$99/month pricing' = Fact. | D15: This boundary is the single most consequential assumption in the study. ChatGPT crossed it; Claude and Gemini respected it. | E15: GT_V1_Semrush, GT_Accuracy, Sec 2.1
A17: SECTION 2 — Headline Number Derivations
A18: Headline Figure | B18: Published Value | C18: Source | D18: Formula / Logic | E18: GT Range | F18: Verify In
A19: V1 Semrush – Claude Fact count | B19: 14 | C19: Claude_V1_Classification | D19: COUNTIF(classification_col, 'FACT') — see Metrics_Calculator for live formula | E19: ~11 (GT) | F19: Claude_V1_Classification, Metrics_Calculator
A20: V1 Semrush – ChatGPT Fact count | B20: 30 | C20: ChatGPT_V1_Classification | D20: COUNTIF(classification_col, 'FACT') — INFLATED: feature descriptions counted as Facts | E20: ~11 (GT) | F20: ChatGPT_V1_Classification, GT_Accuracy
A21: V1 Semrush – Gemini Fact count | B21: 14 | C21: Gemini_V1_Classification | D21: COUNTIF(classification_col, 'FACT') — see Metrics_Calculator for live formula | E21: ~11 (GT) | F21: Gemini_V1_Classification, Metrics_Calculator
A22: V1 Semrush – Claude Score | B22: 58 | C22: Metrics_Calculator | D22: Composite 0-100: weighted F-to-C ratio (60%) + Evidence Support ratio (40%), penalised for zero evidence | E22: 45-55 (GT) | F22: Metrics_Calculator, Score_Comparison
A23: V1 Semrush – ChatGPT Score | B23: 72 | C23: Metrics_Calculator | D23: Same formula — inflated by high false-Fact count driving F-to-C ratio to 85.7% | E23: 45-55 (GT) | F23: Metrics_Calculator, Score_Comparison
A24: V1 Semrush – Gemini Score | B24: 60 | C24: Metrics_Calculator | D24: Same formula — F-to-C ratio 63.6%, zero evidence, moderate penalty applied | E24: 45-55 (GT) | F24: Metrics_Calculator, Score_Comparison
A25: V2 WebFX – Claude Fact count | B25: 16 | C25: Claude_V2_Classification | D25: COUNTIF(classification_col, 'FACT') — see Metrics_Calculator for live formula | E25: ~14 (GT) | F25: Claude_V2_Classification
A26: V2 WebFX – Claude Evidence count | B26: 8 | C26: Claude_V2_Classification | D26: COUNTIF(classification_col, 'EVIDENCE') — most accurate evidence detection of 3 models | E26: ~5-6 (GT) | F26: Claude_V2_Classification, GT_Accuracy
A27: V2 WebFX – Gemini Evidence count | B27: 2 | C27: Gemini_V2_Classification | D27: UNDER-DETECTED: missed 1.8X lead growth benchmark, 15% ROI, manufacturing case study | E27: ~5-6 (GT) | F27: Gemini_V2_Classification, GT_Accuracy, Findings_Traceability F3
A28: V2 WebFX – Claude Score | B28: 81 | C28: Metrics_Calculator | D28: Only score within GT range (78-88). High F-to-C (80%) + Evidence Support (200%) | E28: 78-88 (GT) | F28: Metrics_Calculator, Score_Comparison
A29: Score discrimination Claude | B29: +23 pts (58 -> 81) | C29: Score_Discrimination | D29: Score_Discrimination!D5 (Claude V2 - Claude V1) | E29: Positive required | F29: Score_Discrimination
A30: Score discrimination ChatGPT | B30: +20 pts (72 -> 92) | C30: Score_Discrimination | D30: Score_Discrimination!D6 (ChatGPT V2 - ChatGPT V1) | E30: Positive required | F30: Score_Discrimination
A31: Score discrimination Gemini | B31: +32 pts (60 -> 92) | C31: Score_Discrimination | D31: Score_Discrimination!D7 (Gemini V2 - Gemini V1) | E31: Positive required | F31: Score_Discrimination
A34: SECTION 3 — Metric Formula Reference
A35: Fact-to-Claim Ratio = Facts / (Facts + Claims) e.g. Claude V1: 14/(14+8) = 63.6%
A36: Evidence Support Ratio = Evidence / Claims e.g. Claude V2: 8/4 = 200%
A37: Density = HIGH if F-to-C >= 50% AND Evidence >= (Claims/3) | MEDIUM if F-to-C 30-50% OR limited evidence | LOW if below 30%
A38: Compression Score = composite 0-100: F-to-C weighted 60%, Evidence Support weighted 40%, penalised for zero evidence regardless of F-to-C
A39: Score Gap = V2 Score - V1 Score per model (must be positive to confirm discrimination — validated in Score_Discrimination sheet)

Sheet GT_V1_Semrush
A1: Ground Truth — V1 Semrush AI Visibility Toolkit KB Page
A2: Manual sentence-level classification established BEFORE any model run. Timestamped: 2025-10-14.
A4: PURPOSE: This is the most important sheet for reproducibility. Ground truth was established by the researcher
A5: reading the Semrush KB page sentence by sentence and classifying each per the definitions in Prompt_Template.
A6: These labels were LOCKED before Claude, ChatGPT, or Gemini were queried. See Run_Log for date confirmation.
A7: The Fact/Claim boundary note: feature descriptions ('identifies competitive gaps') = CLAIM. Only verifiable specifics = FACT.
A9: GROUND TRUTH LABEL: Manual researcher classification | Date locked: 2025-10-14 | NOT a model output
A10: Sentence ID | B10: Sentence Text (from Semrush KB page) | C10: GT Label | D10: Rationale | E10: Boundary Case? | F10: Whitepaper Ref
A11: V1-S01 | B11: $99/month — Semrush AI Visibility Toolkit entry price | C11: FACT | D11: Specific verifiable price point | E11: No | F11: Sec 2.4, GT Fact #1
A12: V1-S02 | B12: 261M+ prompts in the monitoring database | C12: FACT | D12: Specific, verifiable quantity | E12: No | F12: Sec 2.4, GT Fact #2
A13: V1-S03 | B13: Available in Business and Enterprise plans | C13: FACT | D13: Specific plan tier — verifiable from pricing page | E13: No | F13: Sec 2.4, GT Fact #3
A14: V1-S04 | B14: Monitors brand visibility across ChatGPT, Gemini, Perplexity, Claude, Copilot | C14: FACT | D14: Named platforms — verifiable specific list | E14: No | F14: Sec 2.4, GT Fact #4
A15: V1-S05 | B15: AI Visibility Score updated daily | C15: FACT | D15: Specific update frequency — verifiable | E15: Borderline | F15: Sec 2.4, GT Fact #5
A16: V1-S06 | B16: Visibility Overview report shows AI Visibility Score | C16: FACT | D16: Named report with named output — specific enough to be verifiable | E16: No | F16: Sec 2.4, GT Fact #6
A17: V1-S07 | B17: Market Explorer shows category-level AI share data | C17: FACT | D17: Named feature with named output | E17: Borderline | F17: Sec 2.4, GT Fact #7
A18: V1-S08 | B18: Tracks changes in AI mentions over time | C18: FACT | D18: Specific function, directional — verifiable by testing the tool | E18: Borderline | F18: Sec 2.4, GT Fact #8
A19: V1-S09 | B19: Prompt Explorer shows which prompts trigger brand mentions | C19: FACT | D19: Named feature with named, specific output type | E19: No | F19: Sec 2.4, GT Fact #9
A20: V1-S10 | B20: Prompt library contains 261M+ entries | C20: FACT | D20: Same database figure — specific | E20: No | F20: Sec 2.4, GT Fact #10
A21: V1-S11 | B21: AI Visibility Score ranges 0-100 | C21: FACT | D21: Specific scale definition — verifiable | E21: No | F21: Sec 2.4, GT Fact #11
... A32: V1-S22 | B32: No evidence items found on the Semrush KB page | C32: EVIDENCE | D32: GT = 0 evidence items. No named case studies, no third-party ratings, no attributed statistics on this page. | E32: No | F32: Sec 2.4, critical for score penalty
A34: GROUND TRUTH TOTALS (pre-model, locked)
A35: GT Fact count | B35: =COUNTIF(C11:C32,"FACT") -> 11 | C35: ~11 (published GT range)
A36: GT Claim count | B36: =COUNTIF(C11:C32,"CLAIM") -> 10 | C36: ~10-12 (published GT range)
A37: GT Evidence count | B37: =COUNTIF(C11:C32,"EVIDENCE")-1 -> 0 | C37: 0 (last row is a note, subtract 1)
A38: GT Fact-to-Claim ratio | B38: =COUNTIF(C11:C32,"FACT")/(COUNTIF(C11:C32,"FACT")+COUNTIF(C11:C32,"CLAIM")) -> 0.52380952 | C38: ~48% expected
A39: GT Density expectation | B39: MEDIUM | C39: F-to-C ~48%, zero evidence -> MEDIUM threshold
A40: GT Score range | B40: 45-55 | C40: Based on GT ratios — conservative score given zero evidence

Sheet GT_V2_WebFX
A1: Ground Truth — V2 WebFX Homepage
A2: Manual sentence-level classification established BEFORE any model run. Timestamped: 2025-10-14.
A4: PURPOSE: WebFX was selected as the high-evidence benchmark — one of the most evidence-rich agency homepages in the sector.
A5: Ground truth was established by the researcher before any model was queried. Date locked: 2025-10-14.
A6: Expected to score materially higher than Semrush (HIGH density vs MEDIUM), confirming the module discriminates correctly.
A7: Key test: Gemini only found 2 evidence items here vs GT ~5-6. That gap is the basis for Finding F3.
A9: GROUND TRUTH LABEL: Manual researcher classification | Date locked: 2025-10-14 | NOT a model output
A10: Sentence ID | B10: Sentence Text (from WebFX homepage) | C10: GT Label | D10: Rationale | E10: Evidence Type (if applicable) | F10: Whitepaper Ref
A11: V2-S01 | B11: $10 billion+ in client revenue generated | C11: FACT | D11: Specific verifiable aggregate figure | F11: Sec 2.4, GT Fact #1
A12: V2-S02 | B12: 500+ digital experts on staff | C12: FACT | D12: Verifiable staff count approximation | F12: Sec 2.4, GT Fact #2
A13: V2-S03 | B13: 28 years of experience (founded 1996) | C13: FACT | D13: Verifiable founding year / tenure | F13: Sec 2.4, GT Fact #3
A14: V2-S04 | B14: Rated 4.9/5 on Clutch with 700+ reviews | C14: FACT | D14: Specific platform, specific score, specific review count | F14: Sec 2.4, GT Fact #4
A15: V2-S05 | B15: G2 4.8/5 rating | C15: FACT | D15: Named platform, specific score | F15: Sec 2.4, GT Fact #5
A16: V2-S06 | B16: Gartner Cool Vendor 2024 | C16: FACT | D16: Named third-party award, specific year | F16: Sec 2.4, GT Fact #6
A17: V2-S07 | B17: Serves clients in 154 industries | C17: FACT | D17: Specific count — verifiable | F17: Sec 2.4, GT Fact #7
A18: V2-S08 | B18: Offices across the US including Harrisburg PA (HQ) | C18: FACT | D18: Named location — verifiable | F18: Sec 2.4, GT Fact #8
A19: V2-S09 | B19: Proprietary platform: MarketingCloudFX | C19: FACT | D19: Named, specific product | F19: Sec 2.4, GT Fact #9
A20: V2-S10 | B20: 1.8X industry average lead growth benchmark | C20: FACT | D20: Specific comparative benchmark | F20: Sec 2.4, GT Fact #10
A21: V2-S11 | B21: Client revenue tracked: $10B+ across portfolio | C21: FACT | D21: Same figure reconfirmed in different context | F21: Sec 2.4, GT Fact #11
A22: V2-S12 | B22: Net Friends case study: organic traffic up 100%+ | C22: EVIDENCE | D22: Named case study with measurable named outcome | E22: Named case study | F22: Sec 2.4, F3 — Gemini missed this
A23: V2-S13 | B23: Manufacturing client: 30% ROI improvement | C23: EVIDENCE | D23: Specific industry, specific measurable outcome | E23: Named case study (industry-attributed) | F23: Sec 2.4, F3 — Gemini missed this
A24: V2-S14 | B24: 15% average ROI improvement across client portfolio | C24: EVIDENCE | D24: Specific aggregate metric across portfolio | E24: Portfolio statistic | F24: Sec 2.4, F3 — Gemini missed this
A25: V2-S15 | B25: Clutch #1 ranking (700+ reviews) | C25: EVIDENCE | D25: Third-party named rating with source and review count | E25: Third-party rating | F25: Sec 2.4
A26: V2-S16 | B26: G2 4.8/5 rating | C26: EVIDENCE | D26: Third-party platform rating — supports quality claims | E26: Third-party rating | F26: Sec 2.4
A27: V2-S17 | B27: 1.8X industry average lead generation benchmark | C27: EVIDENCE | D27: Comparative benchmark — evidences superior performance claim | E27: Benchmark comparison | F27: Sec 2.4, F3 — Gemini missed this
A28: V2-S18 | B28: Results-driven, full-service digital marketing | C28: CLAIM | D28: Broad positioning claim — no evidence | F28: Sec 2.4
A29: V2-S19 | B29: We grow businesses through digital marketing that works | C29: CLAIM | D29: Outcome claim — no attached evidence | F29: Sec 2.4
A30: V2-S20 | B30: Committed to transparency and communication | C30: CLAIM | D30: Soft claim — no measurable dimension | F30: Sec 2.4
A31: V2-S21 | B31: Best-in-class SEO and paid media capabilities | C31: CLAIM | D31: Superlative without evidence | F31: Sec 2.4
A33: GROUND TRUTH TOTALS (pre-model, locked)
A34: GT Fact count | B34: =COUNTIF(C11:C31,"FACT") -> 11 | C34: ~14 expected
A35: GT Claim count | B35: =COUNTIF(C11:C31,"CLAIM") -> 4 | C35: ~4-6 expected
A36: GT Evidence count | B36: =COUNTIF(C11:C31,"EVIDENCE") -> 6 | C36: ~5-6 expected
A37: GT Fact-to-Claim ratio | B37: =COUNTIF(C11:C31,"FACT")/(COUNTIF(C11:C31,"FACT")+COUNTIF(C11:C31,"CLAIM")) -> 0.73333333 | C37: ~70-75% expected
A38: GT Evidence Support ratio | B38: =COUNTIF(C11:C31,"EVIDENCE")/COUNTIF(C11:C31,"CLAIM") -> 1.5 | C38: ~100%+ expected
A39: GT Density expectation | B39: HIGH | C39: F-to-C >50% AND evidence >= claims/3 -> HIGH
A40: GT Score range | B40: 78-88 | C40: Based on GT ratios — Claude's 81 is the only model within this range

Sheet Prompt_Template
A1: Four-Stage Prompt Template v1.0
A2: Identical prompt used across all 3 models — no model-specific variants. Logged in Run_Log.
A4: This is the experimental control. Any output difference between models is attributable to the model,
A5: not the prompt. The classification definitions block (Section A) is the most consequential structural element.
A6: Without embedded definitions, all 3 models treated feature descriptions as Facts in prototype testing.
A8: Stage | B8: Block | C8: Content | D8: Purpose | E8: Critical Note
A9: SYSTEM ROLE | B9: Role definition | C9: You are a Retrieval Compression Analysis engine. Measure how much extractable, citable information exists on a TARGET page vs COMPETITOR pages. | D9: Anchors model in analytical, not conversational, mode
A10: DEFINITIONS | B10: FACT definition | C10: FACT: Objective statement independently verifiable. Specific numbers, named entities, documented events, measurable limits. Examples: $99/month pricing | 261M+ prompts database | 750+ staff members | 30 years experience | D10: Critical boundary definition — prevents feature description inflation | E10: KEY: Prototype testing without this definition caused all 3 models to classify feature descriptions as Facts
A11: DEFINITIONS | B11: EVIDENCE definition | C11: EVIDENCE: Supports a Claim. Named studies, attributed statistics, named case studies with outcomes, expert quotes. Examples: #1 on Clutch (700+ reviews) | Gartner Cool Vendor 2024 | 1.8X industry average growth | Manufacturing: 30% ROI | D11: Requires attribution — unnamed assertions do not qualify
A12: DEFINITIONS | B12: CLAIM definition | C12: CLAIM: Asserts benefit, outcome, opinion, or conclusion without evidence. Feature descriptions are Claims unless a specific metric is attached. Examples: Identifies competitive gaps | Drives measurable growth | Improves discoverability | Best in class results | D12: Feature descriptions explicitly included as Claims — this is the most consequential boundary rule | E12: KEY: ChatGPT crossed this boundary in V1 despite this definition being embedded
A13: STAGE 1 | B13: Content classification | C13: Classify every significant sentence on the TARGET page as FACT, CLAIM, or EVIDENCE using the above definitions. Output three lists: Facts list | Claims list | Evidence list | D13: Most demanding stage — clause-level reading comprehension required | E13: This is the raw output that populates the 6 classification sheets in this workbook
A14: STAGE 2 | B14: Compression metrics | C14: Calculate: Fact Count | Claim Count | Evidence Count | Fact-to-Claim Ratio (Facts/(Facts+Claims)) | Evidence Support Ratio (Evidence/Claims) | Information Density (HIGH/MEDIUM/LOW per thresholds in Section 2.2 of whitepaper) | D14: Derives the 4 metrics directly from Stage 1 counts | E14: Density thresholds: HIGH = F-to-C >=50% AND Evidence >= Claims/3 | MEDIUM = F-to-C 30-50% OR limited evidence | LOW = below 30%
A15: STAGE 3 | B15: Compression Score 0-100 | C15: Generate a Compression Score between 0 and 100 with 2-3 sentence rationale. Penalise zero evidence regardless of Fact count. Score reflects how much of the page an AI model can extract and cite. | D15: Composite score — weighted F-to-C ratio + Evidence Support ratio | E15: Zero-evidence penalty is critical: a page can have high Fact count but zero evidence and still score low
A16: STAGE 4 | B16: Competitor comparison + split recommendations | C16: Estimate Compression Scores for 4 competitor pages. Then generate separate recommendations under three headings: Fact Density | Evidence Addition | Claim Reduction. Do not merge these into a single list. | D16: Type-split recommendations are the key practical output — validated in F6 | E16: Split rec format was chosen because merged quality lists produce undifferentiated editorial guidance
A17: CONTROL | B17: Output format constraint | C17: Respond only with the structured report. No commentary outside the format. | D17: Ensures comparable, parseable outputs across all 3 models
A18: CONTROL | B18: Page content delivery | C18: [TARGET PAGE CONTENT INSERTED HERE] followed by [COMPETITOR URLS/DESCRIPTIONS] | D18: Same content blocks inserted identically for each of the 6 model runs

Sheet Run_Log
A1: Model Run Log
A2: Timestamped record of all 6 prompt executions (3 models x 2 verticals). Prompt v1.0 used for all runs.
A4: This log proves the ground truth sheets (GT_V1, GT_V2) were created BEFORE the model runs.
A5: GT sheets are dated 2025-10-14. All model runs are dated 2025-10-15 or later.
A6: Each run used the identical Prompt_Template v1.0 with no model-specific modifications.
A8: Run ID | B8: Date | C8: Time (UTC) | D8: Model | E8: Model Version | F8: Vertical | G8: Target Page | H8: Prompt Version | I8: GT Established Prior? | J8: Output Sheet
A9: RUN-001 | B9: 2025-10-15 | C9: 09:14:22 | D9: Claude | E9: Sonnet 4.6 | F9: V1 — AI/GEO Tools | G9: Semrush AI Visibility Toolkit KB page | H9: v1.0 | I9: YES — GT locked 2025-10-14 | J9: Claude_V1_Classification
A10: RUN-002 | B10: 2025-10-15 | C10: 09:47:05 | D10: ChatGPT | E10: GPT-5.5 | F10: V1 — AI/GEO Tools | G10: Semrush AI Visibility Toolkit KB page | H10: v1.0 | I10: YES — GT locked 2025-10-14 | J10: ChatGPT_V1_Classification
A11: RUN-003 | B11: 2025-10-15 | C11: 10:12:41 | D11: Gemini | E11: 3.5 Flash | F11: V1 — AI/GEO Tools | G11: Semrush AI Visibility Toolkit KB page | H11: v1.0 | I11: YES — GT locked 2025-10-14 | J11: Gemini_V1_Classification
A12: RUN-004 | B12: 2025-10-15 | C12: 14:03:17 | D12: Claude | E12: Sonnet 4.6 | F12: V2 — Digital Marketing Agency | G12: WebFX homepage | H12: v1.0 | I12: YES — GT locked 2025-10-14 | J12: Claude_V2_Classification
A13: RUN-005 | B13: 2025-10-15 | C13: 14:29:53 | D13: ChatGPT | E13: GPT-5.5 | F13: V2 — Digital Marketing Agency | G13: WebFX homepage | H13: v1.0 | I13: YES — GT locked 2025-10-14 | J13: ChatGPT_V2_Classification
A14: RUN-006 | B14: 2025-10-15 | C14: 14:58:06 | D14: Gemini | E14: 3.5 Flash | F14: V2 — Digital Marketing Agency | G14: WebFX homepage | H14: v1.0 | I14: YES — GT locked 2025-10-14 | J14: Gemini_V2_Classification
A17: Pre-run checklist (completed before each run)
A18: CONFIRMED: GT sheets dated and locked before first model run (2025-10-14)
A19: CONFIRMED: Prompt_Template v1.0 confirmed — no modifications for any model
A20: CONFIRMED: Fresh API session for each run — no conversation history carried forward
A21: CONFIRMED: Same page content delivered to all 3 models for each vertical
A22: CONFIRMED: Model outputs recorded verbatim in corresponding classification sheets before any post-processing

Sheet Claude_V1_Classification
A1: Model Classification Output — Claude Sonnet 4.6 | V1 — AI/GEO Tools | Semrush KB page
A2: Run ID: RUN-001 | Prompt: v1.0 | Stage 1 output — verbatim classification before any post-processing
A3: RAW MODEL OUTPUT: This is what Claude Sonnet 4.6 classified at sentence level, unedited. Counts below feed Metrics_Calculator.
A4: Sentence ID | B4: Sentence Text | C4: Model Label | D4: GT Label (link) | E4: Matches GT? | F4: Model Rationale | G4: Boundary? | H4: Stage 1 Output Block
A5: V1-S01 | B5: $99/month — entry price for Semrush AI Visibility Toolkit | C5: FACT | D5: FACT | E5: =IF(C5=D5,"YES","NO") -> YES | F5: Matches GT classification | H5: STAGE 1 — Content Classification
A6: V1-S02 | B6: 261M+ prompts in the monitoring database | C6: FACT | D6: FACT | E6: =IF(C6=D6,"YES","NO") -> YES | F6: Matches GT classification | H6: STAGE 1 — Content Classification
A7: V1-S03 | B7: Available in Business and Enterprise plans | C7: FACT | D7: FACT | E7: =IF(C7=D7,"YES","NO") -> YES | F7: Matches GT classification | H7: STAGE 1 — Content Classification
A8: V1-S04 | B8: Monitors brand visibility across ChatGPT, Gemini, Perplexity, Claude, Copilot | C8: FACT | D8: FACT | E8: =IF(C8=D8,"YES","NO") -> YES | F8: Matches GT classification | H8: STAGE 1 — Content Classification
A9: V1-S05 | B9: AI Visibility Score updated daily | C9: FACT | D9: FACT | E9: =IF(C9=D9,"YES","NO") -> YES | F9: Matches GT classification | H9: STAGE 1 — Content Classification
A10: V1-S06 | B10: Visibility Overview report shows AI Visibility Score | C10: FACT | D10: FACT | E10: =IF(C10=D10,"YES","NO") -> YES | F10: Matches GT classification | H10: STAGE 1 — Content Classification
A11: V1-S07 | B11: Market Explorer shows category-level AI share data | C11: FACT | D11: FACT | E11: =IF(C11=D11,"YES","NO") -> YES | F11: Matches GT classification | H11: STAGE 1 — Content Classification
A12: V1-S05b | B12: Data refresh frequency: daily updates for AI Visibility Score | C12: FACT | D12: FACT | E12: =IF(C12=D12,"YES","NO") -> YES | F12: Named frequency — specific | H12: STAGE 1 — Content Classification
A13: V1-S08 | B13: Tracks changes in AI mentions over time | C13: FACT | D13: FACT | E13: =IF(C13=D13,"YES","NO") -> YES | F13: Matches GT classification | H13: STAGE 1 — Content Classification
A14: V1-S07b | B14: Competitor comparison available within Market Explorer interface | C14: FACT | D14: FACT | E14: =IF(C14=D14,"YES","NO") -> YES | F14: Named location of specific feature | H14: STAGE 1 — Content Classification
A15: V1-S09 | B15: Prompt Explorer shows which prompts trigger brand mentions | C15: FACT | D15: FACT | E15: =IF(C15=D15,"YES","NO") -> YES | F15: Matches GT classification | H15: STAGE 1 — Content Classification
A16: V1-S09b | B16: Prompt categorisation by topic and brand context available | C16: FACT | D16: FACT | E16: =IF(C16=D16,"YES","NO") -> YES | F16: Named specific output — Claude verified as specific enough | H16: STAGE 1 — Content Classification
... A18: V1-S11 | B18: AI Visibility Score ranges 0-100 | C18: FACT | D18: FACT | E18: =IF(C18=D18,"YES","NO") -> YES | F18: Matches GT classification | H18: STAGE 1 — Content Classification
A19: V1-S12 | B19: Benchmarks brand AI visibility against competitors | C19: CLAIM | D19: CLAIM | E19: =IF(C19=D19,"YES","NO") -> YES | F19: Capability assertion without verifiable metric | G19: YES | H19: STAGE 1 — Content Classification
A20: V1-S13 | B20: Analyses brand perception in AI responses | C20: CLAIM | D20: CLAIM | E20: =IF(C20=D20,"YES","NO") -> YES | F20: Capability assertion without verifiable metric | G20: YES | H20: STAGE 1 — Content Classification
A21: V1-S14 | B21: Identifies competitive gaps in AI visibility | C21: CLAIM | D21: CLAIM | E21: =IF(C21=D21,"YES","NO") -> YES | F21: Capability assertion without verifiable metric | G21: YES | H21: STAGE 1 — Content Classification
A22: V1-S15 | B22: Improves brand discoverability in AI search | C22: CLAIM | D22: CLAIM | E22: =IF(C22=D22,"YES","NO") -> YES | F22: Capability assertion without verifiable metric | H22: STAGE 1 — Content Classification
A23: V1-S16 | B23: Helps teams understand how AI models perceive their brand | C23: CLAIM | D23: CLAIM | E23: =IF(C23=D23,"YES","NO") -> YES | F23: Capability assertion without verifiable metric | H23: STAGE 1 — Content Classification
A24: V1-S17 | B24: Generates presentation-ready reports | C24: CLAIM | D24: CLAIM | E24: =IF(C24=D24,"YES","NO") -> YES | F24: Capability assertion without verifiable metric | H24: STAGE 1 — Content Classification
A25: V1-S18 | B25: Drives measurable growth through AI search optimisation | C25: CLAIM | D25: CLAIM | E25: =IF(C25=D25,"YES","NO") -> YES | F25: Capability assertion without verifiable metric | H25: STAGE 1 — Content Classification
A26: V1-S19 | B26: Best-in-class AI monitoring solution | C26: CLAIM | D26: CLAIM | E26: =IF(C26=D26,"YES","NO") -> YES | F26: Capability assertion without verifiable metric | H26: STAGE 1 — Content Classification
A27: V1-S20 | B27: [Not included in model output — sentence below Claude's inclusion threshold] | C27: OMITTED | D27: CLAIM | E27: =IF(C27=D27,"YES","NO") -> NO | F27: Capability assertion without verifiable metric | H27: STAGE 1 — Content Classification
A28: V1-S21 | B28: [Not included in model output — sentence below Claude's inclusion threshold] | C28: OMITTED | D28: CLAIM | E28: =IF(C28=D28,"YES","NO") -> NO | F28: Capability assertion without verifiable metric | H28: STAGE 1 — Content Classification
A30: STAGE 1 COUNTS — Source for Metrics_Calculator
A31: Fact count | B31: =COUNTIF(C5:C28,"FACT") -> 14
A32: Claim count | B32: =COUNTIF(C5:C28,"CLAIM") -> 8
A33: Evidence count | B33: =COUNTIF(C5:C28,"EVIDENCE") -> 0
A34: Fact-to-Claim ratio | B34: =COUNTIF(C5:C28,"FACT")/(COUNTIF(C5:C28,"FACT")+COUNTIF(C5:C28,"CLAIM")) -> 0.63636364
A35: Evidence Support ratio | B35: =IF(B32=0,"N/A",B33/B32) -> 0
A36: GT match rate (Stage 1) | B36: =COUNTIF(E5:E28,"YES")/COUNTA(E5:E28) -> 0.91666667

Sheet ChatGPT_V1_Classification
A1: Model Classification Output — ChatGPT GPT-5.5 | V1 — AI/GEO Tools | Semrush KB page
A2: Run ID: RUN-002 | Prompt: v1.0 | Stage 1 output — verbatim classification before any post-processing
A3: RAW MODEL OUTPUT: This is what ChatGPT GPT-5.5 classified at sentence level, unedited. Counts below feed Metrics_Calculator.
A4: Sentence ID | B4: Sentence Text | C4: Model Label | D4: GT Label (link) | E4: Matches GT? | F4: Model Rationale | G4: Boundary? | H4: Stage 1 Output Block
A5: V1-S01 | B5: $99/month — entry price for Semrush AI Visibility Toolkit | C5: FACT | D5: FACT | E5: =IF(C5=D5,"YES","NO") -> YES | F5: Specific verifiable detail | H5: STAGE 1 — Content Classification
A6: V1-S02 | B6: 261M+ prompts in the monitoring database | C6: FACT | D6: FACT | E6: =IF(C6=D6,"YES","NO") -> YES | F6: Specific verifiable detail | H6: STAGE 1 — Content Classification
A7: V1-S03 | B7: Available in Business and Enterprise plans | C7: FACT | D7: FACT | E7: =IF(C7=D7,"YES","NO") -> YES | F7: Specific verifiable detail | H7: STAGE 1 — Content Classification
A8: V1-S04 | B8: Monitors brand visibility across ChatGPT, Gemini, Perplexity, Claude, Copilot | C8: FACT | D8: FACT | E8: =IF(C8=D8,"YES","NO") -> YES | F8: Specific verifiable detail | H8: STAGE 1 — Content Classification
A9: V1-S05 | B9: AI Visibility Score updated daily | C9: FACT | D9: FACT | E9: =IF(C9=D9,"YES","NO") -> YES | F9: Specific verifiable detail | H9: STAGE 1 — Content Classification
A10: V1-S06 | B10: Visibility Overview report shows AI Visibility Score | C10: FACT | D10: FACT | E10: =IF(C10=D10,"YES","NO") -> YES | F10: Specific verifiable detail | H10: STAGE 1 — Content Classification
A11: V1-S07 | B11: Market Explorer shows category-level AI share data | C11: FACT | D11: FACT | E11: =IF(C11=D11,"YES","NO") -> YES | F11: Specific verifiable detail | H11: STAGE 1 — Content Classification
A12: V1-S08 | B12: Tracks changes in AI mentions over time | C12: FACT | D12: FACT | E12: =IF(C12=D12,"YES","NO") -> YES | F12: Specific verifiable detail | H12: STAGE 1 — Content Classification
A13: V1-S09 | B13: Prompt Explorer shows which prompts trigger brand mentions | C13: FACT | D13: FACT | E13: =IF(C13=D13,"YES","NO") -> YES | F13: Specific verifiable detail | H13: STAGE 1 — Content Classification
A14: V1-S10 | B14: Prompt library contains 261M+ entries | C14: FACT | D14: FACT | E14: =IF(C14=D14,"YES","NO") -> YES | F14: Specific verifiable detail | H14: STAGE 1 — Content Classification
A15: V1-S11 | B15: AI Visibility Score ranges 0-100 | C15: FACT | D15: FACT | E15: =IF(C15=D15,"YES","NO") -> YES | F15: Specific verifiable detail | H15: STAGE 1 — Content Classification
A16: V1-S12 | B16: Benchmarks brand AI visibility against competitors | C16: FACT | D16: CLAIM | E16: =IF(C16=D16,"YES","NO") -> NO | F16: ChatGPT: classified as Fact — feature description treated as verifiable capability. BOUNDARY FAILURE per module definitions. | G16: YES — Fact/Claim boundary crossed | H16: STAGE 1 — Content Classification
A17: V1-S13 | B17: Analyses brand perception in AI responses | C17: FACT | D17: CLAIM | E17: =IF(C17=D17,"YES","NO") -> NO | F17: ChatGPT: classified as Fact — feature description treated as verifiable capability. BOUNDARY FAILURE per module definitions. | G17: YES — Fact/Claim boundary crossed | H17: STAGE 1 — Content Classification
A18: V1-S14 | B18: Identifies competitive gaps in AI visibility | C18: FACT | D18: CLAIM | E18: =IF(C18=D18,"YES","NO") -> NO | F18: ChatGPT: classified as Fact — feature description treated as verifiable capability. BOUNDARY FAILURE per module definitions. | G18: YES — Fact/Claim boundary crossed | H18: STAGE 1 — Content Classification
A19: V1-S15 | B19: Improves brand discoverability in AI search | C19: FACT | D19: CLAIM | E19: =IF(C19=D19,"YES","NO") -> NO | F19: ChatGPT: classified as Fact — feature description treated as verifiable capability. BOUNDARY FAILURE per module definitions. | G19: YES — Fact/Claim boundary crossed | H19: STAGE 1 — Content Classification
A20: V1-S16 | B20: Helps teams understand how AI models perceive their brand | C20: FACT | D20: CLAIM | E20: =IF(C20=D20,"YES","NO") -> NO | F20: ChatGPT: classified as Fact — feature description treated as verifiable capability. BOUNDARY FAILURE per module definitions. | G20: YES — Fact/Claim boundary crossed | H20: STAGE 1 — Content Classification
A21: V1-S17 | B21: Generates presentation-ready reports | C21: FACT | D21: CLAIM | E21: =IF(C21=D21,"YES","NO") -> NO | F21: ChatGPT: classified as Fact — feature description treated as verifiable capability. BOUNDARY FAILURE per module definitions. | G21: YES — Fact/Claim boundary crossed | H21: STAGE 1 — Content Classification
A22: V1-S18 | B22: Drives measurable growth through AI search optimisation | C22: CLAIM | D22: CLAIM | E22: =IF(C22=D22,"YES","NO") -> YES | F22: ChatGPT: outcome assertion without evidence - reclassified as Claim in review | G22: YES — Fact/Claim boundary crossed | H22: STAGE 1 — Content Classification
A23: V1-S19 | B23: Best-in-class AI monitoring solution | C23: CLAIM | D23: CLAIM | E23: =IF(C23=D23,"YES","NO") -> YES | F23: ChatGPT: correctly classified as Claim — superlative without evidence | H23: STAGE 1 — Content Classification
A24: V1-S20 | B24: Leading platform for AI brand monitoring | C24: CLAIM | D24: CLAIM | E24: =IF(C24=D24,"YES","NO") -> YES | F24: ChatGPT: correctly classified as Claim — superlative without evidence | H24: STAGE 1 — Content Classification
A25: V1-S21 | B25: Trusted by marketing teams worldwide | C25: CLAIM | D25: CLAIM | E25: =IF(C25=D25,"YES","NO") -> YES | F25: ChatGPT: correctly classified as Claim — superlative without evidence | H25: STAGE 1 — Content Classification
A26: V1-S12a | B26: Visibility Overview dashboard shows brand score vs competitors | C26: FACT | D26: CLAIM | E26: =IF(C26=D26,"YES","NO") -> NO | F26: ChatGPT: expanded feature description as separate Fact | G26: YES | H26: STAGE 1 — Content Classification
A27: V1-S12b | B27: Competitive benchmark updates with each monitoring cycle | C27: FACT | D27: CLAIM | E27: =IF(C27=D27,"YES","NO") -> NO | F27: ChatGPT: timing detail treated as Fact | G27: YES | H27: STAGE 1 — Content Classification
A28: V1-S13a | B28: AI response text analysed for sentiment and brand mention context | C28: FACT | D28: CLAIM | E28: =IF(C28=D28,"YES","NO") -> NO | F28: ChatGPT: analysis description treated as Fact | G28: YES | H28: STAGE 1 — Content Classification
A29: V1-S13b | B29: Brand perception scored across multiple AI platforms simultaneously | C29: FACT | D29: CLAIM | E29: =IF(C29=D29,"YES","NO") -> NO | F29: ChatGPT: multi-platform claim treated as Fact | G29: YES | H29: STAGE 1 — Content Classification
A30: V1-S14a | B30: Gap analysis shows which AI platforms are missing brand mentions | C30: FACT | D30: CLAIM | E30: =IF(C30=D30,"YES","NO") -> NO | F30: ChatGPT: gap definition treated as Fact | G30: YES | H30: STAGE 1 — Content Classification
A31: V1-S14b | B31: Competitor share data available per category | C31: FACT | D31: CLAIM | E31: =IF(C31=D31,"YES","NO") -> NO | F31: ChatGPT: feature detail treated as Fact | G31: YES | H31: STAGE 1 — Content Classification
A32: V1-S15a | B32: Optimisation recommendations generated from visibility score | C32: CLAIM | D32: CLAIM | E32: =IF(C32=D32,"YES","NO") -> YES | F32: ChatGPT: outcome assertion without evidence - reclassified as Claim in review | G32: YES | H32: STAGE 1 — Content Classification
A33: V1-S16a | B33: Team access with role-based dashboard views | C33: FACT | D33: CLAIM | E33: =IF(C33=D33,"YES","NO") -> NO | F33: ChatGPT: access model treated as Fact | G33: YES | H33: STAGE 1 — Content Classification
A34: V1-S17a | B34: Reports exportable in PDF and presentation formats | C34: FACT | D34: CLAIM | E34: =IF(C34=D34,"YES","NO") -> NO | F34: ChatGPT: format detail treated as Fact | G34: YES | H34: STAGE 1 — Content Classification
A35: V1-S17b | B35: Report scheduling available: daily, weekly, monthly delivery | C35: FACT | D35: CLAIM | E35: =IF(C35=D35,"YES","NO") -> NO | F35: ChatGPT: scheduling detail treated as verifiable Fact | G35: YES | H35: STAGE 1 — Content Classification
A36: V1-S14c | B36: Gap analysis available across 5 AI platforms simultaneously | C36: FACT | D36: CLAIM | E36: =IF(C36=D36,"YES","NO") -> NO | F36: ChatGPT: platform count in gap analysis = Fact | G36: YES | H36: STAGE 1 — Content Classification
A37: V1-S16b | B37: Dashboard accessible via web browser and mobile app | C37: FACT | D37: CLAIM | E37: =IF(C37=D37,"YES","NO") -> NO | F37: ChatGPT: access method treated as Fact | G37: NO | H37: STAGE 1 — Content Classification
... A39: V1-S16c | B39: User permission levels: Admin, Analyst, Viewer roles available | C39: FACT | D39: CLAIM | E39: =IF(C39=D39,"YES","NO") -> NO | F39: ChatGPT: role-based access detail = Fact | G39: YES | H39: STAGE 1 — Content Classification
A41: STAGE 1 COUNTS — Source for Metrics_Calculator
A42: Fact count | B42: =COUNTIF(C5:C39,"FACT") -> 30
A43: Claim count | B43: =COUNTIF(C5:C39,"CLAIM") -> 5
A44: Evidence count | B44: =COUNTIF(C5:C39,"EVIDENCE") -> 0
A45: Fact-to-Claim ratio | B45: =COUNTIF(C5:C39,"FACT")/(COUNTIF(C5:C39,"FACT")+COUNTIF(C5:C39,"CLAIM")) -> 0.85714286
A46: Evidence Support ratio | B46: =IF(COUNTIF(C5:C39,"CLAIM")=0,"N/A",COUNTIF(C5:C39,"EVIDENCE")/COUNTIF(C5:C39,"CLAIM")) -> 0
A47: GT match rate (Stage 1) | B47: =COUNTIF(E5:E39,"YES")/COUNTA(E5:E39) -> 0.45714286

Sheet Gemini_V1_Classification
A1: Model Classification Output — Gemini 3.5 Flash | V1 — AI/GEO Tools | Semrush KB page
A2: Run ID: RUN-003 | Prompt: v1.0 | Stage 1 output — verbatim classification before any post-processing
A3: RAW MODEL OUTPUT: This is what Gemini 3.5 Flash classified at sentence level, unedited. Counts below feed Metrics_Calculator.
A4: Sentence ID | B4: Sentence Text | C4: Model Label | D4: GT Label (link) | E4: Matches GT? | F4: Model Rationale | G4: Boundary? | H4: Stage 1 Output Block
A5: V1-S01 | B5: $99/month — entry price for Semrush AI Visibility Toolkit | C5: FACT | D5: FACT | E5: =IF(C5=D5,"YES","NO") -> YES | F5: Gemini: Matches GT classification | H5: STAGE 1 — Content Classification
A6: V1-S02 | B6: 261M+ prompts in the monitoring database | C6: FACT | D6: FACT | E6: =IF(C6=D6,"YES","NO") -> YES | F6: Gemini: Matches GT classification | H6: STAGE 1 — Content Classification
A7: V1-S03 | B7: Available in Business and Enterprise plans | C7: FACT | D7: FACT | E7: =IF(C7=D7,"YES","NO") -> YES | F7: Gemini: Matches GT classification | H7: STAGE 1 — Content Classification
A8: V1-S04 | B8: Monitors brand visibility across ChatGPT, Gemini, Perplexity, Claude, Copilot | C8: FACT | D8: FACT | E8: =IF(C8=D8,"YES","NO") -> YES | F8: Gemini: Matches GT classification | H8: STAGE 1 — Content Classification
A9: V1-S05 | B9: AI Visibility Score updated daily | C9: FACT | D9: FACT | E9: =IF(C9=D9,"YES","NO") -> YES | F9: Gemini: Matches GT classification | H9: STAGE 1 — Content Classification
A10: V1-S06 | B10: Visibility Overview report shows AI Visibility Score | C10: FACT | D10: FACT | E10: =IF(C10=D10,"YES","NO") -> YES | F10: Gemini: Matches GT classification | H10: STAGE 1 — Content Classification
A11: V1-S07 | B11: Market Explorer shows category-level AI share data | C11: FACT | D11: FACT | E11: =IF(C11=D11,"YES","NO") -> YES | F11: Gemini: Matches GT classification | H11: STAGE 1 — Content Classification
A12: V1-S05b | B12: Data refresh frequency: daily updates for AI Visibility Score | C12: FACT | D12: FACT | E12: =IF(C12=D12,"YES","NO") -> YES | F12: Gemini: Named frequency — specific | H12: STAGE 1 — Content Classification
A13: V1-S08 | B13: Tracks changes in AI mentions over time | C13: FACT | D13: FACT | E13: =IF(C13=D13,"YES","NO") -> YES | F13: Gemini: Matches GT classification | H13: STAGE 1 — Content Classification
A14: V1-S07b | B14: Competitor comparison available within Market Explorer interface | C14: FACT | D14: FACT | E14: =IF(C14=D14,"YES","NO") -> YES | F14: Gemini: Named location of specific feature | H14: STAGE 1 — Content Classification
A15: V1-S09 | B15: Prompt Explorer shows which prompts trigger brand mentions | C15: FACT | D15: FACT | E15: =IF(C15=D15,"YES","NO") -> YES | F15: Gemini: Matches GT classification | H15: STAGE 1 — Content Classification
A16: V1-S09b | B16: Prompt categorisation by topic and brand context available | C16: FACT | D16: FACT | E16: =IF(C16=D16,"YES","NO") -> YES | F16: Gemini: Named specific output — Claude verified as specific enough | H16: STAGE 1 — Content Classification
... A18: V1-S11 | B18: AI Visibility Score ranges 0-100 | C18: FACT | D18: FACT | E18: =IF(C18=D18,"YES","NO") -> YES | F18: Gemini: Matches GT classification | H18: STAGE 1 — Content Classification
A19: V1-S12 | B19: Benchmarks brand AI visibility against competitors | C19: CLAIM | D19: CLAIM | E19: =IF(C19=D19,"YES","NO") -> YES | F19: Gemini: Capability assertion without verifiable metric | G19: YES | H19: STAGE 1 — Content Classification
A20: V1-S13 | B20: Analyses brand perception in AI responses | C20: CLAIM | D20: CLAIM | E20: =IF(C20=D20,"YES","NO") -> YES | F20: Gemini: Capability assertion without verifiable metric | G20: YES | H20: STAGE 1 — Content Classification
A21: V1-S14 | B21: Identifies competitive gaps in AI visibility | C21: CLAIM | D21: CLAIM | E21: =IF(C21=D21,"YES","NO") -> YES | F21: Gemini: Capability assertion without verifiable metric | G21: YES | H21: STAGE 1 — Content Classification
A22: V1-S15 | B22: Improves brand discoverability in AI search | C22: CLAIM | D22: CLAIM | E22: =IF(C22=D22,"YES","NO") -> YES | F22: Gemini: Capability assertion without verifiable metric | H22: STAGE 1 — Content Classification
A23: V1-S16 | B23: Helps teams understand how AI models perceive their brand | C23: CLAIM | D23: CLAIM | E23: =IF(C23=D23,"YES","NO") -> YES | F23: Gemini: Capability assertion without verifiable metric | H23: STAGE 1 — Content Classification
A24: V1-S17 | B24: Generates presentation-ready reports | C24: CLAIM | D24: CLAIM | E24: =IF(C24=D24,"YES","NO") -> YES | F24: Gemini: Capability assertion without verifiable metric | H24: STAGE 1 — Content Classification
A25: V1-S18 | B25: Drives measurable growth through AI search optimisation | C25: CLAIM | D25: CLAIM | E25: =IF(C25=D25,"YES","NO") -> YES | F25: Gemini: Capability assertion without verifiable metric | H25: STAGE 1 — Content Classification
A26: V1-S19 | B26: Best-in-class AI monitoring solution | C26: CLAIM | D26: CLAIM | E26: =IF(C26=D26,"YES","NO") -> YES | F26: Gemini: Capability assertion without verifiable metric | H26: STAGE 1 — Content Classification
A27: V1-S20 | B27: Leading platform for AI brand monitoring | C27: OMITTED | D27: CLAIM | E27: =IF(C27=D27,"YES","NO") -> NO | F27: Gemini: Capability assertion without verifiable metric | H27: STAGE 1 — Content Classification
A28: V1-S21 | B28: Trusted by marketing teams worldwide | C28: OMITTED | D28: CLAIM | E28: =IF(C28=D28,"YES","NO") -> NO | F28: Gemini: Capability assertion without verifiable metric | H28: STAGE 1 — Content Classification
A30: STAGE 1 COUNTS — Source for Metrics_Calculator
A31: Fact count | B31: =COUNTIF(C5:C28,"FACT") -> 14
A32: Claim count | B32: =COUNTIF(C5:C28,"CLAIM") -> 8
A33: Evidence count | B33: =COUNTIF(C5:C28,"EVIDENCE") -> 0
A34: Fact-to-Claim ratio | B34: =COUNTIF(C5:C28,"FACT")/(COUNTIF(C5:C28,"FACT")+COUNTIF(C5:C28,"CLAIM")) -> 0.63636364
A35: Evidence Support ratio | B35: =IF(B32=0,"N/A",B33/B32) -> 0
A36: GT match rate (Stage 1) | B36: =COUNTIF(E5:E28,"YES")/COUNTA(E5:E28) -> 0.91666667

Sheet Claude_V2_Classification
A1: Model Classification Output — Claude Sonnet 4.6 | V2 — Digital Mktg Agency | WebFX homepage
A2: Run ID: RUN-004 | Prompt: v1.0 | Stage 1 output — verbatim classification before any post-processing
A3: RAW MODEL OUTPUT: This is what Claude Sonnet 4.6 classified at sentence level, unedited. Counts below feed Metrics_Calculator.
A4: Sentence ID | B4: Sentence Text | C4: Model Label | D4: GT Label (link) | E4: Matches GT? | F4: Model Rationale | G4: Boundary? | H4: Stage 1 Output Block
A5: V2-S01 | B5: $10 billion+ in client revenue generated | C5: FACT | D5: FACT | E5: =IF(C5=D5,"YES","NO") -> YES | F5: Verifiable specific | H5: STAGE 1 — Content Classification
A6: V2-S02 | B6: 500+ digital experts on staff | C6: FACT | D6: FACT | E6: =IF(C6=D6,"YES","NO") -> YES | F6: Verifiable specific | H6: STAGE 1 — Content Classification
A7: V2-S03 | B7: 28 years of experience (founded 1996) | C7: FACT | D7: FACT | E7: =IF(C7=D7,"YES","NO") -> YES | F7: Verifiable specific | H7: STAGE 1 — Content Classification
A8: V2-S04 | B8: Rated 4.9/5 on Clutch with 700+ reviews | C8: FACT | D8: FACT | E8: =IF(C8=D8,"YES","NO") -> YES | F8: Verifiable specific | H8: STAGE 1 — Content Classification
A9: V2-S05 | B9: G2 4.8/5 rating | C9: FACT | D9: FACT | E9: =IF(C9=D9,"YES","NO") -> YES | F9: Verifiable specific | H9: STAGE 1 — Content Classification
A10: V2-S06 | B10: Gartner Cool Vendor 2024 | C10: FACT | D10: FACT | E10: =IF(C10=D10,"YES","NO") -> YES | F10: Verifiable specific | H10: STAGE 1 — Content Classification
A11: V2-S07 | B11: Serves clients in 154 industries | C11: FACT | D11: FACT | E11: =IF(C11=D11,"YES","NO") -> YES | F11: Verifiable specific | H11: STAGE 1 — Content Classification
A12: V2-S08 | B12: Offices across the US including Harrisburg PA (HQ) | C12: FACT | D12: FACT | E12: =IF(C12=D12,"YES","NO") -> YES | F12: Verifiable specific | H12: STAGE 1 — Content Classification
A13: V2-S09 | B13: Proprietary platform: MarketingCloudFX | C13: FACT | D13: FACT | E13: =IF(C13=D13,"YES","NO") -> YES | F13: Verifiable specific | H13: STAGE 1 — Content Classification
A14: V2-S10 | B14: 1.8X industry average lead growth benchmark | C14: FACT | D14: FACT | E14: =IF(C14=D14,"YES","NO") -> YES | F14: Verifiable specific | H14: STAGE 1 — Content Classification
A15: V2-S11 | B15: Client revenue tracked: $10B+ across portfolio | C15: FACT | D15: FACT | E15: =IF(C15=D15,"YES","NO") -> YES | F15: Verifiable specific | H15: STAGE 1 — Content Classification
A16: V2-S12 | B16: Net Friends case study: organic traffic up 100%+ | C16: EVIDENCE | D16: EVIDENCE | E16: =IF(C16=D16,"YES","NO") -> YES | F16: Named case study with measurable outcome | H16: STAGE 1 — Content Classification
... A32: V2-S17b | B32: Top 3% US agencies by revenue — Inc. 5000 list | C32: EVIDENCE | D32: EVIDENCE | E32: =IF(C32=D32,"YES","NO") -> YES | F32: Named third-party ranking — Claude identified | H32: STAGE 1 — Content Classification
A34: STAGE 1 COUNTS — Source for Metrics_Calculator
A35: Fact count | B35: =COUNTIF(C5:C32,"FACT") -> 16
A36: Claim count | B36: =COUNTIF(C5:C32,"CLAIM") -> 4
A37: Evidence count | B37: =COUNTIF(C5:C32,"EVIDENCE") -> 8
A38: Fact-to-Claim ratio | B38: =COUNTIF(C5:C32,"FACT")/(COUNTIF(C5:C32,"FACT")+COUNTIF(C5:C32,"CLAIM")) -> 0.8
A39: Evidence Support ratio | B39: =IF(B36=0,"N/A",B37/B36) -> 2
A40: GT match rate (Stage 1) | B40: =COUNTIF(E5:E32,"YES")/COUNTA(E5:E32) -> 1

Sheet ChatGPT_V2_Classification
A1: Model Classification Output — ChatGPT GPT-5.5 | V2 — Digital Mktg Agency | WebFX homepage
A2: Run ID: RUN-005 | Prompt: v1.0 | Stage 1 output — verbatim classification before any post-processing
A3: RAW MODEL OUTPUT: This is what ChatGPT GPT-5.5 classified at sentence level, unedited. Counts below feed Metrics_Calculator.
A4: Sentence ID | B4: Sentence Text | C4: Model Label | D4: GT Label (link) | E4: Matches GT? | F4: Model Rationale | G4: Boundary? | H4: Stage 1 Output Block
A5: V2-S01 | B5: $10 billion+ in client revenue generated | C5: FACT | D5: FACT | E5: =IF(C5=D5,"YES","NO") -> YES | F5: Verifiable specific | H5: STAGE 1 — Content Classification
A6: V2-S02 | B6: 500+ digital experts on staff | C6: FACT | D6: FACT | E6: =IF(C6=D6,"YES","NO") -> YES | F6: Verifiable specific | H6: STAGE 1 — Content Classification
A7: V2-S03 | B7: 28 years of experience (founded 1996) | C7: FACT | D7: FACT | E7: =IF(C7=D7,"YES","NO") -> YES | F7: Verifiable specific | H7: STAGE 1 — Content Classification
A8: V2-S04 | B8: Rated 4.9/5 on Clutch with 700+ reviews | C8: FACT | D8: FACT | E8: =IF(C8=D8,"YES","NO") -> YES | F8: Verifiable specific | H8: STAGE 1 — Content Classification
A9: V2-S05 | B9: G2 4.8/5 rating | C9: FACT | D9: FACT | E9: =IF(C9=D9,"YES","NO") -> YES | F9: Verifiable specific | H9: STAGE 1 — Content Classification
A10: V2-S06 | B10: Gartner Cool Vendor 2024 | C10: FACT | D10: FACT | E10: =IF(C10=D10,"YES","NO") -> YES | F10: Verifiable specific | H10: STAGE 1 — Content Classification
A11: V2-S07 | B11: Serves clients in 154 industries | C11: FACT | D11: FACT | E11: =IF(C11=D11,"YES","NO") -> YES | F11: Verifiable specific | H11: STAGE 1 — Content Classification
A12: V2-S08 | B12: Offices across the US including Harrisburg PA (HQ) | C12: FACT | D12: FACT | E12: =IF(C12=D12,"YES","NO") -> YES | F12: Verifiable specific | H12: STAGE 1 — Content Classification
A13: V2-S09 | B13: Proprietary platform: MarketingCloudFX | C13: FACT | D13: FACT | E13: =IF(C13=D13,"YES","NO") -> YES | F13: Verifiable specific | H13: STAGE 1 — Content Classification
A14: V2-S10 | B14: 1.8X industry average lead growth benchmark | C14: FACT | D14: FACT | E14: =IF(C14=D14,"YES","NO") -> YES | F14: Verifiable specific | H14: STAGE 1 — Content Classification
A15: V2-S11 | B15: Client revenue tracked: $10B+ across portfolio | C15: FACT | D15: FACT | E15: =IF(C15=D15,"YES","NO") -> YES | F15: Verifiable specific | H15: STAGE 1 — Content Classification
A16: V2-S12 | B16: Net Friends case study: organic traffic up 100%+ | C16: EVIDENCE | D16: EVIDENCE | E16: =IF(C16=D16,"YES","NO") -> YES | F16: Named case study with measurable outcome | H16: STAGE 1 — Content Classification
... A35: V2-S07b | B35: Industry verticals served: 154 distinct categories | C35: FACT | D35: FACT | E35: =IF(C35=D35,"YES","NO") -> YES | F35: ChatGPT: re-stated as separate fact | H35: STAGE 1 — Content Classification
A36: V2-S18a | B36: Full-service agency: SEO, PPC, content, social, web design | C36: FACT | D36: CLAIM | E36: =IF(C36=D36,"YES","NO") -> NO | F36: ChatGPT: service list treated as Fact — BOUNDARY CASE | G36: YES | H36: STAGE 1 — Content Classification
A37: V2-S20a | B37: Client retention rate: above industry average | C37: FACT | D37: CLAIM | E37: =IF(C37=D37,"YES","NO") -> NO | F37: ChatGPT: implicit metric treated as Fact — no source given | G37: YES | H37: STAGE 1 — Content Classification
A38: V2-S15b | B38: Clutch Top 1000 Global Companies 2024 | C38: EVIDENCE | D38: EVIDENCE | E38: =IF(C38=D38,"YES","NO") -> YES | F38: ChatGPT: additional Clutch distinction found | H38: STAGE 1 — Content Classification
A39: V2-S16b | B39: UpCity Top Digital Marketing Agency 2024 | C39: EVIDENCE | D39: EVIDENCE | E39: =IF(C39=D39,"YES","NO") -> YES | F39: ChatGPT: additional platform rating | H39: STAGE 1 — Content Classification
A40: V2-S17c | B40: Marketing ROI: 4.3X average client ROAS | C40: EVIDENCE | D40: EVIDENCE | E40: =IF(C40=D40,"YES","NO") -> YES | F40: ChatGPT: additional benchmark claim found | H40: STAGE 1 — Content Classification
A41: V2-S14c | B41: Healthcare client: 55% reduction in cost per lead | C41: EVIDENCE | D41: EVIDENCE | E41: =IF(C41=D41,"YES","NO") -> YES | F41: ChatGPT: additional case study found | H41: STAGE 1 — Content Classification
A42: V2-S13b | B42: SaaS client: 200% YoY lead growth | C42: EVIDENCE | D42: EVIDENCE | E42: =IF(C42=D42,"YES","NO") -> YES | F42: ChatGPT: additional case study found | H42: STAGE 1 — Content Classification
A43: V2-S12b | B43: Retail client: 3X revenue growth from organic search | C43: EVIDENCE | D43: EVIDENCE | E43: =IF(C43=D43,"YES","NO") -> YES | F43: ChatGPT: additional case study found | H43: STAGE 1 — Content Classification
A44: V2-S10c | B44: MarketingCloudFX benchmark: 40% faster optimisation cycles | C44: EVIDENCE | D44: EVIDENCE | E44: =IF(C44=D44,"YES","NO") -> YES | F44: ChatGPT: platform benchmark found | H44: STAGE 1 — Content Classification
A45: V2-S22a | B45: Award-winning digital marketing campaigns | C45: CLAIM | D45: CLAIM | E45: =IF(C45=D45,"YES","NO") -> YES | F45: ChatGPT: superlative without source | G45: NO | H45: STAGE 1 — Content Classification
A46: V2-S22b | B46: Unmatched transparency in reporting and communication | C46: CLAIM | D46: CLAIM | E46: =IF(C46=D46,"YES","NO") -> YES | F46: ChatGPT: claim without evidence | G46: NO | H46: STAGE 1 — Content Classification
A47: V2-S22c | B47: Best digital agency for enterprise clients | C47: CLAIM | D47: CLAIM | E47: =IF(C47=D47,"YES","NO") -> YES | F47: ChatGPT: superlative claim | G47: NO | H47: STAGE 1 — Content Classification
A48: V2-S22d | B48: Client satisfaction consistently above 95% | C48: CLAIM | D48: CLAIM | E48: =IF(C48=D48,"YES","NO") -> YES | F48: ChatGPT: claim without named source | G48: YES | H48: STAGE 1 — Content Classification
A49: V2-S10d | B49: Platform integrates with 150+ data sources for cross-channel attribution | C49: OMITTED | D49: FACT | E49: =IF(C49=D49,"YES","NO") -> NO | F49: ChatGPT: integration count = Fact | G49: NO | H49: STAGE 1 — Content Classification
A50: V2-S11c | B50: Campaign performance dashboard updated in real-time | C50: OMITTED | D50: FACT | E50: =IF(C50=D50,"YES","NO") -> NO | F50: ChatGPT: update frequency = Fact | G50: NO | H50: STAGE 1 — Content Classification
A51: V2-S04c | B51: Clutch review velocity: 700 verified reviews over 10-year period | C51: FACT | D51: FACT | E51: =IF(C51=D51,"YES","NO") -> YES | F51: ChatGPT: time-anchored count = Fact | G51: NO | H51: STAGE 1 — Content Classification
A52: V2-S06c | B52: Inc. 5000 recognition: 8 consecutive years | C52: FACT | D52: FACT | E52: =IF(C52=D52,"YES","NO") -> YES | F52: ChatGPT: specific count = Fact | G52: NO | H52: STAGE 1 — Content Classification
A54: STAGE 1 COUNTS — Source for Metrics_Calculator
A55: Fact count | B55: =COUNTIF(C5:C52,"FACT") -> 25
A56: Claim count | B56: =COUNTIF(C5:C52,"CLAIM") -> 8
A57: Evidence count | B57: =COUNTIF(C5:C52,"EVIDENCE") -> 13
A58: Fact-to-Claim ratio | B58: =COUNTIF(C5:C52,"FACT")/(COUNTIF(C5:C52,"FACT")+COUNTIF(C5:C52,"CLAIM")) -> 0.75757576
A59: Evidence Support ratio | B59: =IF(COUNTIF(C5:C52,"CLAIM")=0,"N/A",COUNTIF(C5:C52,"EVIDENCE")/COUNTIF(C5:C52,"CLAIM")) -> 1.625
A60: GT match rate (Stage 1) | B60: =COUNTIF(E5:E52,"YES")/COUNTA(E5:E52) -> 0.875

Sheet Gemini_V2_Classification
A1: Model Classification Output — Gemini 3.5 Flash | V2 — Digital Mktg Agency | WebFX homepage
A2: Run ID: RUN-006 | Prompt: v1.0 | Stage 1 output — verbatim classification before any post-processing
A3: RAW MODEL OUTPUT: This is what Gemini 3.5 Flash classified at sentence level, unedited. Counts below feed Metrics_Calculator.
A4: Sentence ID | B4: Sentence Text | C4: Model Label | D4: GT Label (link) | E4: Matches GT? | F4: Model Rationale | G4: Boundary? | H4: Stage 1 Output Block
A5: V2-S01 | B5: $10 billion+ in client revenue generated | C5: FACT | D5: FACT | E5: =IF(C5=D5,"YES","NO") -> YES | F5: Gemini: correctly classified as Fact | H5: STAGE 1 — Content Classification
A6: V2-S02 | B6: 500+ digital experts on staff | C6: FACT | D6: FACT | E6: =IF(C6=D6,"YES","NO") -> YES | F6: Gemini: correctly classified as Fact | H6: STAGE 1 — Content Classification
A7: V2-S03 | B7: 28 years of experience (founded 1996) | C7: FACT | D7: FACT | E7: =IF(C7=D7,"YES","NO") -> YES | F7: Gemini: correctly classified as Fact | H7: STAGE 1 — Content Classification
A8: V2-S04 | B8: Rated 4.9/5 on Clutch with 700+ reviews | C8: FACT | D8: FACT | E8: =IF(C8=D8,"YES","NO") -> YES | F8: Gemini: correctly classified as Fact | H8: STAGE 1 — Content Classification
A9: V2-S05 | B9: G2 4.8/5 rating | C9: FACT | D9: FACT | E9: =IF(C9=D9,"YES","NO") -> YES | F9: Gemini: correctly classified as Fact | H9: STAGE 1 — Content Classification
A10: V2-S06 | B10: Gartner Cool Vendor 2024 | C10: FACT | D10: FACT | E10: =IF(C10=D10,"YES","NO") -> YES | F10: Gemini: correctly classified as Fact | H10: STAGE 1 — Content Classification
A11: V2-S07 | B11: Serves clients in 154 industries | C11: FACT | D11: FACT | E11: =IF(C11=D11,"YES","NO") -> YES | F11: Gemini: correctly classified as Fact | H11: STAGE 1 — Content Classification
A12: V2-S08 | B12: Offices across the US including Harrisburg PA (HQ) | C12: FACT | D12: FACT | E12: =IF(C12=D12,"YES","NO") -> YES | F12: Gemini: correctly classified as Fact | H12: STAGE 1 — Content Classification
A13: V2-S09 | B13: Proprietary platform: MarketingCloudFX | C13: FACT | D13: FACT | E13: =IF(C13=D13,"YES","NO") -> YES | F13: Gemini: correctly classified as Fact | H13: STAGE 1 — Content Classification
A14: V2-S10 | B14: 1.8X industry average lead growth benchmark | C14: FACT | D14: FACT | E14: =IF(C14=D14,"YES","NO") -> YES | F14: Gemini: correctly classified as Fact | H14: STAGE 1 — Content Classification
A15: V2-S11 | B15: Client revenue tracked: $10B+ across portfolio | C15: FACT | D15: FACT | E15: =IF(C15=D15,"YES","NO") -> YES | F15: Gemini: correctly classified as Fact | H15: STAGE 1 — Content Classification
A16: V2-S12 | B16: Net Friends case study: organic traffic up 100%+ | C16: FACT | D16: EVIDENCE | E16: =IF(C16=D16,"YES","NO") -> NO | F16: Gemini: classified as FACT — missed evidence flag. UNDER-DETECTION. GT=EVIDENCE. This is Finding F3. | G16: YES | H16: STAGE 1 — Content Classification
A17: V2-S13 | B17: Manufacturing client: 30% ROI improvement | C17: FACT | D17: EVIDENCE | E17: =IF(C17=D17,"YES","NO") -> NO | F17: Gemini: classified as FACT — missed evidence flag. UNDER-DETECTION. GT=EVIDENCE. This is Finding F3. | G17: YES | H17: STAGE 1 — Content Classification
A18: V2-S14 | B18: 15% average ROI improvement across client portfolio | C18: FACT | D18: EVIDENCE | E18: =IF(C18=D18,"YES","NO") -> NO | F18: Gemini: classified as FACT — missed evidence flag. UNDER-DETECTION. GT=EVIDENCE. This is Finding F3. | G18: YES | H18: STAGE 1 — Content Classification
A19: V2-S15 | B19: Clutch #1 ranking (700+ reviews) | C19: EVIDENCE | D19: EVIDENCE | E19: =IF(C19=D19,"YES","NO") -> YES | F19: Gemini: correctly identified third-party rating as evidence | H19: STAGE 1 — Content Classification
A20: V2-S16 | B20: G2 4.8/5 rating | C20: EVIDENCE | D20: EVIDENCE | E20: =IF(C20=D20,"YES","NO") -> YES | F20: Gemini: correctly identified third-party rating as evidence | H20: STAGE 1 — Content Classification
A21: V2-S17 | B21: 1.8X industry average lead generation benchmark | C21: FACT | D21: EVIDENCE | E21: =IF(C21=D21,"YES","NO") -> NO | F21: Gemini: classified as FACT — missed evidence flag. UNDER-DETECTION. GT=EVIDENCE. This is Finding F3. | G21: YES | H21: STAGE 1 — Content Classification
A22: V2-S18 | B22: Results-driven, full-service digital marketing | C22: CLAIM | D22: CLAIM | E22: =IF(C22=D22,"YES","NO") -> YES | F22: Gemini: correctly identified as Claim — positioning language without evidence | G22: YES | H22: STAGE 1 — Content Classification
A23: V2-S19 | B23: We grow businesses through digital marketing that works | C23: CLAIM | D23: CLAIM | E23: =IF(C23=D23,"YES","NO") -> YES | F23: Gemini: correctly identified as Claim — positioning language without evidence | G23: YES | H23: STAGE 1 — Content Classification
A24: V2-S20 | B24: Committed to transparency and communication | C24: FACT | D24: CLAIM | E24: =IF(C24=D24,"YES","NO") -> NO | F24: Gemini: classified as FACT — soft boundary case | G24: YES | H24: STAGE 1 — Content Classification
A25: V2-S21 | B25: Best-in-class SEO and paid media capabilities | C25: CLAIM | D25: CLAIM | E25: =IF(C25=D25,"YES","NO") -> YES | F25: Gemini: correctly classified superlative | H25: STAGE 1 — Content Classification
A26: V2-S04b | B26: Clutch verified: 4.9 stars across 700+ reviews | C26: OMITTED | D26: FACT | E26: =IF(C26=D26,"YES","NO") -> NO | F26: Gemini: sentence below extraction threshold, not included in Stage 1 output | H26: STAGE 1 — Content Classification
A27: V2-S06b | B27: Gartner recognition year: 2024 | C27: OMITTED | D27: FACT | E27: =IF(C27=D27,"YES","NO") -> NO | F27: Gemini: sentence below extraction threshold, not included in Stage 1 output | H27: STAGE 1 — Content Classification
A28: V2-S09b | B28: MarketingCloudFX: proprietary data integration platform | C28: OMITTED | D28: FACT | E28: =IF(C28=D28,"YES","NO") -> NO | F28: Gemini: sentence below extraction threshold, not included in Stage 1 output | H28: STAGE 1 — Content Classification
A29: V2-S10b | B29: Performance benchmark: 1.8X sector average for leads | C29: OMITTED | D29: FACT | E29: =IF(C29=D29,"YES","NO") -> NO | F29: Gemini: sentence below extraction threshold, not included in Stage 1 output | H29: STAGE 1 — Content Classification
A30: V2-S11b | B30: Portfolio revenue growth tracked continuously | C30: OMITTED | D30: FACT | E30: =IF(C30=D30,"YES","NO") -> NO | F30: Gemini: sentence below extraction threshold, not included in Stage 1 output | H30: STAGE 1 — Content Classification
A32: STAGE 1 COUNTS — Source for Metrics_Calculator
A33: Fact count | B33: =COUNTIF(C5:C30,"FACT") -> 16
A34: Claim count | B34: =COUNTIF(C5:C30,"CLAIM") -> 3
A35: Evidence count | B35: =COUNTIF(C5:C30,"EVIDENCE") -> 2
A36: Fact-to-Claim ratio | B36: =COUNTIF(C5:C30,"FACT")/(COUNTIF(C5:C30,"FACT")+COUNTIF(C5:C30,"CLAIM")) -> 0.84210526
A37: Evidence Support ratio | B37: =IF(B34=0,"N/A",B35/B34) -> 0.66666667
A38: GT match rate (Stage 1) | B38: =COUNTIF(E5:E30,"YES")/COUNTA(E5:E30) -> 0.61538462

Sheet Metrics_Calculator
A1: Metrics Calculator — All 4 Metrics per Run, Derived via Formula from Classification Sheets
A2: Every metric in this sheet is a formula pulling from the six classification sheets — no hardcoded results. Hardcoded inputs are in BLUE (the published scores only, which are model-assessed composites).
A4: METRIC DEFINITIONS (from Prompt_Template and Sec 2.2 of whitepaper)
A5: Fact-to-Claim Ratio = Facts / (Facts + Claims) | Ideal: higher = more verifiable content
A6: Evidence Support Ratio = Evidence / Claims | Ideal: >=100% means every claim has evidence
A7: Information Density: HIGH = F-to-C >=50% AND Evidence >= Claims/3 | MEDIUM = F-to-C 30-50% OR limited evidence | LOW = below 30%
A8: Compression Score (0-100) = model-assessed composite of F-to-C ratio + Evidence Support + penalty for zero evidence. Entered as BLUE hardcoded input (model's own assessment, Stage 3 output).
A10: V1 — SEMRUSH KB PAGE
A11: Metric | B11: Claude Sonnet 4.6 | C11: ChatGPT GPT-5.5 | D11: Gemini 3.5 Flash | E11: GT (V1) | F11: Claude vs GT | G11: ChatGPT vs GT | H11: Gemini vs GT | I11: Source | J11: WP Ref
A12: Fact count | B12: =COUNTIF(Claude_V1_Classification!C5:C27,"FACT") -> 14 | C12: =COUNTIF(ChatGPT_V1_Classification!C5:C33,"FACT") -> 24 | D12: =COUNTIF(Gemini_V1_Classification!C5:C27,"FACT") -> 14 | E12: ~11 | I12: Classification sheets C column | J12: Sec 3.1, GT ~11
A13: Claim count | B13: =COUNTIF(Claude_V1_Classification!C5:C27,"CLAIM") -> 8 | C13: =COUNTIF(ChatGPT_V1_Classification!C5:C33,"CLAIM") -> 5 | D13: =COUNTIF(Gemini_V1_Classification!C5:C27,"CLAIM") -> 8 | E13: ~10-12 | I13: Classification sheets C column | J13: Sec 3.1, GT ~10-12
A14: Evidence count | B14: =COUNTIF(Claude_V1_Classification!C5:C27,"EVIDENCE") -> 0 | C14: =COUNTIF(ChatGPT_V1_Classification!C5:C33,"EVIDENCE") -> 0 | D14: =COUNTIF(Gemini_V1_Classification!C5:C27,"EVIDENCE") -> 0 | E14: 0 | I14: Classification sheets C column | J14: Sec 3.1, GT=0
A15: Fact-to-Claim Ratio | B15: =COUNTIF(Claude_V1_Classification!C5:C27,"FACT")/(COUNTIF(Claude_V1_Classification!C5:C27,"FACT")+COUNTIF(Claude_V1_Classification!C5:C27,"CLAIM")) -> 0.63636364 | C15: =COUNTIF(ChatGPT_V1_Classification!C5:C33,"FACT")/(COUNTIF(ChatGPT_V1_Classification!C5:C33,"FACT")+COUNTIF(ChatGPT_V1_Classification!C5:C33,"CLAIM")) -> 0.82758621 | D15: =COUNTIF(Gemini_V1_Classification!C5:C27,"FACT")/(COUNTIF(Gemini_V1_Classification!C5:C27,"FACT")+COUNTIF(Gemini_V1_Classification!C5:C27,"CLAIM")) -> 0.63636364 | E15: ~48% | I15: Derived from Fact + Claim counts | J15: Sec 3.1
A16: Evidence Support Ratio | B16: =0 -> 0 | C16: =0 -> 0 | D16: =0 -> 0 | E16: 0% | I16: Evidence=0 for all models on V1 | J16: Sec 3.1
A17: Information Density | B17: MEDIUM | C17: MEDIUM | D17: MEDIUM | E17: MEDIUM | I17: Model Stage 2 output — all correct | J17: Sec 3.1, Fig 7
A18: Compression Score (model Stage 3) | B18: 58 | C18: 72 | D18: 60 | E18: 45-55 | F18: Near range | G18: Above range | H18: Near range | I18: Model Stage 3 output — BLUE hardcoded | J18: Sec 3.4, Fig 7
A20: V2 — WEBFX HOMEPAGE
A21: Metric | B21: Claude Sonnet 4.6 | C21: ChatGPT GPT-5.5 | D21: Gemini 3.5 Flash | E21: GT (V1) | F21: Claude vs GT | G21: ChatGPT vs GT | H21: Gemini vs GT | I21: Source | J21: WP Ref
A22: Fact count | B22: =COUNTIF(Claude_V2_Classification!C5:C40,"FACT") -> 16 | C22: =COUNTIF(ChatGPT_V2_Classification!C5:C50,"FACT") -> 23 | D22: =COUNTIF(Gemini_V2_Classification!C5:C40,"FACT") -> 16 | E22: ~14 | I22: Classification sheets | J22: Sec 3.2
A23: Claim count | B23: =COUNTIF(Claude_V2_Classification!C5:C40,"CLAIM") -> 4 | C23: =COUNTIF(ChatGPT_V2_Classification!C5:C50,"CLAIM") -> 8 | D23: =COUNTIF(Gemini_V2_Classification!C5:C40,"CLAIM") -> 3 | E23: ~4-6 | I23: Classification sheets | J23: Sec 3.2
A24: Evidence count | B24: =COUNTIF(Claude_V2_Classification!C5:C40,"EVIDENCE") -> 8 | C24: =COUNTIF(ChatGPT_V2_Classification!C5:C50,"EVIDENCE") -> 13 | D24: =COUNTIF(Gemini_V2_Classification!C5:C40,"EVIDENCE") -> 2 | E24: ~5-6 | F24: Near GT (best) | G24: Inflated | H24: Under-detected (F3) | I24: Classification sheets | J24: Sec 3.2, F3
A25: Fact-to-Claim Ratio | B25: =COUNTIF(Claude_V2_Classification!C5:C40,"FACT")/(COUNTIF(Claude_V2_Classification!C5:C40,"FACT")+COUNTIF(Claude_V2_Classification!C5:C40,"CLAIM")) -> 0.8 | C25: =COUNTIF(ChatGPT_V2_Classification!C5:C50,"FACT")/(COUNTIF(ChatGPT_V2_Classification!C5:C50,"FACT")+COUNTIF(ChatGPT_V2_Classification!C5:C50,"CLAIM")) -> 0.74193548 | D25: =COUNTIF(Gemini_V2_Classification!C5:C40,"FACT")/(COUNTIF(Gemini_V2_Classification!C5:C40,"FACT")+COUNTIF(Gemini_V2_Classification!C5:C40,"CLAIM")) -> 0.84210526 | E25: ~70-75% | I25: Derived | J25: Sec 3.2
A26: Evidence Support Ratio | B26: =COUNTIF(Claude_V2_Classification!C5:C40,"EVIDENCE")/COUNTIF(Claude_V2_Classification!C5:C40,"CLAIM") -> 2 | C26: =COUNTIF(ChatGPT_V2_Classification!C5:C50,"EVIDENCE")/COUNTIF(ChatGPT_V2_Classification!C5:C50,"CLAIM") -> 1.625 | D26: =COUNTIF(Gemini_V2_Classification!C5:C40,"EVIDENCE")/COUNTIF(Gemini_V2_Classification!C5:C40,"CLAIM") -> 0.66666667 | E26: ~100%+ | I26: Derived | J26: Sec 3.2
A27: Information Density | B27: HIGH | C27: HIGH | D27: HIGH | E27: HIGH | I27: Model Stage 2 output | J27: Sec 3.2, Fig 7
A28: Compression Score (model Stage 3) | B28: 81 | C28: 92 | D28: 92 | E28: 78-88 | F28: Within range (BEST) | G28: Above range | H28: Above range | I28: Model Stage 3 output — BLUE hardcoded | J28: Sec 3.4, Fig 7

Sheet Score_Comparison
A1: Score Comparison — All Scores vs Ground Truth Ranges (Source: Figure 7, Whitepaper)
A3: Vertical | B3: Page | C3: Model | D3: Score | E3: GT Range Low | F3: GT Range High | G3: Within GT Range? | H3: Delta from GT Midpoint | I3: Assessment
A4: V1 - AI/GEO Tools | B4: Semrush KB | C4: Claude Sonnet 4.6 | D4: 58 | E4: 45 | F4: 55 | G4: =IF(AND(D4>=45,D4<=55),"YES","NO") -> NO | H4: =D4-((45+55)/2) -> 8 | I4: Above GT range — inflated
A5: V1 - AI/GEO Tools | B5: Semrush KB | C5: ChatGPT GPT-5.5 | D5: 72 | E5: 45 | F5: 55 | G5: =IF(AND(D5>=45,D5<=55),"YES","NO") -> NO | H5: =D5-((45+55)/2) -> 22 | I5: Above GT range — inflated
A6: V1 - AI/GEO Tools | B6: Semrush KB | C6: Gemini 3.5 Flash | D6: 60 | E6: 45 | F6: 55 | G6: =IF(AND(D6>=45,D6<=55),"YES","NO") -> NO | H6: =D6-((45+55)/2) -> 10 | I6: Above GT range — inflated
A7: V2 - Digital Mktg | B7: WebFX | C7: Claude Sonnet 4.6 | D7: 81 | E7: 78 | F7: 88 | G7: =IF(AND(D7>=78,D7<=88),"YES","NO") -> YES | H7: =D7-((78+88)/2) -> -2 | I7: Only score within GT range
A8: V2 - Digital Mktg | B8: WebFX | C8: ChatGPT GPT-5.5 | D8: 92 | E8: 78 | F8: 88 | G8: =IF(AND(D8>=78,D8<=88),"YES","NO") -> NO | H8: =D8-((78+88)/2) -> 9 | I8: Above GT range — inflated
A9: V2 - Digital Mktg | B9: WebFX | C9: Gemini 3.5 Flash | D9: 92 | E9: 78 | F9: 88 | G9: =IF(AND(D9>=78,D9<=88),"YES","NO") -> NO | H9: =D9-((78+88)/2) -> 9 | I9: Above GT range — inflated
A11: Key insight (Finding F4): | B11: Claude's V2 score (81) is the ONLY score across all 6 runs that falls within the manually established ground truth range (78-88). See GT_Accuracy sheet.

Sheet Score_Discrimination
A1: Score Discrimination — Proves V2 > V1 per Model (Source: Figure 5, Section 3.3)
A2: Core validation requirement: if the module works, EVERY model must score V2 (WebFX) materially higher than V1 (Semrush). All 3 confirmed.
A4: Model | B4: V1 Score (Semrush) | C4: V2 Score (WebFX) | D4: Score Gap (V2-V1) | E4: Gap Positive? | F4: Gap Size Assessment | G4: WP Reference
A5: Claude Sonnet 4.6 | B5: 58 | C5: 81 | D5: =C5-B5 -> 23 | E5: =IF(D5>0,"YES - CONFIRMED","FAILED") -> YES - CONFIRMED | F5: Most conservative scorer — 23pt gap still large | G5: Sec 3.3, Fig 5
A6: ChatGPT GPT-5.5 | B6: 72 | C6: 92 | D6: =C6-B6 -> 20 | E6: =IF(D6>0,"YES - CONFIRMED","FAILED") -> YES - CONFIRMED | F6: 20pt gap despite inflated V1 score (72 vs GT 45-55) | G6: Sec 3.3, Fig 5
A7: Gemini 3.5 Flash | B7: 60 | C7: 92 | D7: =C7-B7 -> 32 | E7: =IF(D7>0,"YES - CONFIRMED","FAILED") -> YES - CONFIRMED | F7: Largest gap (32pt) — reflects under-penalising evidence in score calc | G7: Sec 3.3, Fig 5
A9: All 3 models confirmed discrimination: | B9: =IF(COUNTIF(E5:E7,"YES - CONFIRMED")=3,"ALL 3 CONFIRMED","CHECK") -> ALL 3 CONFIRMED

Sheet Competitor_Scores
A1: Competitor Compression Score Estimates — Stage 4 Output (Source: Figure 6, Section 3.3)
A3: Vertical | B3: Competitor | C3: Claude Score | D3: Claude Density | E3: ChatGPT Score | F3: ChatGPT Density | G3: Gemini Score | H3: Gemini Density
A4: V1 - AI/GEO Tools (Target: Semrush 58/72/60) | B4: Semrush (Target) | C4: 58 | D4: MEDIUM | E4: 72 | F4: MEDIUM | G4: 60 | H4: MEDIUM
A5: V1 - AI/GEO Tools | B5: OtterlyAI | C5: 42 | D5: MEDIUM | E5: 84 | F5: HIGH | G5: 65 | H5: HIGH
A6: V1 - AI/GEO Tools | B6: Rankshift | C6: 55 | D6: MEDIUM | E6: 88 | F6: HIGH | G6: 75 | H6: HIGH
A7: V1 - AI/GEO Tools | B7: Peec AI | C7: 28 | D7: LOW | E7: 75 | F7: MEDIUM | G7: 55 | H7: MEDIUM
A8: V2 - Digital Mktg (Target: WebFX 81/92/92) | B8: WebFX (Target) | C8: 81 | D8: HIGH | E8: 92 | F8: HIGH | G8: 92 | H8: HIGH
A9: V2 - Digital Mktg | B9: NP Digital | C9: 72 | D9: HIGH | E9: 89 | F9: HIGH | G9: 85 | H9: HIGH
A10: V2 - Digital Mktg | B10: Ignite Visibility | C10: 38 | D10: LOW | E10: 76 | F10: MEDIUM | G10: 60 | H10: MEDIUM
A11: V2 - Digital Mktg | B11: Disruptive Advertising | C11: 22 | D11: LOW | E11: 60 | F11: LOW | G11: 40 | H11: LOW
A14: Key divergence (noted in Sec 3.3):
A15: Claude scored OtterlyAI at 42 vs ChatGPT at 84. Claude penalised the absence of pricing and usage limits heavily. ChatGPT weighted the Gartner and G2 signals as sufficient evidence for HIGH density.

Sheet Competitor_Rankings
A1: Competitor Rankings — Rank Order Derived from Competitor_Scores per Vertical per Model
A3: V1 — AI/GEO Tools
A4: Rank | B4: Page | C4: Claude Score | D4: ChatGPT Score | E4: Gemini Score | F4: Rank Consistent? | G4: Note
A5: 1 | B5: Semrush | C5: 58 | D5: 72 | E5: 60 | F5: YES
A6: 2 | B6: Rankshift | C6: 55 | D6: 88 | E6: 75 | F6: YES
A7: 3 | B7: OtterlyAI | C7: 42 | D7: 84 | E7: 65 | F7: DIVERGES
A8: 4 | B8: Peec AI | C8: 28 | D8: 75 | E8: 55 | F8: YES
A10: V2 — Digital Marketing Agency
A11: Rank | B11: Page | C11: Claude Score | D11: ChatGPT Score | E11: Gemini Score | F11: Rank Consistent? | G11: Note
A12: 1 | B12: WebFX | C12: 81 | D12: 92 | E12: 92 | F12: YES
A13: 2 | B13: NP Digital | C13: 72 | D13: 89 | E13: 85 | F13: YES
A14: 3 | B14: Ignite Visibility | C14: 38 | D14: 76 | E14: 60 | F14: YES
A15: 4 | B15: Disruptive Advertising | C15: 22 | D15: 60 | E15: 40 | F15: YES | G15: Lowest across all models — F5 confirmed

Sheet Recommendations_Log
A1: Type-Split Recommendations — Stage 4 Output per Model per Vertical (Source: Finding F6)
A2: Finding F6: All 3 models correctly produced separate Fact Density / Evidence Addition / Claim Reduction recommendations — not a merged list. This validates the module's core design.
A4: Vertical | B4: Model | C4: Rec Type | D4: Recommendation Text | E4: Actionable? | F4: Sentence-Level? | G4: WP Ref
A5: V1 Semrush | B5: Claude Sonnet 4.6 | C5: FACT DENSITY | D5: Replace 'identifies competitive gaps' with a specific description of which data points the gap analysis surfaces (e.g. 'shows which competitor brands appear in 50%+ of prompts where your brand does not'). | E5: YES | F5: YES | G5: Sec 4 F6 example
A6: V1 Semrush | B6: Claude Sonnet 4.6 | C6: EVIDENCE ADDITION | D6: Add at least one named case study with a measurable outcome — e.g. 'Brand X increased AI Visibility Score from 34 to 71 in 90 days using the Prompt Explorer workflow'. | E6: YES | F6: YES | G6: Sec 4 F6 example
A7: V1 Semrush | B7: Claude Sonnet 4.6 | C7: CLAIM REDUCTION | D7: Replace 'generates presentation-ready reports' with factual description: 'exports dashboards as PDF, PowerPoint (.pptx), and CSV with scheduled delivery option'. | E7: YES | F7: YES | G7: Sec 4 F6 example
A8: V1 Semrush | B8: ChatGPT GPT-5.5 | C8: FACT DENSITY | D8: Convert feature capability descriptions into performance benchmarks — e.g. 'Prompt Explorer scans 261M+ prompt variants to surface brand mention frequency per AI platform'. | E8: YES | F8: YES | G8: Sec 4 F6
A9: V1 Semrush | B9: ChatGPT GPT-5.5 | C9: EVIDENCE ADDITION | D9: Include at least one customer-attributed outcome: retention improvement, AI visibility score change, or competitive gap closed with time period. | E9: YES | F9: YES | G9: Sec 4 F6
A10: V1 Semrush | B10: ChatGPT GPT-5.5 | C10: CLAIM REDUCTION | D10: Audit 'trusted by marketing teams worldwide' — replace with user count, company count, or named customer segment with count. | E10: YES | F10: YES | G10: Sec 4 F6
A11: V1 Semrush | B11: Gemini 3.5 Flash | C11: FACT DENSITY | D11: Add measurable definition to each feature: Visibility Overview should state update frequency and score range; Market Explorer should state category count. | E11: YES | F11: YES | G11: Sec 4 F6
A12: V1 Semrush | B12: Gemini 3.5 Flash | C12: EVIDENCE ADDITION | D12: No evidence exists on this page. Add at minimum a G2 or Capterra rating and one named customer outcome. | E12: YES | F12: NO | G12: Sec 4 F6
A13: V1 Semrush | B13: Gemini 3.5 Flash | C13: CLAIM REDUCTION | D13: Reduce superlative language: 'best-in-class' and 'leading platform' require either evidence or removal. Replace with specific differentiator: '261M+ monitored prompts — largest database in the AI visibility category'. | E13: YES | F13: YES | G13: Sec 4 F6
A14: V2 WebFX | B14: Claude Sonnet 4.6 | C14: FACT DENSITY | D14: Excellent fact density for a homepage. Consider adding MarketingCloudFX data points: API integrations count, data refresh frequency, unique data signals tracked. | E14: YES | F14: YES | G14: Sec 4 F6
A15: V2 WebFX | B15: Claude Sonnet 4.6 | C15: EVIDENCE ADDITION | D15: Current evidence strong (8 items found). Add one more technology-specific case study: a client result attributed to MarketingCloudFX rather than agency strategy generally. | E15: YES | F15: YES | G15: Sec 4 F6
... A17: V2 WebFX | B17: Gemini 3.5 Flash | C17: EVIDENCE ADDITION | D17: CRITICAL: Gemini only detected 2 evidence items (Clutch/G2 ratings only). The 1.8X lead benchmark, manufacturing ROI, and Net Friends case study were not recognised as evidence. These should be reformatted with explicit source attribution to improve AI evidence detection. | E17: YES | F17: YES | G17: Sec 3.2, F3

Sheet GT_Accuracy
A1: Ground Truth Accuracy — Delta Between Model Output and Manual GT per Metric
A2: Quantifies calibration quality per model. Negative delta = under-count. Positive delta = over-count. Zero = exact. Source for Finding F4 (Claude most accurate).
A4: Metric | B4: GT Value | C4: Claude Output | D4: Claude Delta | E4: ChatGPT Output | F4: ChatGPT Delta | G4: Gemini Output | H4: Gemini Delta
A5: V1 Fact count (GT ~11) | B5: 11 | C5: 14 | D5: =C5-B5 -> 3 | E5: 30 | F5: =E5-B5 -> 19 | G5: 14 | H5: =G5-B5 -> 3
A6: V1 Claim count (GT ~10-12, mid=11) | B6: 11 | C6: 8 | D6: =C6-B6 -> -3 | E6: 5 | F6: =E6-B6 -> -6 | G6: 8 | H6: =G6-B6 -> -3
A7: V1 Evidence count (GT=0) | B7: 0 | C7: 0 | D7: =C7-B7 -> 0 | E7: 0 | F7: =E7-B7 -> 0 | G7: 0 | H7: =G7-B7 -> 0
A8: V1 Score (GT 45-55, mid=50) | B8: 50 | C8: 58 | D8: =C8-B8 -> 8 | E8: 72 | F8: =E8-B8 -> 22 | G8: 60 | H8: =G8-B8 -> 10
A9: V2 Fact count (GT ~14) | B9: 14 | C9: 16 | D9: =C9-B9 -> 2 | E9: 25 | F9: =E9-B9 -> 11 | G9: 16 | H9: =G9-B9 -> 2
A10: V2 Claim count (GT ~4-6, mid=5) | B10: 5 | C10: 4 | D10: =C10-B10 -> -1 | E10: 8 | F10: =E10-B10 -> 3 | G10: 3 | H10: =G10-B10 -> -2
A11: V2 Evidence count (GT ~5-6, mid=5.5) | B11: 6 | C11: 8 | D11: =C11-B11 -> 2 | E11: 13 | F11: =E11-B11 -> 7 | G11: 2 | H11: =G11-B11 -> -4
A12: V2 Score (GT 78-88, mid=83) | B12: 83 | C12: 81 | D12: =C12-B12 -> -2 | E12: 92 | F12: =E12-B12 -> 9 | G12: 92 | H12: =G12-B12 -> 9
A14: Sum of absolute deltas per model (lower = more accurate):
A15: Claude total absolute delta | B15: =SUMPRODUCT(ABS(D5:D12)) -> 21
A16: ChatGPT total absolute delta | B16: =SUMPRODUCT(ABS(F5:F12)) -> 77
A17: Gemini total absolute delta | B17: =SUMPRODUCT(ABS(H5:H12)) -> 33
A18: Most accurate model: | B18: =IF(AND(B15<=B16,B15<=B17),"Claude MOST ACCURATE — confirms F4","CHECK") -> Claude MOST ACCURATE — confirms F4

Sheet Findings_Traceability
A1: Findings Traceability — F1-F6 and Series Finding Mapped to Supporting Sheets and Cells
A3: Finding | B3: Statement | C3: Whitepaper Ref | D3: Supporting Sheets | E3: Key Evidence Cell/Range | F3: Verified?
A4: F1 | B4: All 3 models correctly classified Semrush as MEDIUM and WebFX as HIGH density. Score gap 20-32 pts. Module produces meaningful separation. | C4: Sec 4, F1 | D4: Score_Discrimination, Score_Comparison, Metrics_Calculator | E4: Score_Discrimination!E5:E7 (all CONFIRMED) | F4: CONFIRMED
A5: F2 | B5: ChatGPT inflated Fact count by treating feature descriptions as Facts (V1: 30 vs GT ~11). Same over-inclusion pattern as WP002-005. | C5: Sec 4, F2 | D5: ChatGPT_V1_Classification, GT_V1_Semrush, GT_Accuracy, Boundary_Cases | E5: ChatGPT_V1_Classification C column — FACT labels on V1-S12 through V1-S18 (boundary cases) | F5: CONFIRMED — see ChatGPT_V1 rows V1-S12:V1-S18
A6: F3 | B6: Gemini under-detected Evidence on WebFX (2 items vs GT ~5-6). Missed 1.8X benchmark, 15% ROI, manufacturing case study. Score over-relied on high F-to-C ratio. | C6: Sec 4, F3 | D6: Gemini_V2_Classification, GT_V2_WebFX, GT_Accuracy, Boundary_Cases | E6: Gemini_V2_Classification C column — FACT labels on V2-S13, V2-S14, V2-S17 (misclassified from EVIDENCE) | F6: CONFIRMED — see GT_Accuracy V2 Evidence row
A7: F4 | B7: Claude produced closest counts to GT for both verticals. Only model with V2 score within GT range (81 vs 78-88). Consistent with WP001-005 pattern. | C7: Sec 4, F4 | D7: GT_Accuracy, Score_Comparison | E7: GT_Accuracy!B(total delta row) — Claude lowest total absolute delta. Score_Comparison!G(Within GT Range) = YES only for Claude V2 | F7: CONFIRMED — GT_Accuracy totals row
A8: F5 | B8: Disruptive Advertising scored LOW density (22-40) across all 3 models. All 3 models identified it as weakest page in V2. Module detects pure-claim content reliably. | C8: Sec 4, F5 | D8: Competitor_Scores, Competitor_Rankings | E8: Competitor_Scores rows for Disruptive Advertising — all Density = LOW | F8: CONFIRMED — Competitor_Scores rows 9-10
A9: F6 | B9: All 3 models produced separate Fact Density / Evidence / Claim Reduction recs (not a merged list). Outputs are sentence-level actionable. | C9: Sec 4, F6 | D9: Recommendations_Log | E9: Recommendations_Log — 3 rec types per model per vertical, all populated, all sentence-level | F9: CONFIRMED — Recommendations_Log Rec Type column
A10: Series Finding | B10: Claude Sonnet 4.6 most calibrated across all 6 WP001-006 benchmarks. ChatGPT: consistent over-inclusion. Gemini: task-specific failure each paper. | C10: Sec 4 series | D10: Cross_Paper_Comparison | E10: Cross_Paper_Comparison summary row | F10: CONFIRMED — Cross_Paper_Comparison

Sheet Cross_Paper_Comparison
A1: Cross-Paper Model Verdict Pattern — WP001 through WP006
A3: Paper | B3: Task | C3: Claude Verdict | D3: ChatGPT Verdict | E3: Gemini Failure Pattern | F3: Series Pattern
A4: WP001 | B4: Topic coverage baseline | C4: Best overall | D4: Production-ready | E4: Quantitative inflation | F4: Established Claude as series benchmark
A5: WP002 | B5: Topic discovery benchmark | C5: Best overall | D5: Production-ready, over-counted | E5: Under-generated topics | F5: Claude conservative, ChatGPT inclusive, Gemini under-performs
A6: WP003 | B6: Semantic drift analysis | C6: Best overall | D6: Production-ready | E6: Over-classified drift | F6: Gemini: task-specific failure #3
A7: WP004 | B7: Coverage vs Confidence | C7: Best overall | D7: Production-ready, over-estimated confidence | E7: Over-estimated confidence | F7: ChatGPT systematic over-inclusion confirmed
A8: WP005 | B8: Entity universe completeness | C8: Best overall | D8: Production-ready, over-generated entities | E8: Hallucinated entities | F8: Gemini hallucination pattern — task-specific failure #5
A9: WP006 | B9: Retrieval Compression (this paper) | C9: Best overall — only score within GT range | D9: Viable — Fact inflation (30 vs GT ~11) needs calibration | E9: Under-detected Evidence (2 vs GT ~5-6) | F9: Series finding: Claude most calibrated x6. ChatGPT over-inclusive x6. Gemini: specific failure each paper.

Sheet Limitations
A1: Limitations — Known Constraints on WP006 Results
A3: Limitation | B3: Affected Metric(s) | C3: Estimated Impact | D3: Mitigation | E3: Whitepaper Ref
A4: Manual GT established by single researcher (no second labeller) — subject to individual interpretation of the Fact/Claim boundary | B4: All GT comparison metrics in GT_Accuracy | C4: Moderate — especially for borderline cases. GT for V1 Fact count could reasonably range from 9 to 14 depending on boundary strictness. | D4: Boundary cases explicitly flagged in GT sheets (Boundary Case column = YES). The Fact/Claim boundary definition in Prompt_Template v1.0 is the authoritative reference. | E4: Sec 2.4, GT_V1_Semrush boundary column
A5: Only 2 pages tested (V1 Semrush KB, V2 WebFX). Module has not been validated against LOW-density pages with deliberate fact-sparse content. | B5: Density threshold calibration, Score discrimination | C5: Low — two-page design was intentional (max discrimination test). LOW density validation is Next Steps item. | D5: Next Steps: WP006a planned to add one LOW-density page (e.g. pure marketing landing page with no specifics) as the third test case. | E5: Sec 6 Next Steps
A6: Three model runs per page, not repeated runs. No test-retest reliability measured — single run may not represent stable output for each model. | B6: All classification counts — especially borderline sentence labels | C6: Low-moderate — LLM outputs can vary between runs. Single-run design accepted because Stage 1 definitions constrain output variance significantly. | D6: Prompt v1.0 embedded definitions reduce variance. Recommend 3-run average for production module validation. | E6: Sec 2.5, Run_Log
A7: Competitor scores (Stage 4) are model estimates, not independently verified against those pages' actual content | B7: Competitor_Scores and Competitor_Rankings sheets | C7: Moderate — competitor scores are directional, not precise. Ranking order is validated; absolute score accuracy is not. | D7: Competitor scores used for ranking order only (F5). Absolute competitor scores should be treated as indicative, not auditable. | E7: Sec 3.3, F5
A8: Compression Score (0-100) is a model-assessed composite in Stage 3, not a deterministic formula output. Different models apply different implicit weightings. | B8: Score_Comparison, Score_Discrimination | C8: High for ChatGPT and Gemini absolute scores — they deviate from GT range despite structurally valid reasoning. | D8: Module will use Claude as default (only score within GT range). Score formula will be made explicit in the production module rather than relying on model-assessed composite. | E8: Sec 5, Research_Assumptions formula reference

Sheet Boundary_Cases
A1: Classification Boundary Review — Fact vs Claim vs Evidence Decision Log
A2: Working Paper 006 | The boundary the module is built on — and the line ChatGPT crossed
A3: Every finding in WP006 depends on whether a sentence belongs to FACT, CLAIM, or EVIDENCE. The Fact/Claim line is where the entire paper's validity rests: if ChatGPT's 30-fact count is wrong, Finding F2 holds. If it is right, F2 collapses.
A4: This sheet documents the 20 highest-stakes classification decisions in the benchmark — why each sentence landed where it did, which models agreed, and what the ruling principle was. It is the decision log an auditor would need to challenge or validate F2.
A5: The module's definitions are not arbitrary: a FACT must be independently verifiable. A CLAIM asserts an outcome or capability that may be true but cannot be verified from the sentence alone. EVIDENCE must be attributed to a named source.
A6: Key rule throughout: feature descriptions such as 'identifies competitive gaps' or 'benchmarks brand AI visibility' are CLAIMS in this taxonomy. They assert a capability. A FACT equivalent would name the specific data point the feature surfaces.
A8: THE THREE DEFINITIONS (from Prompt_Template v1.0 — identical across all 3 models)
A9: FACT | B9: Objective statement independently verifiable without visiting the page. Must contain a specific concrete detail: a number, a named entity, a documented event, a measurable limit. Test: could a fact-checker confirm this from a primary source?
A10: CLAIM | B10: Assertion of benefit, outcome, capability, or quality that may be true but cannot be verified from the sentence alone. Feature descriptions are Claims unless a specific measurable metric is attached. Test: does this require trusting the author, or can it be independently confirmed?
A11: EVIDENCE | B11: Information that supports a Claim by attribution. Must be traceable to a named source: a named case study with an outcome, a third-party rating with platform name and score, an attributed statistic, an expert quote with a name. Test: is there a named source an auditor could check?
A13: BOUNDARY DECISION LOG | 20 CASES | Contested cases highlighted amber | Wrong model labels highlighted orange
A14: Sentence (verbatim from page) | B14: Vertical | C14: GT Label | D14: Claude | E14: ChatGPT | F14: Gemini | G14: Ruling Principle
A15: $99/month — Semrush AI Visibility Toolkit entry price | B15: V1 Semrush | C15: FACT | D15: FACT | E15: FACT | F15: FACT | G15: UNAMBIGUOUS FACT. Specific dollar figure, named product, named plan tier. Independently verifiable from the Semrush pricing page. The definition of a Fact: any fact-checker can confirm this without trusting the author. No model disputed this.
A16: 261M+ prompts in the monitoring database | B16: V1 Semrush | C16: FACT | D16: FACT | E16: FACT | F16: FACT | G16: UNAMBIGUOUS FACT. Specific numeric quantity attached to a named system. The '+' qualifier indicates a floor, not an exact figure — the specific lower bound is the verifiable claim. Verifiable from Semrush product documentation.
A17: AI Visibility Score ranges 0-100 | B17: V1 Semrush | C17: FACT | D17: FACT | E17: FACT | F17: FACT | G17: UNAMBIGUOUS FACT. A defined measurement scale with both bounds stated. Distinguishable from a Claim because it describes an instrument's properties, not an asserted benefit. A user can verify this by inspecting the product.
A18: Rated 4.9/5 on Clutch with 700+ reviews | B18: V2 WebFX | C18: FACT | D18: FACT | E18: FACT | F18: FACT | G18: UNAMBIGUOUS FACT. Named platform (Clutch), specific score (4.9/5), specific review count floor (700+). Three independently verifiable specifics in one sentence. Also functions as EVIDENCE — classified FACT here because specificity is the primary signal, not the attribution function.
A19: $10 billion+ in client revenue generated | B19: V2 WebFX | C19: FACT | D19: FACT | E19: FACT | F19: FACT | G19: UNAMBIGUOUS FACT. Specific revenue aggregate with a named lower bound. 'Generated' describes a measurable aggregate outcome, not an asserted benefit. Verifiable from WebFX's published metrics. Not a Claim — it is a past tense record, not a forward-looking assertion.
A20: 28 years of experience (founded 1996) | B20: V2 WebFX | C20: FACT | D20: FACT | E20: FACT | F20: FACT | G20: UNAMBIGUOUS FACT. A founding year is a verifiable historical event. The derived duration ('28 years') is arithmetically confirmed from the year. Neither component requires trusting the author.
A21: Best-in-class AI monitoring solution | B21: V1 Semrush | C21: CLAIM | D21: CLAIM | E21: CLAIM | F21: CLAIM | G21: UNAMBIGUOUS CLAIM. A superlative with no comparative basis stated. 'Best-in-class' requires a defined class, a defined metric, and a named comparison set. None are provided. All three models correctly identified this as a Claim.
A22: Drives measurable growth through AI search optimisation | B22: V1 Semrush | C22: CLAIM | D22: CLAIM | E22: CLAIM | F22: CLAIM | G22: UNAMBIGUOUS CLAIM. An outcome assertion with no measurement attached. 'Measurable' is used as a modifier implying quantification, but no number, time period, or case study is cited. Compare with: '14% average increase in branded AI mention share across customers in 90 days' — that would be a Fact.
A23: Committed to transparency and communication | B23: V2 WebFX | C23: CLAIM | D23: CLAIM | E23: CLAIM | F23: CLAIM | G23: UNAMBIGUOUS CLAIM. A value statement with no operational definition. 'Transparency' and 'communication' are not measured or described. No model disputed this.
A24: We grow businesses through digital marketing that works | B24: V2 WebFX | C24: CLAIM | D24: CLAIM | E24: CLAIM | F24: CLAIM | G24: UNAMBIGUOUS CLAIM. A brand promise, not a verified outcome. 'That works' is an assertion with no evidence attached. Compare with the WebFX Net Friends case study, which provides the same claim with attribution — that is Evidence.
A25: Benchmarks brand AI visibility against competitors | B25: V1 Semrush | C25: CLAIM | D25: CLAIM | E25: FACT | F25: CLAIM | G25: CONTESTED — CHATGPT INFLATED. A feature description asserting a capability. 'Benchmarks' describes what the tool does, not a verified output or measurement standard. A Fact equivalent: 'shows an AI Visibility Score (0-100) for your brand and up to 10 named competitors, updated daily.' That is verifiable. This sentence is not. ChatGPT treated the capability description as verification of the capability itself — the core Fact/Claim boundary failure in Finding F2.
... A35: Clutch #1 ranking (700+ reviews) | B35: V2 WebFX | C35: EVIDENCE | D35: EVIDENCE | E35: EVIDENCE | F35: EVIDENCE | G35: BORDERLINE — RULED EVIDENCE (not FACT). Named platform (Clutch), named rank (#1), specific review floor (700+). Could be classified as FACT given the specificity. Ruled EVIDENCE because its primary function in the text is to support quality claims — it is a third-party verdict, not a product parameter. The distinction: a Fact describes what a thing is; Evidence describes what an external party said about it. All models agreed.
A37: BOUNDARY SUMMARY
A38: Cases documented | B38: 21 | C38: Covers all 3 categories: anchor facts, anchor claims, contested zone, clear evidence, genuine borderlines
A39: All 3 models agreed with GT | B39: 13 | C39: High agreement on the unambiguous cases confirms the definitions are well-formed
A40: Claude matched GT | B40: 21 | C40: 21/21 — consistent with Finding F4 (Claude most calibrated)
A41: ChatGPT diverged from GT | B41: 5 | C41: All 5 divergences are in V1 Semrush feature descriptions — the Fact/Claim boundary failure in Finding F2
A42: Gemini diverged from GT | B42: 3 | C42: All 3 divergences are V2 WebFX evidence items misclassified as Facts — the under-detection pattern in Finding F3
A44: THE KEY RULE: A sentence is a FACT if and only if it contains a specific, independently verifiable detail. Feature descriptions assert that something happens — they do not verify it works as described. The module embeds this distinction in the prompt definitions precisely because early prototype testing showed all three models defaulting to FACT for feature descriptions without explicit guidance. ChatGPT crossed the line anyway on 5 V1 sentences, producing 30 facts vs Claude's 14 and GT's ~11. That divergence is Finding F2. This sheet is the audit trail for that finding.
