Workbook

Sheet README
A1: WP007 Research Appendix — Multi-Hop Reasoning for AI Retrievability
A2: Working Paper No. 007 | Akshay Dahiya | AI Spider Pre-Build Validation Series | 2025-2026
A4: HOW TO USE THIS WORKBOOK
A5: This workbook is the complete research audit trail for WP007. Every number in the whitepaper traces to a specific cell.
A6: Ground truth sheets (GT_V1, GT_V2) contain MANUAL entity and relationship labels established BEFORE any model was run (dated 2025-11-04).
A7: Relationship extraction sheets (6 sheets, one per model per vertical) are the core raw data — every triple [Source]-[type]->[Target] the model produced.
A8: Chain_Depth_Analysis reconstructs the actual longest paths from the raw triples — this is where the 7-hop SEO chain is documented.
A9: Relationship_Boundary is the decision log for the Fact/Relationship boundary — the equivalent of Boundary_Cases in WP006, and the central methodological sheet.
A10: Colour convention: BLUE = hardcoded model output | BLACK = formula | GREEN = cross-sheet link | AMBER = GT reference | ORANGE = over-extraction flag | LAVENDER = under-extraction flag
A12: SHEET INDEX
A13: # | B13: Sheet Name | C13: Purpose | D13: WP Ref | E13: Type
A14: 1 | B14: README | C14: Workbook guide and sheet index | D14: All | E14: Navigation
A15: 2 | B15: Research_Assumptions | C15: Key assumptions and derivation of every headline figure | D15: Abstract, Sec 2 | E15: Assumptions
A16: 3 | B16: GT_V1_Semrush | C16: Manual ground truth — V1 Semrush page entities + relationships (locked 2025-11-04) | D16: Sec 2.3 | E16: Ground truth
A17: 4 | B17: GT_V2_WebFX | C17: Manual ground truth — V2 WebFX page entities + relationships (locked 2025-11-04) | D17: Sec 2.3 | E17: Ground truth
A18: 5 | B18: Prompt_Template | C18: Full 5-stage prompt used identically across all 3 models | D18: Sec 2.2 | E18: Methodology
A19: 6 | B19: Run_Log | C19: Timestamped log of all 6 model runs — proves GT-first methodology | D19: Sec 2.4 | E19: Process log
A20: 7 | B20: Claude_V1_Relationships | C20: All relationship triples extracted by Claude from V1 Semrush (10 relationships) | D20: Sec 3.1 | E20: Raw extraction
A21: 8 | B21: ChatGPT_V1_Relationships | C21: All relationship triples extracted by ChatGPT from V1 Semrush (28 — inflated) | D21: Sec 3.1, F2 | E21: Raw extraction
A22: 9 | B22: Gemini_V1_Relationships | C22: All relationship triples extracted by Gemini from V1 Semrush (2 — under) | D22: Sec 3.1, F3 | E22: Raw extraction
A23: 10 | B23: Claude_V2_Relationships | C23: All relationship triples extracted by Claude from V2 WebFX (18) | D23: Sec 3.2 | E23: Raw extraction
A24: 11 | B24: ChatGPT_V2_Relationships | C24: All relationship triples extracted by ChatGPT from V2 WebFX (24) | D24: Sec 3.2 | E24: Raw extraction
A25: 12 | B25: Gemini_V2_Relationships | C25: All relationship triples extracted by Gemini from V2 WebFX (21) | D25: Sec 3.2 | E25: Raw extraction
... A37: 24 | B37: Limitations | C37: Known constraints on WP007 results | D37: Sec 6 | E37: Methodology

Sheet Research_Assumptions
A1: Research Assumptions and Key Number Derivations
A2: How every headline figure in WP007 was calculated — the fast-path for any auditor
A4: Every relationship count, chain depth, coverage %, and score in the whitepaper is traced to a source here.
A5: Ground truth figures are AMBER. Model outputs are BLUE hardcoded inputs. Formula-derived values are BLACK.
A6: The most important assumption in this paper: the boundary between a reasoning relationship and a feature description.
A8: SECTION 1 — Framework and Design Assumptions
A9: Parameter | B9: Value | C9: Derivation | D9: Assumption Made | E9: Verify In
A10: Models tested | B10: 3 (Claude Sonnet 4.6, ChatGPT GPT-5.5, Gemini 3.5 Flash) | C10: Same 3 models used across WP001-006 for series continuity | D10: 3 models provide sufficient coverage of the extraction style spectrum (conservative / inclusive / literal) | E10: Run_Log, Sec 2.4
A11: Verticals | B11: 2 (V1: Semrush KB page, V2: WebFX homepage) | C11: V1 = intentionally low-reasoning-depth feature list. V2 = intentionally high-reasoning-depth with explicit chains. | D11: Maximum discrimination design: pages chosen to maximise chain depth difference to prove module discriminates | E11: GT_V1_Semrush, GT_V2_WebFX, Sec 2.3
A12: Total runs | B12: 6 (3 models x 2 verticals) | C12: =3*2 -> 6 | D12: Independent fresh-context runs — no conversation history, no cross-contamination between verticals | E12: Run_Log
A13: Critical prompt constraint | B13: Do NOT infer from domain knowledge | C13: Embedded verbatim in SYSTEM ROLE block of Prompt_Template v1.0 | D13: Without this constraint, all 3 models hallucinate reasoning chains that exist in the domain but are not stated in the text. Validated in prototype testing. | E13: Prompt_Template, Sec 2.2
A14: Relationship quality rule | B14: Only CAUSAL, ENABLING, IMPROVING, DETERMINING relationships count toward chain depth | C14: Feature descriptions (measures, monitors, shows, identifies) are valid as single-hop nodes but NOT counted as reasoning relationships in depth calculation | D14: This is the most consequential design decision in WP007. ChatGPT crossed this boundary on 11 V1 triples. See Relationship_Boundary sheet. | E14: Relationship_Boundary, Sec 2.2
A15: Ground truth method | B15: Manual entity and relationship mapping per page before model runs | C15: Researcher mapped every entity and every explicit relationship from both pages sentence by sentence | D15: GT established first to prevent anchoring — locked 2025-11-04, all model runs 2025-11-05 | E15: GT_V1_Semrush, GT_V2_WebFX, Run_Log
A17: SECTION 2 — Headline Number Derivations
A18: Headline Figure | B18: Published Value | C18: Source | D18: Derivation Logic | E18: GT Range | F18: Verify In
A19: V1 Semrush — Claude relationships | B19: 10 | C19: Claude_V1_Relationships | D19: COUNTIF of all rows where Relationship_Quality = REASONING (not FEATURE_DESC) | E19: ~7 (GT) | F19: Claude_V1_Relationships, Metrics_Calculator
A20: V1 Semrush — ChatGPT relationships | B20: 28 | C20: ChatGPT_V1_Relationships | D20: COUNTIF of all rows — INFLATED: 11 'tool enables feature' descriptions counted as relationships | E20: ~7 (GT) | F20: ChatGPT_V1_Relationships, Relationship_Boundary
A21: V1 Semrush — Gemini relationships | B21: 2 | C21: Gemini_V1_Relationships | D21: COUNTIF — UNDER-EXTRACTED: only 2 literal causal statements accepted | E21: ~7 (GT) | F21: Gemini_V1_Relationships, GT_Accuracy
A22: V1 Semrush — Claude max chain depth | B22: 3 | C22: Chain_Depth_Analysis | D22: Longest path in Claude's V1 relationship graph: Technical Issues -> AI Crawlers -> Page Inclusion (depth 3) | E22: 2-3 (GT) | F22: Chain_Depth_Analysis
A23: V1 Semrush — Claude Reasoning Score | B23: 34 | C23: Metrics_Calculator | D23: Model Stage 4 composite: weighted relationship quality + chain depth + coverage penalty for isolated concepts | E23: 25-40 (GT) | F23: Metrics_Calculator, Score_Comparison
A24: V1 Semrush — ChatGPT Reasoning Score | B24: 68 | C24: Metrics_Calculator | D24: Same formula — inflated by 28 relationship count driving high coverage % and chain calculation | E24: 25-40 (GT) | F24: Metrics_Calculator, Score_Comparison
A25: V1 Semrush — Gemini Reasoning Score | B25: 15 | C25: Metrics_Calculator | D25: Same formula — depressed by only 2 relationships and 14.3% coverage | E25: 25-40 (GT) | F25: Metrics_Calculator, Score_Comparison
A26: V2 WebFX — Claude max chain depth | B26: 7 | C26: Chain_Depth_Analysis | D26: Longest path: SEO -> Organic Traffic -> Leads -> CRM -> Campaign Opt. -> CPA -> Marketing ROI (7 nodes = depth 7) | E26: 5-6 (GT) | F26: Chain_Depth_Analysis, Sec 3.2
A27: V2 WebFX — Claude Reasoning Score | B27: 72 | C27: Metrics_Calculator | D27: Only V2 score within GT range (65-80) for Claude. High chain depth + good coverage. | E27: 65-80 (GT) | F27: Metrics_Calculator, Score_Comparison
A28: Score discrimination — Claude | B28: +38 pts (34->72) | C28: Score_Discrimination | D28: Score_Discrimination!D5 (Claude V2 - Claude V1) | E28: Positive required | F28: Score_Discrimination
A29: Score discrimination — ChatGPT | B29: +22 pts (68->90) | C29: Score_Discrimination | D29: Score_Discrimination!D6 (ChatGPT V2 - ChatGPT V1) | E29: Positive required | F29: Score_Discrimination
A30: Score discrimination — Gemini | B30: +73 pts (15->88) | C30: Score_Discrimination | D30: Score_Discrimination!D7 (Gemini V2 - Gemini V1) — largest gap because V1 severely under-scored | E30: Positive required | F30: Score_Discrimination
A31: V1 Multi-Hop Coverage — Claude | B31: 52% | C31: Metrics_Calculator | D31: Connected concepts / (Connected + Isolated). Claude found 13 connected, 12 isolated from V1. | E31: N/A | F31: Metrics_Calculator
A32: V1 Multi-Hop Coverage — ChatGPT | B32: 67.5% | C32: Metrics_Calculator | D32: ChatGPT found 27 connected, 13 isolated — higher due to inflated relationship count. | E32: N/A | F32: Metrics_Calculator
A33: V1 Multi-Hop Coverage — Gemini | B33: 14.3% | C33: Metrics_Calculator | D33: Gemini found 2 connected, 12 isolated — extremely low due to under-extraction. | E33: N/A | F33: Metrics_Calculator
A36: SECTION 3 — Metric Formula Reference
A37: Relationship Count = COUNTIF(Relationship_Quality column, 'REASONING') -- feature descriptions excluded from chain depth
A38: Max Chain Depth = longest directed path in the relationship graph (computed manually in Chain_Depth_Analysis sheet)
A39: Connected Concepts = entities participating in at least one REASONING relationship
A40: Isolated Concepts = entities mentioned but not in any REASONING relationship
A41: Multi-Hop Coverage = Connected / (Connected + Isolated) e.g. Claude V1: 13/(13+12) = 52.0%
A42: Reasoning Score = model Stage 4 composite 0-100: chain depth weighted 50%, coverage 30%, relationship count 20%
A43: Score Discrimination Gap = V2_Score - V1_Score per model (must be positive — validated in Score_Discrimination sheet)

Sheet GT_V1_Semrush
A1: Ground Truth — V1 Semrush AI Visibility Toolkit KB Page
A2: Manual entity and relationship mapping established BEFORE any model run. Locked: 2025-11-04.
A4: PURPOSE: Every entity and relationship on the Semrush KB page was mapped by the researcher sentence-by-sentence before any model was queried.
A5: The key GT finding: the page has almost no explicit causal reasoning chains — it is a feature list. Explicit chains: ~7.
A6: The one clear multi-hop chain: Technical Issues -> blocks -> AI Crawlers -> affects -> Page Inclusion in AI answers (depth 2).
A7: This is what makes V1 the hard test case: extracting 2 or 28 relationships from the same low-reasoning-depth page both represent model failures in opposite directions.
A9: GROUND TRUTH — Manual researcher mapping | Date locked: 2025-11-04 | NOT a model output | All model runs: 2025-11-05
A10: SECTION A — Entity Inventory (manual, pre-model)
A11: Entity ID | B11: Entity Name | C11: Entity Type | D11: Connected? | E11: Reasoning Role | F11: Source Sentence | G11: GT Notes
A12: V1-E01 | B12: Semrush AI Visibility Toolkit | C12: Product | D12: YES | E12: Source — the primary tool being described | F12: 'Semrush AI Visibility Toolkit' | G12: Named product — anchor entity for all other V1 relationships
A13: V1-E02 | B13: AI Visibility Score | C13: Feature/Metric | D13: YES | E13: Intermediate — score produced by the tool | F13: 'AI Visibility Score updated daily' | G13: Named metric with frequency — connects to monitoring chain
A14: V1-E03 | B14: Technical Issues | C14: Problem entity | D14: YES | E14: Source — triggers the one clear causal chain | F14: 'AI Search Site Audit identifies technical issues' | G14: Starting node of the page's only explicit causal chain
A15: V1-E04 | B15: AI Crawlers | C15: Agent | D15: YES | E15: Intermediate — the mechanism in the causal chain | F15: 'blocking AI bots from accessing pages' | G15: Core of the depth-2 causal chain
A16: V1-E05 | B16: Page Inclusion in AI Answers | C16: Outcome | D16: YES | E16: Target — end of the causal chain | F16: 'affects inclusion in AI answers' | G16: Only explicitly stated outcome in V1 — depth-2 chain terminus
A17: V1-E06 | B17: Share of Voice | C17: Metric | D17: YES | E17: Intermediate — measured by Brand Performance feature | F17: 'Brand Performance measures Share of Voice' | G17: Named metric — chain stops here; downstream effect not stated
A18: V1-E07 | B18: Brand Performance | C18: Feature | D18: YES | E18: Source — names a feature | F18: 'Brand Performance feature measures Share of Voice' | G18: Feature entity — relates to SoV but chain is incomplete
A19: V1-E08 | B19: Prompt Research | C19: Feature | D19: YES | E19: Source — names a feature | F19: 'Prompt Research measures volume/difficulty/intent' | G19: Named feature with named outputs
A20: V1-E09 | B20: AI Mention Volume | C20: Output metric | D20: YES | E20: Target of Prompt Research relationship | F20: 'measures volume, difficulty, intent' | G20: Named output — isolated beyond this single relationship
A21: V1-E10 | B21: 261M+ prompts database | C21: Data asset | D21: NO | E21: Isolated — mentioned as a spec, no relationship | F21: '261M+ prompts in the monitoring database' | G21: Fact, not a node in any reasoning chain
A22: V1-E11 | B22: $99/month pricing | C22: Pricing | D22: NO | E22: Isolated — product spec, no reasoning connection | F22: '$99/month' | G22: Price point — no causal role in any chain
... A30: V1-E19 | B30: Peec AI | C30: Competitor | D30: NO | E30: Competitor reference only | F30: Implicit from competitor set | G30: Benchmark competitor
A32: GT Entity counts
A33: Total entities | B33: =COUNTA(A12:A30) -> 19
A34: Connected entities | B34: =COUNTIF(D12:D30,"YES") -> 10 | C34: (participating in at least one reasoning relationship)
A35: Isolated entities | B35: =COUNTIF(D12:D30,"NO") -> 9 | C35: (mentioned but no meaningful reasoning connection)
A37: SECTION B — Relationship Inventory (manual, pre-model)
A38: Rel ID | B38: Source Entity | C38: Rel Type | D38: Target Entity | E38: Hop Depth | F38: Explicit? | G38: GT Inclusion | H38: Source Sentence
A39: V1-R01 | B39: AI Search Site Audit | C39: identifies | D39: Technical Issues | E39: 1 | F39: YES | G39: INCLUDED | H39: 'AI Search Site Audit identifies technical issues blocking AI bots'
A40: V1-R02 | B40: Technical Issues | C40: blocks | D40: AI Crawlers | E40: 1 | F40: YES | G40: INCLUDED | H40: 'blocking AI bots from accessing pages'
A41: V1-R03 | B41: AI Crawlers | C41: affects | D41: Page Inclusion in AI Answers | E41: 1 | F41: YES | G41: INCLUDED | H41: 'affects inclusion in AI answers' — implied by 'blocking AI bots'
A42: V1-R04 | B42: Brand Performance | C42: measures | D42: Share of Voice | E42: 1 | F42: YES | G42: INCLUDED | H42: 'Brand Performance measures Share of Voice'
A43: V1-R05 | B43: Semrush Toolkit | C43: monitors | D43: AI Mention Volume | E43: 1 | F43: YES | G43: INCLUDED | H43: 'monitors brand visibility across ChatGPT, Gemini, Perplexity'
A44: V1-R06 | B44: Prompt Research | C44: measures | D44: AI Mention Volume | E44: 1 | F44: YES | G44: INCLUDED | H44: 'Prompt Research measures volume, difficulty, intent'
A45: V1-R07 | B45: AI Visibility Score | C45: tracks | D45: Brand Visibility Trend | E45: 1 | F45: YES | G45: INCLUDED | H45: 'tracks changes in AI mentions over time'
A46: V1-R08 | B46: Semrush Toolkit | C46: enables | D46: Competitive Benchmarking | E46: 1 | F46: IMPLICIT | G46: BORDERLINE — EXCLUDED from GT count | H46: 'benchmarks brand AI visibility against competitors' — feature description, not causal
A47: V1-R09 | B47: Share of Voice improvement | C47: leads to | D47: Brand Discoverability in AI | E47: 1 | F47: NO | G47: EXCLUDED — MISSING CHAIN | H47: NOT STATED on page. This is the key relationship gap identified in F5.
A48: V1-R10 | B48: Technical Issues fix | C48: leads to | D48: Improved AI Visibility | E48: 2 | F48: NO | G48: EXCLUDED — MISSING CHAIN | H48: NOT STATED. The page identifies issues but never states fixing them improves AI visibility.
A50: GT Relationship count (explicit, included) | B50: =COUNTIF(G39:G48,"INCLUDED") -> 7 | C50: ~7 (published GT range)
A51: GT Max chain depth | B51: 2-3 | C51: AI Search Site Audit -> Tech Issues -> AI Crawlers -> Page Inclusion (depth 3, partially implicit)

Sheet GT_V2_WebFX
A1: Ground Truth — V2 WebFX Homepage
A2: Manual entity and relationship mapping established BEFORE any model run. Locked: 2025-11-04.
A4: PURPOSE: WebFX was selected as the high-reasoning-depth benchmark — one of the most explicitly chain-rich homepages in the dataset.
A5: Key GT finding: The SEO chain (depth 7) and RevenueCloudFX chain (depth 4-5) are explicitly stated in the page copy.
A6: Expected: all 3 models should find the SEO chain. Finding F4 confirms all 3 did (depth 6-7). This validates max chain depth as the most robust metric.
A7: The GT expected ~12-15 relationships. Actual model outputs: Claude 18, ChatGPT 24, Gemini 21 — all higher than GT, but all converged on max depth.
A9: GROUND TRUTH — Manual researcher mapping | Date locked: 2025-11-04 | NOT a model output | All model runs: 2025-11-05
A10: SECTION A — Entity Inventory
A11: Entity ID | B11: Entity Name | C11: Entity Type | D11: Connected? | E11: Chain Role | F11: Source Sentence | G11: GT Notes
A12: V2-E01 | B12: SEO | C12: Service/Strategy | D12: YES | E12: Chain start — initiates the primary 7-hop chain | F12: 'SEO services drive organic traffic' | G12: Anchor of the most important reasoning chain in the dataset
A13: V2-E02 | B13: Organic Traffic | C13: Outcome | D13: YES | E13: Chain node 2 — bridges SEO to leads | F13: 'organic traffic converts to leads' | G13: Key conversion node
A14: V2-E03 | B14: Leads | C14: Outcome | D14: YES | E14: Chain node 3 | F14: 'leads feed into CRM' | G14: Bridge to data infrastructure
A15: V2-E04 | B15: CRM | C15: System | D15: YES | E15: Chain node 4 | F15: 'CRM data informs campaign optimisation' | G15: Data → strategy bridge
A16: V2-E05 | B16: Campaign Optimisation | C16: Process | D16: YES | E16: Chain node 5 | F16: 'campaign optimisation reduces CPA' | G16: Efficiency node
A17: V2-E06 | B17: CPA (Cost Per Acquisition) | C17: Metric | D17: YES | E17: Chain node 6 | F17: 'reduces CPA' | G17: Cost metric — reduces
A18: V2-E07 | B18: Marketing ROI | C18: Outcome | D18: YES | E18: Chain terminus — 7-hop chain end | F18: 'improves Marketing ROI' | G18: The final outcome node — what the entire chain is arguing for
A19: V2-E08 | B19: RevenueCloudFX | C19: Platform | D19: YES | E19: Parallel chain start | F19: 'RevenueCloudFX enables revenue attribution' | G19: Second major chain in V2
A20: V2-E09 | B20: Revenue Attribution | C20: Process | D20: YES | E20: Intermediate — bridges data to budget | F20: 'enables revenue attribution' | G20: Links platform to budget decision
A21: V2-E10 | B21: Budget Allocation | C21: Process | D21: YES | E21: Intermediate | F21: 'informs budget allocation' | G21: Strategic decision node
A22: V2-E11 | B22: Revenue Growth | C22: Outcome | D22: YES | E22: Chain terminus — parallel chain | F22: 'leads to revenue growth' | G22: Parallel chain terminus
... A31: V2-E20 | B31: Ignite Visibility | C31: Competitor | D31: NO | E31: Competitor reference only | F31: Competitor set | G31: Third competitor
A33: GT Entity counts
A34: Total entities | B34: =COUNTA(A12:A31) -> 20
A35: Connected entities | B35: =COUNTIF(D12:D31,"YES") -> 17
A36: Isolated entities | B36: =COUNTIF(D12:D31,"NO") -> 3
A38: SECTION B — Relationship Inventory (manual, pre-model): THE 7-HOP SEO CHAIN
A39: Rel ID | B39: Source Entity | C39: Rel Type | D39: Target Entity | E39: Chain | F39: Depth in Chain | G39: Explicit? | H39: Source Sentence
A40: V2-R01 | B40: SEO | C40: drives | D40: Organic Traffic | E40: SEO Chain | F40: 1 | G40: YES EXPLICIT | H40: 'SEO services drive organic traffic to your site'
A41: V2-R02 | B41: Organic Traffic | C41: converts to | D41: Leads | E41: SEO Chain | F41: 2 | G41: YES EXPLICIT | H41: 'organic traffic converts to leads'
A42: V2-R03 | B42: Leads | C42: feed into | D42: CRM | E42: SEO Chain | F42: 3 | G42: YES EXPLICIT | H42: 'leads feed into CRM'
A43: V2-R04 | B43: CRM | C43: informs | D43: Campaign Optimisation | E43: SEO Chain | F43: 4 | G43: YES EXPLICIT | H43: 'CRM data informs campaign optimisation'
A44: V2-R05 | B44: Campaign Optimisation | C44: reduces | D44: CPA | E44: SEO Chain | F44: 5 | G44: YES EXPLICIT | H44: 'campaign optimisation reduces CPA'
A45: V2-R06 | B45: CPA | C45: improves | D45: Marketing ROI | E45: SEO Chain | F45: 6 | G45: YES EXPLICIT | H45: 'reduces CPA, improves Marketing ROI'
A46: V2-R07 | B46: RevenueCloudFX | C46: enables | D46: Revenue Attribution | E46: RCF Chain | F46: 1 | G46: YES EXPLICIT | H46: 'RevenueCloudFX enables revenue attribution'
A47: V2-R08 | B47: Revenue Attribution | C47: enables | D47: Budget Allocation | E47: RCF Chain | F47: 2 | G47: YES EXPLICIT | H47: 'attribution enables informed budget allocation'
A48: V2-R09 | B48: Budget Allocation | C48: leads to | D48: Revenue Growth | E48: RCF Chain | F48: 3 | G48: YES EXPLICIT | H48: 'budget allocation leads to revenue growth'
A49: V2-R10 | B49: Net Friends case study | C49: demonstrates | D49: Organic Traffic outcome | E49: Evidence | F49: 1 | G49: YES EXPLICIT | H49: 'Net Friends: organic traffic up 100%+'
A50: V2-R11 | B50: Manufacturing client | C50: demonstrates | D50: ROI outcome | E50: Evidence | F50: 1 | G50: YES EXPLICIT | H50: 'Manufacturing: 30% ROI improvement'
A51: V2-R12 | B51: Clutch #1 ranking | C51: validates | D51: WebFX quality claims | E51: Evidence | F51: 1 | G51: YES EXPLICIT | H51: 'Clutch #1 ranking (700+ reviews)'
... A54: V2-R15 | B54: 500+ experts | C54: deliver | D54: Client Revenue ($10B+) | E54: Service chain | F54: 1 | G54: YES EXPLICIT | H54: '500+ experts have generated $10B+ in client revenue'
A56: GT Relationship count | B56: =COUNTA(A40:A54) -> 15 | C56: ~12-15 (published GT range)
A57: GT Max chain depth | B57: 6 (SEO chain: 6 hops from SEO to ROI) | C57: Models found 6-7 depending on whether SEO->ROI counted as 6 or 7 nodes

Sheet Prompt_Template
A1: Five-Stage Prompt Template v1.0
A2: Identical prompt used across all 3 models. The 'do not infer' constraint is the most critical structural element.
A4: Without 'Do NOT infer relationships from domain knowledge', all 3 models hallucinate chains that exist in the domain but are not in the text.
A5: This was validated in prototype testing: Claude, ChatGPT, and Gemini all added 'optimising -> improves visibility' chains not stated in V1 text.
A6: ChatGPT crossed this boundary anyway on 11 V1 sentences despite the constraint — treating feature descriptions as reasoning relationships.
A8: Stage | B8: Block | C8: Content | D8: Purpose | E8: Critical Note
A9: SYSTEM ROLE | B9: Role + constraint | C9: You are a Multi-Hop Reasoning Analysis engine. Measure how well a TARGET page connects concepts into logical reasoning chains compared to COMPETITOR pages. CRITICAL: Only extract relationships EXPLICITLY stated or directly implied in the provided text. Do NOT infer relationships from your domain knowledge. | D9: Anchors model in extraction mode, not inference mode | E9: MOST CRITICAL element. Without this, all 3 models hallucinate reasoning chains from domain knowledge.
A10: RELATIONSHIP DEFINITIONS | B10: Reasoning Relationships (COUNT toward depth) | C10: Include: causes, drives, enables, improves, leads to, determines, converts to, feeds into, reduces, increases. A relationship must express a mechanism — the source entity must produce or cause a change in the target entity. | D10: Defines what qualifies for chain depth calculation | E10: These are the verb types that constitute genuine multi-hop reasoning chains.
A11: RELATIONSHIP DEFINITIONS | B11: Feature Descriptions (do NOT count toward depth) | C11: Exclude from depth calculation: measures, monitors, shows, identifies, tracks, displays, generates. These describe what a feature does, not a causal mechanism. A tool that 'measures Share of Voice' creates a single node — it does not drive a reasoning chain. | D11: Prevents ChatGPT-style inflation of feature description -> relationship | E11: ChatGPT crossed this line on 11 V1 triples despite this definition being embedded.
A12: STAGE 1 | B12: Entity identification | C12: List all significant entities on the TARGET page. For each entity, classify as: CONNECTED (participates in at least one reasoning relationship) or ISOLATED (mentioned but not connected to any reasoning chain). | D12: Produces entity inventory and connected/isolated classification | E12: This is where Gemini under-performed on V1 — classified too many entities as isolated.
A13: STAGE 2 | B13: Relationship extraction | C13: For every reasoning relationship you identified: output as a directed triple: [Source Entity] --[relationship type]--> [Target Entity]. Only include relationships that meet the REASONING definition above. Flag any borderline cases as BORDERLINE with rationale. | D13: The core extraction output — each row is one triple | E13: The BORDERLINE flag was added after prototype testing where all models silently included feature descriptions.
A14: STAGE 3 | B14: Graph metrics | C14: Calculate: Total relationship count | Maximum chain depth (longest connected path) | Connected concept count | Isolated concept count | Multi-Hop Coverage % (Connected / Total entities). | D14: Derives the 5 metrics from Stage 2 output | E14: Max chain depth is the most important metric — tested in F4.
A15: STAGE 4 | B15: Multi-Hop Reasoning Score 0-100 | C15: Generate a Reasoning Score between 0 and 100. Weight: chain depth 50%, coverage 30%, relationship count 20%. Penalise isolated concepts. Provide 2-3 sentence rationale. | D15: The composite score used in Score_Comparison and Score_Discrimination | E15: Model-assessed composite — entered as BLUE hardcoded input in workbook.
A16: STAGE 5 | B16: Competitor comparison + gaps + recommendations | C16: Estimate Reasoning Scores for 4 competitor pages. Then output: Relationship Gap List (specific chains that COMPETITOR pages have that TARGET page lacks) and Prioritised Recommendations (each recommendation = one specific chain to add, formatted as: [Source]-[type]->[Intermediate]-[type]->[Target]). | D16: Chain-level recommendations — the F5 output | E16: Format requirement: each rec must be an explicit chain, not a topic suggestion.
A17: CONTROL | B17: Output format | C17: Respond only with the structured report. No commentary outside the format. For each relationship: output the triple + the source sentence that supports it + your rationale for inclusion/exclusion. | D17: Ensures parseable, comparable outputs across all 3 models | E17: Source sentence requirement is essential for Relationship_Boundary audit.

Sheet Run_Log
A1: Model Run Log
A2: Timestamped record of all 6 prompt executions. GT locked 2025-11-04. All runs 2025-11-05 — proves GT-first methodology.
A4: This log proves the ground truth sheets (GT_V1, GT_V2) were established BEFORE any model was queried.
A5: Each run used identical Prompt_Template v1.0 — no model-specific modifications.
A6: Fresh API session per run — no conversation history, no cross-contamination between verticals.
A8: Run ID | B8: Date | C8: Time (UTC) | D8: Model | E8: Version | F8: Vertical | G8: Target Page | H8: Prompt v | I8: GT Prior? | J8: Output Sheet
A9: RUN-001 | B9: 2025-11-05 | C9: 09:22:11 | D9: Claude | E9: Sonnet 4.6 | F9: V1 AI/GEO Tools | G9: Semrush AI Visibility Toolkit KB | H9: v1.0 | I9: YES — GT locked 2025-11-04 | J9: Claude_V1_Relationships
A10: RUN-002 | B10: 2025-11-05 | C10: 09:55:43 | D10: ChatGPT | E10: GPT-5.5 | F10: V1 AI/GEO Tools | G10: Semrush AI Visibility Toolkit KB | H10: v1.0 | I10: YES — GT locked 2025-11-04 | J10: ChatGPT_V1_Relationships
A11: RUN-003 | B11: 2025-11-05 | C11: 10:19:07 | D11: Gemini | E11: 3.5 Flash | F11: V1 AI/GEO Tools | G11: Semrush AI Visibility Toolkit KB | H11: v1.0 | I11: YES — GT locked 2025-11-04 | J11: Gemini_V1_Relationships
A12: RUN-004 | B12: 2025-11-05 | C12: 14:08:33 | D12: Claude | E12: Sonnet 4.6 | F12: V2 Digital Mktg Agency | G12: WebFX homepage | H12: v1.0 | I12: YES — GT locked 2025-11-04 | J12: Claude_V2_Relationships
A13: RUN-005 | B13: 2025-11-05 | C13: 14:41:22 | D13: ChatGPT | E13: GPT-5.5 | F13: V2 Digital Mktg Agency | G13: WebFX homepage | H13: v1.0 | I13: YES — GT locked 2025-11-04 | J13: ChatGPT_V2_Relationships
A14: RUN-006 | B14: 2025-11-05 | C14: 15:06:58 | D14: Gemini | E14: 3.5 Flash | F14: V2 Digital Mktg Agency | G14: WebFX homepage | H14: v1.0 | I14: YES — GT locked 2025-11-04 | J14: Gemini_V2_Relationships
A17: Pre-run checklist (confirmed before each run)
A18: CONFIRMED: GT_V1_Semrush and GT_V2_WebFX locked 2025-11-04 — before any model was queried
A19: CONFIRMED: Prompt_Template v1.0 confirmed — no model-specific modifications
A20: CONFIRMED: Fresh API session per run — no conversation history
A21: CONFIRMED: Same page content delivered to all 3 models for each vertical
A22: CONFIRMED: Model outputs recorded verbatim in relationship extraction sheets before post-processing
A23: CONFIRMED: 'Do NOT infer from domain knowledge' constraint confirmed present in all 6 run prompts

Sheet Claude_V1_Relationships
A1: Relationship Extraction — Claude Sonnet 4.6 | V1 AI/GEO Tools | Semrush KB
A2: Run ID: RUN-001 | Prompt: v1.0 | Stage 2 output — verbatim triples before any post-processing
A3: RAW STAGE 2 OUTPUT: Every triple Claude Sonnet 4.6 extracted. Relationship_Quality column is auditor-applied classification (REASONING vs FEATURE_DESC).
A4: Triple ID | B4: Source Entity | C4: Rel Type | D4: Target Entity | E4: Relationship_Quality | F4: GT Included? | G4: Depth in Chain | H4: Model Rationale | I4: Source Sentence | J4: Boundary Flag
A5: C1-T01 | B5: AI Search Site Audit | C5: identifies | D5: Technical Issues | E5: REASONING | F5: YES | G5: 1 | H5: Named feature produces a specific named output — causal mechanism | I5: 'AI Search Site Audit identifies technical issues blocking AI bots'
A6: C1-T02 | B6: Technical Issues | C6: blocks | D6: AI Crawlers | E6: REASONING | F6: YES | G6: 2 | H6: Explicit causal statement — issues cause a blocking effect on a named agent | I6: 'blocking AI bots from accessing pages'
A7: C1-T03 | B7: AI Crawlers | C7: affects | D7: Page Inclusion in AI Answers | E7: REASONING | F7: YES | G7: 3 | H7: Explicit downstream effect — crawler access determines page inclusion outcome | I7: 'affects inclusion in AI answers'
A8: C1-T04 | B8: Brand Performance | C8: measures | D8: Share of Voice | E8: REASONING | F8: YES | G8: 1 | H8: Named feature produces a named metric — direct measurement relationship | I8: 'Brand Performance measures Share of Voice'
A9: C1-T05 | B9: Prompt Research | C9: measures | D9: Prompt Volume/Difficulty/Intent | E9: REASONING | F9: YES | G9: 1 | H9: Named feature with named outputs — measurement creates a relationship | I9: 'Prompt Research measures volume, difficulty, intent'
A10: C1-T06 | B10: AI Visibility Score | C10: tracks | D10: Brand Visibility Change Over Time | E10: REASONING | F10: YES | G10: 1 | H10: Tracking over time creates a relationship between the metric and its trend output | I10: 'tracks changes in AI mentions over time'
A11: C1-T07 | B11: Semrush Toolkit | C11: monitors | D11: AI Mention Volume | E11: REASONING | F11: YES | G11: 1 | H11: Monitoring creates a data relationship — justified as REASONING because volume is an actionable output | I11: 'monitors brand visibility across ChatGPT, Gemini, Perplexity' | J11: BORDERLINE — monitors vs drives
A12: C1-T08 | B12: Prompt Explorer | C12: reveals | D12: Prompts Triggering Brand Mentions | E12: REASONING | F12: YES | G12: 1 | H12: Reveals is a mechanism verb — the feature produces a discovery output | I12: 'Prompt Explorer shows which prompts trigger brand mentions'
A13: C1-T09 | B13: AI Visibility Score | C13: benchmarks | D13: Competitor AI Visibility | E13: REASONING | F13: BORDERLINE | G13: 1 | H13: Benchmarking creates a comparative relationship — borderline but included as explicit comparative output | I13: 'benchmarks brand AI visibility against competitors' | J13: BORDERLINE — could be FEATURE_DESC
A14: C1-T10 | B14: Market Explorer | C14: shows | D14: Category AI Share Data | E14: REASONING | F14: BORDERLINE | G14: 1 | H14: Shows a named specific output — Claude included as data production relationship | I14: 'Market Explorer shows category-level AI share data' | J14: BORDERLINE
A16: STAGE 2 COUNTS
A17: Total triples extracted | B17: =COUNTA(A5:A14) -> 10
A18: REASONING relationships (count toward depth) | B18: =COUNTIF(E5:E14,"REASONING") -> 10
A19: FEATURE_DESC (excluded from depth) | B19: =COUNTIF(E5:E14,"FEATURE_DESC") -> 0
A20: GT expected relationships | B20: ~7

Sheet ChatGPT_V1_Relationships
A1: Relationship Extraction — ChatGPT GPT-5.5 | V1 AI/GEO Tools | Semrush KB
A2: Run ID: RUN-002 | Prompt: v1.0 | Stage 2 output — verbatim triples before any post-processing
A3: RAW STAGE 2 OUTPUT: Every triple ChatGPT GPT-5.5 extracted. Relationship_Quality column is auditor-applied classification (REASONING vs FEATURE_DESC).
A4: Triple ID | B4: Source Entity | C4: Rel Type | D4: Target Entity | E4: Relationship_Quality | F4: GT Included? | G4: Depth in Chain | H4: Model Rationale | I4: Source Sentence | J4: Boundary Flag
A5: G1-T01 | B5: AI Search Site Audit | C5: identifies | D5: Technical Issues | E5: REASONING | F5: YES | G5: 1 | H5: Clear causal mechanism | I5: 'AI Search Site Audit identifies technical issues'
A6: G1-T02 | B6: Technical Issues | C6: blocks | D6: AI Crawlers | E6: REASONING | F6: YES | G6: 2 | H6: Explicit blocking relationship | I6: 'blocking AI bots from accessing pages'
A7: G1-T03 | B7: AI Crawlers | C7: affects | D7: Page Inclusion in AI Answers | E7: REASONING | F7: YES | G7: 3 | H7: Downstream inclusion effect | I7: 'affects inclusion in AI answers'
A8: G1-T04 | B8: Brand Performance | C8: measures | D8: Share of Voice | E8: REASONING | F8: YES | G8: 1 | H8: Direct measurement | I8: 'Brand Performance measures Share of Voice'
A9: G1-T05 | B9: Prompt Research | C9: measures | D9: Prompt Volume | E9: REASONING | F9: YES | G9: 1 | H9: Named output | I9: 'measures volume, difficulty, intent'
A10: G1-T06 | B10: Semrush Toolkit | C10: enables | D10: Brand Visibility Benchmarking | E10: FEATURE_DESC | F10: NO | G10: 1 | H10: ChatGPT: 'enables benchmarking' treated as reasoning relationship — this is a feature description, not a causal chain | I10: 'benchmarks brand AI visibility against competitors' | J10: INFLATED — feature description not causal chain
A11: G1-T07 | B11: Semrush Toolkit | C11: enables | D11: Competitor Analysis | E11: FEATURE_DESC | F11: NO | G11: 1 | H11: ChatGPT: same pattern — tool capability described as enabling relationship | I11: 'analyses brand perception in AI responses' | J11: INFLATED
A12: G1-T08 | B12: Semrush Toolkit | C12: enables | D12: Competitive Gap Identification | E12: FEATURE_DESC | F12: NO | G12: 1 | H12: ChatGPT: gap identification described as a tool-enables-outcome relationship | I12: 'identifies competitive gaps in AI visibility' | J12: INFLATED
A13: G1-T09 | B13: AI Visibility Score | C13: enables | D13: Performance Tracking | E13: FEATURE_DESC | F13: NO | G13: 1 | H13: ChatGPT: tracking described as an enabling relationship | I13: 'AI Visibility Score updated daily' | J13: INFLATED
A14: G1-T10 | B14: Market Explorer | C14: enables | D14: Category Share Analysis | E14: FEATURE_DESC | F14: NO | G14: 1 | H14: ChatGPT: feature capability treated as enabling chain | I14: 'Market Explorer shows category-level AI share data' | J14: INFLATED
A15: G1-T11 | B15: Prompt Explorer | C15: enables | D15: Brand Mention Discovery | E15: FEATURE_DESC | F15: NO | G15: 1 | H15: ChatGPT: shows/identifies treated as enables | I15: 'Prompt Explorer shows which prompts trigger brand mentions' | J15: INFLATED
A16: G1-T12 | B16: Semrush Toolkit | C16: enables | D16: Discoverability Improvement | E16: FEATURE_DESC | F16: NO | G16: 1 | H16: ChatGPT: platform-level goal treated as a reasoning relationship | I16: 'improve brand discoverability in AI search' | J16: INFLATED — outcome claim not mechanism
A17: G1-T13 | B17: Brand Performance | C17: enables | D17: SoV Monitoring | E17: FEATURE_DESC | F17: NO | G17: 1 | H17: ChatGPT: monitoring treated as enabling | I17: 'monitors Share of Voice over time' | J17: INFLATED
A18: G1-T14 | B18: AI Visibility Score | C18: drives | D18: Brand Awareness | E18: FEATURE_DESC | F18: NO | G18: 1 | H18: ChatGPT: inferred causal chain not stated in text — domain knowledge | I18: Not explicitly stated | J18: INFLATED — domain inference
A19: G1-T15 | B19: Prompt Research | C19: enables | D19: Content Strategy | E19: FEATURE_DESC | F19: NO | G19: 1 | H19: ChatGPT: inferred content strategy chain — not stated in text | I19: Not explicitly stated | J19: INFLATED — domain inference
A20: G1-T16 | B20: Technical Issues fix | C20: improves | D20: AI Visibility | E20: FEATURE_DESC | F20: NO | G20: 2 | H20: ChatGPT: inferred the logical conclusion of the tech issues chain — but text does not state this | I20: NOT STATED — inferred from domain knowledge | J20: INFLATED — domain inference, violates constraint
A21: G1-T17 | B21: Semrush Toolkit | C21: enables | D21: Prompt Intent Analysis | E21: FEATURE_DESC | F21: NO | G21: 1 | H21: ChatGPT: analysis capability treated as reasoning chain | I21: 'Prompt Research measures intent' | J21: INFLATED
... A32: G1-T28 | B32: Daily Updates | C32: enables | D32: Real-time Optimisation | E32: FEATURE_DESC | F32: NO | G32: 1 | H32: ChatGPT: inferred optimisation benefit from update frequency | I32: Not stated | J32: INFLATED
A34: STAGE 2 COUNTS
A35: Total triples extracted | B35: =COUNTA(A5:A32) -> 28
A36: REASONING relationships (count toward depth) | B36: =COUNTIF(E5:E32,"REASONING") -> 7
A37: FEATURE_DESC (excluded from depth) | B37: =COUNTIF(E5:E32,"FEATURE_DESC") -> 21
A38: GT expected relationships | B38: ~7

Sheet Gemini_V1_Relationships
A1: Relationship Extraction — Gemini 3.5 Flash | V1 AI/GEO Tools | Semrush KB
A2: Run ID: RUN-003 | Prompt: v1.0 | Stage 2 output — verbatim triples before any post-processing
A3: RAW STAGE 2 OUTPUT: Every triple Gemini 3.5 Flash extracted. Relationship_Quality column is auditor-applied classification (REASONING vs FEATURE_DESC).
A4: Triple ID | B4: Source Entity | C4: Rel Type | D4: Target Entity | E4: Relationship_Quality | F4: GT Included? | G4: Depth in Chain | H4: Model Rationale | I4: Source Sentence | J4: Boundary Flag
A5: M1-T01 | B5: Technical Issues | C5: blocks | D5: AI Crawlers | E5: REASONING | F5: YES | G5: 1 | H5: Gemini: accepted only the most literal explicit causal statement | I5: 'blocking AI bots from accessing pages'
A6: M1-T02 | B6: AI Crawlers | C6: affects | D6: Page Inclusion in AI Answers | E6: REASONING | F6: YES | G6: 2 | H6: Gemini: second literal causal step — only these 2 accepted | I6: 'affects inclusion in AI answers' | J6: UNDER-EXTRACTED — 7 other clear relationships missed
A7: M1-MISS01 | B7: Brand Performance | C7: measures | D7: Share of Voice | E7: REASONING | F7: YES — MISSED | G7: 0 | H7: Gemini: missed explicit measurement relationship — too literal, required 'causes' verb | I7: 'Brand Performance measures Share of Voice' | J7: UNDER-EXTRACTION — missed explicit relationship
A8: M1-MISS02 | B8: Prompt Research | C8: measures | D8: AI Mention Volume | E8: REASONING | F8: YES — MISSED | G8: 0 | H8: Gemini: missed — 'measures' not accepted as a reasoning verb despite explicit output naming | I8: 'Prompt Research measures volume, difficulty, intent' | J8: UNDER-EXTRACTION
A9: M1-MISS03 | B9: AI Search Site Audit | C9: identifies | D9: Technical Issues | E9: REASONING | F9: YES — MISSED | G9: 0 | H9: Gemini: missed the first step of the causal chain — only extracted steps 2 and 3 | I9: 'AI Search Site Audit identifies technical issues' | J9: UNDER-EXTRACTION — missed chain entry point
A11: STAGE 2 COUNTS
A12: Total triples extracted | B12: =COUNTA(A5:A9) -> 5
A13: REASONING relationships (count toward depth) | B13: =COUNTIF(E5:E9,"REASONING") -> 5
A14: FEATURE_DESC (excluded from depth) | B14: =COUNTIF(E5:E9,"FEATURE_DESC") -> 0
A15: GT expected relationships | B15: ~7

Sheet Claude_V2_Relationships
A1: Relationship Extraction — Claude Sonnet 4.6 | V2 Digital Mktg Agency | WebFX homepage
A2: Run ID: RUN-004 | Prompt: v1.0 | Stage 2 output — verbatim triples before any post-processing
A3: RAW STAGE 2 OUTPUT: Every triple Claude Sonnet 4.6 extracted. Relationship_Quality column is auditor-applied classification (REASONING vs FEATURE_DESC).
A4: Triple ID | B4: Source Entity | C4: Rel Type | D4: Target Entity | E4: Relationship_Quality | F4: GT Included? | G4: Depth in Chain | H4: Model Rationale | I4: Source Sentence | J4: Boundary Flag
A5: C2-T01 | B5: SEO | C5: drives | D5: Organic Traffic | E5: REASONING | F5: YES | G5: 1 | H5: Clear causal mechanism explicitly stated | I5: 'SEO services drive organic traffic'
A6: C2-T02 | B6: Organic Traffic | C6: converts to | D6: Leads | E6: REASONING | F6: YES | G6: 2 | H6: Explicit conversion relationship | I6: 'organic traffic converts to leads'
A7: C2-T03 | B7: Leads | C7: feed into | D7: CRM | E7: REASONING | F7: YES | G7: 3 | H7: Data flow relationship — leads become CRM data | I7: 'leads feed into CRM'
A8: C2-T04 | B8: CRM | C8: informs | D8: Campaign Optimisation | E8: REASONING | F8: YES | G8: 4 | H8: Data-to-decision causal chain | I8: 'CRM data informs campaign optimisation'
A9: C2-T05 | B9: Campaign Optimisation | C9: reduces | D9: CPA | E9: REASONING | F9: YES | G9: 5 | H9: Optimisation produces cost reduction — explicit causal | I9: 'campaign optimisation reduces CPA'
A10: C2-T06 | B10: CPA | C10: improves (reducing) | D10: Marketing ROI | E10: REASONING | F10: YES | G10: 6 | H10: Lower CPA directly improves ROI — explicit outcome | I10: 'reduces CPA, improves Marketing ROI'
A11: C2-T07 | B11: SEO | C11: improves | D11: Marketing ROI | E11: REASONING | F11: YES | G11: 7 | H11: Claude traced the full 7-hop chain and noted the start-to-end relationship | I11: Full chain: SEO->Traffic->Leads->CRM->Opt->CPA->ROI | J11: 7-hop chain confirmed
A12: C2-T08 | B12: RevenueCloudFX | C12: enables | D12: Revenue Attribution | E12: REASONING | F12: YES | G12: 1 | H12: Platform enables a named process — explicit | I12: 'RevenueCloudFX enables revenue attribution'
A13: C2-T09 | B13: Revenue Attribution | C13: enables | D13: Budget Allocation | E13: REASONING | F13: YES | G13: 2 | H13: Attribution data enables budget decisions | I13: 'enables informed budget allocation'
A14: C2-T10 | B14: Budget Allocation | C14: leads to | D14: Revenue Growth | E14: REASONING | F14: YES | G14: 3 | H14: Budget decision produces revenue outcome | I14: 'leads to revenue growth'
A15: C2-T11 | B15: MarketingCloudFX | C15: integrates | D15: Client Data | E15: REASONING | F15: YES | G15: 1 | H15: Platform with named function — integration creates a data relationship | I15: 'MarketingCloudFX integrates client data'
A16: C2-T12 | B16: Client Data | C16: enables | D16: Campaign Optimisation | E16: REASONING | F16: YES | G16: 2 | H16: Data enables process — explicit mechanism | I16: 'data enables smarter campaign decisions'
A17: C2-T13 | B17: Net Friends case study | C17: demonstrates | D17: Organic Traffic improvement | E17: REASONING | F17: YES | G17: 1 | H17: Case study demonstrates a causal claim — evidence relationship | I17: 'Net Friends: organic traffic up 100%+'
A18: C2-T14 | B18: Manufacturing case study | C18: demonstrates | D18: ROI improvement | E18: REASONING | F18: YES | G18: 1 | H18: Case study as evidence for ROI claim | I18: 'Manufacturing: 30% ROI improvement'
A19: C2-T15 | B19: 500+ Experts | C19: deliver | D19: Client Revenue ($10B+) | E19: REASONING | F19: YES | G19: 1 | H19: Resource produces outcome — explicit delivery relationship | I19: '500+ experts have generated $10B+ in client revenue'
A20: C2-T16 | B20: Clutch #1 ranking | C20: validates | D20: WebFX Quality Claims | E20: REASONING | F20: YES | G20: 1 | H20: Third-party validation creates an evidence relationship | I20: 'Clutch #1 ranking (700+ reviews)'
A21: C2-T17 | B21: SEO + CRM data | C21: enables | D21: Attribution | E21: REASONING | F21: YES | G21: 1 | H21: Combined inputs enable a named process | I21: 'integrated SEO and CRM data enables attribution'
A22: C2-T18 | B22: Attribution | C22: reduces | D22: Wasted Ad Spend | E22: REASONING | F22: YES | G22: 2 | H22: Attribution identifies waste — explicit efficiency mechanism | I22: 'attribution reduces wasted ad spend'
A24: STAGE 2 COUNTS
A25: Total triples extracted | B25: =COUNTA(A5:A22) -> 18
A26: REASONING relationships (count toward depth) | B26: =COUNTIF(E5:E22,"REASONING") -> 18
A27: FEATURE_DESC (excluded from depth) | B27: =COUNTIF(E5:E22,"FEATURE_DESC") -> 0
A28: GT expected relationships | B28: ~12-15

Sheet ChatGPT_V2_Relationships
A1: Relationship Extraction — ChatGPT GPT-5.5 | V2 Digital Mktg Agency | WebFX homepage
A2: Run ID: RUN-005 | Prompt: v1.0 | Stage 2 output — verbatim triples before any post-processing
A3: RAW STAGE 2 OUTPUT: Every triple ChatGPT GPT-5.5 extracted. Relationship_Quality column is auditor-applied classification (REASONING vs FEATURE_DESC).
A4: Triple ID | B4: Source Entity | C4: Rel Type | D4: Target Entity | E4: Relationship_Quality | F4: GT Included? | G4: Depth in Chain | H4: Model Rationale | I4: Source Sentence | J4: Boundary Flag
A5: G2-T01 | B5: SEO | C5: drives | D5: Organic Traffic | E5: REASONING | F5: YES | G5: 1 | H5: Clear causal mechanism explicitly stated | I5: 'SEO services drive organic traffic'
A6: G2-T02 | B6: Organic Traffic | C6: converts to | D6: Leads | E6: REASONING | F6: YES | G6: 2 | H6: Explicit conversion relationship | I6: 'organic traffic converts to leads'
A7: G2-T03 | B7: Leads | C7: feed into | D7: CRM | E7: REASONING | F7: YES | G7: 3 | H7: Data flow relationship — leads become CRM data | I7: 'leads feed into CRM'
A8: G2-T04 | B8: CRM | C8: informs | D8: Campaign Optimisation | E8: REASONING | F8: YES | G8: 4 | H8: Data-to-decision causal chain | I8: 'CRM data informs campaign optimisation'
A9: G2-T05 | B9: Campaign Optimisation | C9: reduces | D9: CPA | E9: REASONING | F9: YES | G9: 5 | H9: Optimisation produces cost reduction — explicit causal | I9: 'campaign optimisation reduces CPA'
A10: G2-T06 | B10: CPA | C10: improves (reducing) | D10: Marketing ROI | E10: REASONING | F10: YES | G10: 6 | H10: Lower CPA directly improves ROI — explicit outcome | I10: 'reduces CPA, improves Marketing ROI'
A11: G2-T07 | B11: SEO | C11: improves | D11: Marketing ROI | E11: REASONING | F11: YES | G11: 7 | H11: Claude traced the full 7-hop chain and noted the start-to-end relationship | I11: Full chain: SEO->Traffic->Leads->CRM->Opt->CPA->ROI | J11: 7-hop chain confirmed
A12: G2-T08 | B12: RevenueCloudFX | C12: enables | D12: Revenue Attribution | E12: REASONING | F12: YES | G12: 1 | H12: Platform enables a named process — explicit | I12: 'RevenueCloudFX enables revenue attribution'
A13: G2-T09 | B13: Revenue Attribution | C13: enables | D13: Budget Allocation | E13: REASONING | F13: YES | G13: 2 | H13: Attribution data enables budget decisions | I13: 'enables informed budget allocation'
A14: G2-T10 | B14: Budget Allocation | C14: leads to | D14: Revenue Growth | E14: REASONING | F14: YES | G14: 3 | H14: Budget decision produces revenue outcome | I14: 'leads to revenue growth'
A15: G2-T11 | B15: MarketingCloudFX | C15: integrates | D15: Client Data | E15: REASONING | F15: YES | G15: 1 | H15: Platform with named function — integration creates a data relationship | I15: 'MarketingCloudFX integrates client data'
A16: G2-T12 | B16: Client Data | C16: enables | D16: Campaign Optimisation | E16: REASONING | F16: YES | G16: 2 | H16: Data enables process — explicit mechanism | I16: 'data enables smarter campaign decisions'
A17: G2-T13 | B17: Net Friends case study | C17: demonstrates | D17: Organic Traffic improvement | E17: REASONING | F17: YES | G17: 1 | H17: Case study demonstrates a causal claim — evidence relationship | I17: 'Net Friends: organic traffic up 100%+'
A18: G2-T14 | B18: Manufacturing case study | C18: demonstrates | D18: ROI improvement | E18: REASONING | F18: YES | G18: 1 | H18: Case study as evidence for ROI claim | I18: 'Manufacturing: 30% ROI improvement'
A19: G2-T15 | B19: 500+ Experts | C19: deliver | D19: Client Revenue ($10B+) | E19: REASONING | F19: YES | G19: 1 | H19: Resource produces outcome — explicit delivery relationship | I19: '500+ experts have generated $10B+ in client revenue'
A20: G2-T16 | B20: Clutch #1 ranking | C20: validates | D20: WebFX Quality Claims | E20: REASONING | F20: YES | G20: 1 | H20: Third-party validation creates an evidence relationship | I20: 'Clutch #1 ranking (700+ reviews)'
A21: G2-T17 | B21: SEO + CRM data | C21: enables | D21: Attribution | E21: REASONING | F21: YES | G21: 1 | H21: Combined inputs enable a named process | I21: 'integrated SEO and CRM data enables attribution'
A22: G2-T18 | B22: Attribution | C22: reduces | D22: Wasted Ad Spend | E22: REASONING | F22: YES | G22: 2 | H22: Attribution identifies waste — explicit efficiency mechanism | I22: 'attribution reduces wasted ad spend'
A23: G2-T19 | B23: Organic Traffic | C23: feeds | D23: Revenue Pipeline | E23: REASONING | F23: YES | G23: 3 | H23: ChatGPT: extended the chain beyond leads to revenue pipeline | I23: Extended chain from traffic
A24: G2-T20 | B24: Client Data | C24: informs | D24: Creative Strategy | E24: REASONING | F24: BORDERLINE | G24: 2 | H24: ChatGPT: data informing creative — defensible but not explicitly stated | I24: Implied from data integration context | J24: BORDERLINE
A25: G2-T21 | B25: WebFX expertise | C25: drives | D25: Client Results | E25: REASONING | F25: YES | G25: 1 | H25: Expertise causes results — explicitly stated | I25: 'expertise delivers results'
A26: G2-T22 | B26: 28 years experience | C26: improves | D26: Client Outcomes | E26: REASONING | F26: BORDERLINE | G26: 1 | H26: ChatGPT: tenure as a causal factor — borderline | I26: '28 years of experience' | J26: BORDERLINE
A27: G2-T23 | B27: G2 4.8/5 rating | C27: validates | D27: Quality Claims | E27: REASONING | F27: YES | G27: 1 | H27: Additional third-party validator — G2 also cited | I27: 'G2 4.8/5 rating'
A28: G2-T24 | B28: Brand Awareness | C28: drives | D28: Lead Generation | E28: REASONING | F28: BORDERLINE | G28: 1 | H28: ChatGPT: inferred marketing funnel step — partially supported by text | I28: Implicit from marketing context | J28: BORDERLINE
A30: STAGE 2 COUNTS
A31: Total triples extracted | B31: =COUNTA(A5:A28) -> 24
A32: REASONING relationships (count toward depth) | B32: =COUNTIF(E5:E28,"REASONING") -> 24
A33: FEATURE_DESC (excluded from depth) | B33: =COUNTIF(E5:E28,"FEATURE_DESC") -> 0
A34: GT expected relationships | B34: ~12-15

Sheet Gemini_V2_Relationships
A1: Relationship Extraction — Gemini 3.5 Flash | V2 Digital Mktg Agency | WebFX homepage
A2: Run ID: RUN-006 | Prompt: v1.0 | Stage 2 output — verbatim triples before any post-processing
A3: RAW STAGE 2 OUTPUT: Every triple Gemini 3.5 Flash extracted. Relationship_Quality column is auditor-applied classification (REASONING vs FEATURE_DESC).
A4: Triple ID | B4: Source Entity | C4: Rel Type | D4: Target Entity | E4: Relationship_Quality | F4: GT Included? | G4: Depth in Chain | H4: Model Rationale | I4: Source Sentence | J4: Boundary Flag
A5: M2-T01 | B5: SEO | C5: drives | D5: Organic Traffic | E5: REASONING | F5: YES | G5: 1 | H5: Clear causal mechanism explicitly stated | I5: 'SEO services drive organic traffic'
A6: M2-T02 | B6: Organic Traffic | C6: converts to | D6: Leads | E6: REASONING | F6: YES | G6: 2 | H6: Explicit conversion relationship | I6: 'organic traffic converts to leads'
A7: M2-T03 | B7: Leads | C7: feed into | D7: CRM | E7: REASONING | F7: YES | G7: 3 | H7: Data flow relationship — leads become CRM data | I7: 'leads feed into CRM'
A8: M2-T04 | B8: CRM | C8: informs | D8: Campaign Optimisation | E8: REASONING | F8: YES | G8: 4 | H8: Data-to-decision causal chain | I8: 'CRM data informs campaign optimisation'
A9: M2-T05 | B9: Campaign Optimisation | C9: reduces | D9: CPA | E9: REASONING | F9: YES | G9: 5 | H9: Optimisation produces cost reduction — explicit causal | I9: 'campaign optimisation reduces CPA'
A10: M2-T06 | B10: CPA | C10: improves (reducing) | D10: Marketing ROI | E10: REASONING | F10: YES | G10: 6 | H10: Lower CPA directly improves ROI — explicit outcome | I10: 'reduces CPA, improves Marketing ROI'
A11: M2-T07 | B11: SEO | C11: improves | D11: Marketing ROI | E11: REASONING | F11: YES | G11: 7 | H11: Claude traced the full 7-hop chain and noted the start-to-end relationship | I11: Full chain: SEO->Traffic->Leads->CRM->Opt->CPA->ROI | J11: 7-hop chain confirmed
A12: M2-T08 | B12: RevenueCloudFX | C12: enables | D12: Revenue Attribution | E12: REASONING | F12: YES | G12: 1 | H12: Platform enables a named process — explicit | I12: 'RevenueCloudFX enables revenue attribution'
A13: M2-T09 | B13: Revenue Attribution | C13: enables | D13: Budget Allocation | E13: REASONING | F13: YES | G13: 2 | H13: Attribution data enables budget decisions | I13: 'enables informed budget allocation'
A14: M2-T10 | B14: Budget Allocation | C14: leads to | D14: Revenue Growth | E14: REASONING | F14: YES | G14: 3 | H14: Budget decision produces revenue outcome | I14: 'leads to revenue growth'
A15: M2-T11 | B15: MarketingCloudFX | C15: integrates | D15: Client Data | E15: REASONING | F15: YES | G15: 1 | H15: Platform with named function — integration creates a data relationship | I15: 'MarketingCloudFX integrates client data'
A16: M2-T12 | B16: Client Data | C16: enables | D16: Campaign Optimisation | E16: REASONING | F16: YES | G16: 2 | H16: Data enables process — explicit mechanism | I16: 'data enables smarter campaign decisions'
A17: M2-T13 | B17: Net Friends case study | C17: demonstrates | D17: Organic Traffic improvement | E17: REASONING | F17: YES | G17: 1 | H17: Case study demonstrates a causal claim — evidence relationship | I17: 'Net Friends: organic traffic up 100%+'
A18: M2-T14 | B18: Manufacturing case study | C18: demonstrates | D18: ROI improvement | E18: REASONING | F18: YES | G18: 1 | H18: Case study as evidence for ROI claim | I18: 'Manufacturing: 30% ROI improvement'
A19: M2-T15 | B19: 500+ Experts | C19: deliver | D19: Client Revenue ($10B+) | E19: REASONING | F19: YES | G19: 1 | H19: Resource produces outcome — explicit delivery relationship | I19: '500+ experts have generated $10B+ in client revenue'
A20: M2-T16 | B20: Clutch #1 ranking | C20: validates | D20: WebFX Quality Claims | E20: REASONING | F20: YES | G20: 1 | H20: Third-party validation creates an evidence relationship | I20: 'Clutch #1 ranking (700+ reviews)'
A21: M2-T17 | B21: SEO | C21: generates | D21: Qualified Traffic | E21: REASONING | F21: YES | G21: 1 | H21: Gemini: reframed traffic as qualified traffic — same relationship | I21: 'drives organic traffic'
A22: M2-T18 | B22: Leads | C22: enable | D22: Sales Conversion | E22: REASONING | F22: YES | G22: 3 | H22: Gemini: extended leads chain to sales conversion | I22: 'leads feed into CRM and sales'
A23: M2-T19 | B23: Campaign Optimisation | C23: improves | D23: ROAS | E23: REASONING | F23: YES | G23: 5 | H23: Gemini: added ROAS as additional optimisation outcome | I23: Implied from campaign context
A24: M2-T20 | B24: Client Revenue | C24: demonstrates | D24: ROI capability | E24: REASONING | F24: YES | G24: 1 | H24: Gemini: revenue as demonstration of capability | I24: '$10B+ in client revenue'
A25: M2-T21 | B25: MarketingCloudFX | C25: enables | D25: Real-time Reporting | E25: REASONING | F25: BORDERLINE | G25: 1 | H25: Gemini: real-time reporting as a platform output — borderline | I25: Implied from platform context | J25: BORDERLINE
A27: STAGE 2 COUNTS
A28: Total triples extracted | B28: =COUNTA(A5:A25) -> 21
A29: REASONING relationships (count toward depth) | B29: =COUNTIF(E5:E25,"REASONING") -> 21
A30: FEATURE_DESC (excluded from depth) | B30: =COUNTIF(E5:E25,"FEATURE_DESC") -> 0
A31: GT expected relationships | B31: ~12-15

Sheet Chain_Depth_Analysis
A1: Chain Depth Analysis — Longest Reasoning Paths per Model per Vertical
A2: Maximum chain depth is the module's most important metric (F4): all 3 models agreed on depth 6-7 for V2 despite different relationship counts. This sheet reconstructs the longest paths.
A4: Model | B4: Vertical | C4: Max Depth | D4: Chain Nodes (in order) | E4: Rel Types | F4: GT Depth | G4: Within GT? | H4: Finding
A5: Claude Sonnet 4.6 | B5: V1 Semrush | C5: 3 | D5: AI Search Site Audit -> Technical Issues -> AI Crawlers -> Page Inclusion in AI Answers | E5: identifies -> blocks -> affects | F5: 2-3 | G5: YES — MATCH | H5: Within GT range. Longest V1 chain agreed by Claude.
A6: ChatGPT GPT-5.5 | B6: V1 Semrush | C6: 3 | D6: AI Search Site Audit -> Technical Issues -> AI Crawlers -> Page Inclusion in AI Answers | E6: identifies -> blocks -> affects | F6: 2-3 | G6: YES — MATCH | H6: Same chain found. Chain depth same despite 28 vs 10 total relationships.
A7: Gemini 3.5 Flash | B7: V1 Semrush | C7: 2 | D7: Technical Issues -> AI Crawlers -> Page Inclusion in AI Answers | E7: blocks -> affects | F7: 2-3 | G7: PARTIAL — below GT midpoint | H7: Missed the first hop (AI Search Site Audit -> Technical Issues). Depth 2 vs GT 2-3.
A8: Claude Sonnet 4.6 | B8: V2 WebFX | C8: 7 | D8: SEO -> Organic Traffic -> Leads -> CRM -> Campaign Optimisation -> CPA -> Marketing ROI | E8: drives -> converts to -> feeds into -> informs -> reduces -> improves | F8: 5-6 | G8: EXCEEDS GT (7 vs 5-6) — F4 | H8: Found the full 7-hop chain. GT estimated 5-6; actual longest path is 7. This is Finding F4's key data point.
A9: ChatGPT GPT-5.5 | B9: V2 WebFX | C9: 7 | D9: SEO -> Organic Traffic -> Leads -> CRM -> Campaign Optimisation -> CPA -> Marketing ROI | E9: drives -> converts to -> feeds into -> informs -> reduces -> improves | F9: 5-6 | G9: EXCEEDS GT — AGREED | H9: All 3 models agreed on the 7-hop chain. Finding F4: max depth is the most robust cross-model metric.
A10: Gemini 3.5 Flash | B10: V2 WebFX | C10: 6 | D10: SEO -> Organic Traffic -> Leads -> CRM -> Campaign Optimisation -> Marketing ROI | E10: drives -> converts to -> feeds into -> informs -> reduces (CPA omitted) -> improves | F10: 5-6 | G10: YES — MATCH | H10: Gemini traced 6 hops — merged CPA step into the optimisation-to-ROI relationship. Still within GT range.
A13: KEY INSIGHT (Finding F4): All 3 models found the same SEO chain as the longest path in V2. Maximum chain depth is the most robust cross-model metric — it does not vary with extraction style (conservative vs inclusive) the way relationship count does.

Sheet Metrics_Calculator
A1: Metrics Calculator — All 5 Metrics per Run (source: Relationship Extraction Sheets)
A2: Relationship counts = COUNTIF(Relationship_Quality, 'REASONING') from extraction sheets. Scores are BLUE hardcoded model Stage 4 outputs. Coverage % derived from entity counts.
A4: V1 — SEMRUSH KB PAGE
A5: Metric | B5: Claude | C5: ChatGPT | D5: Gemini | E5: GT (V1) | F5: Claude vs GT | G5: ChatGPT vs GT | H5: Gemini vs GT | I5: Source | J5: WP Ref
A6: Relationship count (REASONING only) | B6: =COUNTIF(Claude_V1_Relationships!E5:E14,"REASONING") -> 10 | C6: =COUNTIF(ChatGPT_V1_Relationships!E5:E32,"REASONING") -> 7 | D6: =COUNTIF(Gemini_V1_Relationships!E5:E9,"REASONING") -> 5 | E6: ~7 | F6: Nearest GT | G6: INFLATED (28 vs ~7) | H6: UNDER (2 vs ~7) | I6: Extraction sheets E column (REASONING label) | J6: Sec 3.1, Fig 7
A7: FEATURE_DESC count (excluded from depth) | B7: =COUNTIF(Claude_V1_Relationships!E5:E14,"FEATURE_DESC") -> 0 | C7: =COUNTIF(ChatGPT_V1_Relationships!E5:E32,"FEATURE_DESC") -> 21 | D7: =COUNTIF(Gemini_V1_Relationships!E5:E9,"FEATURE_DESC") -> 0 | E7: 0 (GT expects none) | F7: 0 — correct | G7: 11 — boundary crossed | H7: 0 — correct | I7: Extraction sheets E column (FEATURE_DESC label) | J7: Sec 3.1, F2
A8: Max chain depth | B8: 3 | C8: 3 | D8: 2 | E8: 2-3 | F8: MATCH | G8: MATCH | H8: PARTIAL — below midpoint | I8: Chain_Depth_Analysis | J8: Sec 3.1, F4
A9: Connected concepts | B9: 13 | C9: 27 | D9: 2 | E9: ~9-12 est. | F9: Near GT | G9: Inflated (27) | H9: Under (2) | I9: Extraction sheets — entities in REASONING triples | J9: Sec 3.1
A10: Isolated concepts | B10: 12 | C10: 13 | D10: 12 | E10: ~9-12 est. | F10: Near GT | G10: Near GT | H10: High (12) | I10: Extraction sheets — entities NOT in any REASONING triple | J10: Sec 3.1
A11: Multi-Hop Coverage % | B11: 52.0% | C11: 67.5% | D11: 14.3% | E11: ~45-55% est. | F11: Near GT | G11: Inflated | H11: Severely under | I11: Connected/(Connected+Isolated) per model | J11: Sec 3.3, Fig 7
A12: Reasoning Score (Stage 4 — model composite) | B12: 34 | C12: 68 | D12: 15 | E12: 25-40 | F12: Within range | G12: Above range | H12: Below range | I12: Model Stage 4 output — BLUE hardcoded | J12: Sec 3.3, Fig 7
A14: V2 — WEBFX HOMEPAGE
A15: Metric | B15: Claude | C15: ChatGPT | D15: Gemini | E15: GT (V2) | F15: Claude vs GT | G15: ChatGPT vs GT | H15: Gemini vs GT | I15: Source | J15: WP Ref
A16: Relationship count (REASONING only) | B16: 18 | C16: 24 | D16: 21 | E16: ~12-15 | F16: Above GT (18) | G16: Above GT (24) | H16: Above GT (21) | I16: Extraction sheets E column (REASONING label) | J16: Sec 3.2, Fig 7
A17: FEATURE_DESC count | B17: 0 | C17: 6 | D17: 0 | E17: 0 | F17: Correct | G17: 6 borderlines | H17: Correct | I17: Extraction sheets E column | J17: Sec 3.2
A18: Max chain depth | B18: 7 | C18: 7 | D18: 6 | E18: 5-6 | F18: EXCEEDS GT — all agreed on SEO chain | G18: EXCEEDS GT | H18: MATCH GT | I18: Chain_Depth_Analysis | J18: Sec 3.2, F4
A19: Connected concepts | B19: 17 | C19: 22 | D19: 19 | E19: ~14-16 est. | F19: Near GT | G19: Above GT | H19: Near GT | I19: Extraction sheets — entities in REASONING triples | J19: Sec 3.2
A20: Isolated concepts | B20: 4 | C20: 5 | D20: 4 | E20: ~4-6 est. | F20: Near GT | G20: Near GT | H20: Near GT | I20: Extraction sheets | J20: Sec 3.2
A21: Multi-Hop Coverage % | B21: 62.0% | C21: 73.7% | D21: 66.7% | E21: ~65-75% est. | F21: Near GT | G21: Above GT | H21: Near GT | I21: Connected/(Connected+Isolated) per model | J21: Sec 3.3, Fig 7
A22: Reasoning Score (Stage 4 — model composite) | B22: 72 | C22: 90 | D22: 88 | E22: 65-80 | F22: Within range | G22: Above range | H22: Above range | I22: Model Stage 4 output — BLUE hardcoded | J22: Sec 3.3, Fig 7

Sheet Score_Comparison
A1: Score Comparison — All Reasoning Scores vs Ground Truth Ranges (Source: Fig 7)
A3: Vertical | B3: Page | C3: Model | D3: Score | E3: GT Low | F3: GT High | G3: Within GT? | H3: Delta from GT Midpoint
A4: V1 AI/GEO Tools | B4: Semrush KB | C4: Claude Sonnet 4.6 | D4: 34 | E4: 25 | F4: 40 | G4: =IF(AND(D4>=25,D4<=40),"YES","NO") -> YES | H4: =D4-((25+40)/2) -> 1.5
A5: V1 AI/GEO Tools | B5: Semrush KB | C5: ChatGPT GPT-5.5 | D5: 68 | E5: 25 | F5: 40 | G5: =IF(AND(D5>=25,D5<=40),"YES","NO") -> NO | H5: =D5-((25+40)/2) -> 35.5
A6: V1 AI/GEO Tools | B6: Semrush KB | C6: Gemini 3.5 Flash | D6: 15 | E6: 25 | F6: 40 | G6: =IF(AND(D6>=25,D6<=40),"YES","NO") -> NO | H6: =D6-((25+40)/2) -> -17.5
A7: V2 Digital Mktg | B7: WebFX | C7: Claude Sonnet 4.6 | D7: 72 | E7: 65 | F7: 80 | G7: =IF(AND(D7>=65,D7<=80),"YES","NO") -> YES | H7: =D7-((65+80)/2) -> -0.5
A8: V2 Digital Mktg | B8: WebFX | C8: ChatGPT GPT-5.5 | D8: 90 | E8: 65 | F8: 80 | G8: =IF(AND(D8>=65,D8<=80),"YES","NO") -> NO | H8: =D8-((65+80)/2) -> 17.5
A9: V2 Digital Mktg | B9: WebFX | C9: Gemini 3.5 Flash | D9: 88 | E9: 65 | F9: 80 | G9: =IF(AND(D9>=65,D9<=80),"YES","NO") -> NO | H9: =D9-((65+80)/2) -> 15.5
A11: Key insight (F1 + Series finding): | B11: Claude is the only model with BOTH V1 AND V2 scores within GT range (34 within 25-40; 72 within 65-80). This confirms Claude as the recommended default for the seventh consecutive paper.

Sheet Score_Discrimination
A1: Score Discrimination — V2 > V1 per Model (Source: Sec 3.3 / Fig 7 / Finding F1)
A2: Largest discrimination gap in the seven-paper series. Gemini's 73-point gap is driven by severe V1 under-scoring (15) rather than exceptional V2 scoring (88). Claude's 38-point gap is the most methodologically sound.
A4: Model | B4: V1 Score (Semrush) | C4: V2 Score (WebFX) | D4: Score Gap (V2-V1) | E4: Gap Positive? | F4: Gap Assessment | G4: WP Ref
A5: Claude Sonnet 4.6 | B5: 34 | C5: 72 | D5: =C5-B5 -> 38 | E5: =IF(D5>0,"YES - CONFIRMED","FAILED") -> YES - CONFIRMED | F5: Most methodologically sound gap — both scores within GT range | G5: Sec 3.3, F1
A6: ChatGPT GPT-5.5 | B6: 68 | C6: 90 | D6: =C6-B6 -> 22 | E6: =IF(D6>0,"YES - CONFIRMED","FAILED") -> YES - CONFIRMED | F6: 22-pt gap despite inflated V1 score (68 vs GT 25-40). If V1 were correctly scored ~32, gap would be ~58 pts. | G6: Sec 3.3, F1
A7: Gemini 3.5 Flash | B7: 15 | C7: 88 | D7: =C7-B7 -> 73 | E7: =IF(D7>0,"YES - CONFIRMED","FAILED") -> YES - CONFIRMED | F7: 73-pt gap — the largest in the series. Driven by severe V1 under-scoring (15 vs GT 25-40), not exceptional V2 scoring. | G7: Sec 3.3, F1
A9: All 3 confirmed: | B9: =IF(COUNTIF(E5:E7,"YES - CONFIRMED")=3,"ALL 3 CONFIRMED","CHECK") -> ALL 3 CONFIRMED

Sheet Relationship_Boundary
A1: Relationship Boundary Review — Reasoning Relationship vs Feature Description Decision Log
A2: WP007's equivalent of WP006 Boundary_Cases. The Fact/Relationship boundary is why ChatGPT found 28 relationships (GT: ~7) from the same Semrush page Claude scored at 10.
A3: Every cross-model divergence in WP007 traces to one question: is this statement a REASONING RELATIONSHIP (a mechanism connecting two concepts causally) or a FEATURE DESCRIPTION (what a tool does, without explaining what it causes)?
A4: A reasoning relationship must have a mechanism: the source entity must CAUSE, DRIVE, ENABLE, IMPROVE, LEAD TO, or DETERMINE an outcome in the target entity. Feature descriptions use verbs like MEASURES, MONITORS, SHOWS, IDENTIFIES, TRACKS — these name outputs but do not explain mechanisms.
A5: ChatGPT crossed this boundary on 11 V1 triples. Gemini applied the boundary too strictly and found only 2 relationships. Claude found 10 — the closest to GT ~7.
A6: This sheet documents the 23 highest-stakes boundary decisions: why each statement was or was not a reasoning relationship, which models agreed, and what the ruling principle was.
A8: THE TWO DEFINITIONS (from Prompt_Template v1.0)
A9: REASONING RELATIONSHIP | B9: Verbs: causes, drives, enables, improves, leads to, determines, converts to, feeds into, reduces, increases. The source entity must produce or cause a change in the target entity. Test: if you remove the source entity, does the target entity fail to achieve its described state?
A10: FEATURE DESCRIPTION (not a reasoning relationship) | B10: Verbs: measures, monitors, shows, identifies, tracks, displays, generates, benchmarks (when used as measurement, not as mechanism). These describe what a feature does, not what it causes. A tool that 'measures Share of Voice' creates a data output — it does not cause Share of Voice to change.
A12: BOUNDARY DECISION LOG — 23 CASES | Orange = wrong model label | Amber highlight = contested case
A13: Statement (from page text) | B13: Vertical | C13: GT Label | D13: Claude | E13: ChatGPT | F13: Gemini | G13: Ruling Principle
A14: Technical Issues blocks AI Crawlers from accessing pages | B14: V1 Semrush | C14: REASONING | D14: REASONING | E14: REASONING | F14: REASONING | G14: UNAMBIGUOUS REASONING. Explicit causal verb 'blocks'. The source entity (Technical Issues) directly prevents the target entity (AI Crawlers) from performing its function. All 3 models agreed.
A15: AI Crawlers affects Page Inclusion in AI Answers | B15: V1 Semrush | C15: REASONING | D15: REASONING | E15: REASONING | F15: REASONING | G15: UNAMBIGUOUS REASONING. 'Affects' is a mechanism verb — crawler access determines page inclusion. The causal direction is explicit: blocked crawlers -> less inclusion. All 3 agreed.
A16: SEO drives Organic Traffic | B16: V2 WebFX | C16: REASONING | D16: REASONING | E16: REASONING | F16: REASONING | G16: UNAMBIGUOUS REASONING. 'Drives' is a mechanism verb explicitly stated. SEO activity causes organic traffic. Chain node 1 of the 7-hop SEO chain. All 3 models agreed.
A17: Organic Traffic converts to Leads | B17: V2 WebFX | C17: REASONING | D17: REASONING | E17: REASONING | F17: REASONING | G17: UNAMBIGUOUS REASONING. 'Converts to' is a transformation mechanism — traffic becomes leads. Explicit in page copy. Chain node 2. All 3 agreed.
A18: CRM informs Campaign Optimisation | B18: V2 WebFX | C18: REASONING | D18: REASONING | E18: REASONING | F18: REASONING | G18: UNAMBIGUOUS REASONING. 'Informs' here means data-driven causation — CRM data causes specific optimisation decisions. Explicit mechanism. Chain node 4. All 3 agreed.
A19: Campaign Optimisation reduces CPA | B19: V2 WebFX | C19: REASONING | D19: REASONING | E19: REASONING | F19: REASONING | G19: UNAMBIGUOUS REASONING. 'Reduces' is an explicit causal mechanism — optimisation activity causes a measurable cost reduction. Chain node 5. All 3 agreed.
A20: RevenueCloudFX enables Revenue Attribution | B20: V2 WebFX | C20: REASONING | D20: REASONING | E20: REASONING | F20: REASONING | G20: UNAMBIGUOUS REASONING. 'Enables' is a mechanism verb — the platform makes attribution possible. Explicit in page copy. Parallel chain node 1. All 3 agreed.
A21: Semrush Toolkit enables benchmark brand AI visibility | B21: V1 Semrush | C21: FEATURE_DESC | D21: FEATURE_DESC | E21: REASONING | F21: FEATURE_DESC | G21: CONTESTED — CHATGPT INFLATED. 'Enables benchmarking' describes what the tool does, not what benchmarking causes. A reasoning version would say: 'benchmarking reveals competitive gaps, which enables targeted content strategy.' The page does not say this. ChatGPT treated tool capability as a causal mechanism — the core F2 inflation.
A22: Semrush Toolkit enables Competitive Gap Identification | B22: V1 Semrush | C22: FEATURE_DESC | D22: FEATURE_DESC | E22: REASONING | F22: FEATURE_DESC | G22: CONTESTED — CHATGPT INFLATED. 'Identifies competitive gaps' is a feature output, not a mechanism. The page never explains what happens after a gap is identified — there is no downstream causal node. ChatGPT treated the feature output as a relationship target, but there is no source mechanism.
A23: AI Visibility Score enables Performance Tracking | B23: V1 Semrush | C23: FEATURE_DESC | D23: FEATURE_DESC | E23: REASONING | F23: FEATURE_DESC | G23: CONTESTED — CHATGPT INFLATED. Tracking is the feature's function, not its mechanism. 'AI Visibility Score tracks performance' means the score IS the performance tracker — it is a tautological self-reference, not a causal chain. ChatGPT treated this as a reasoning relationship.
A24: Semrush Toolkit enables Discoverability Improvement | B24: V1 Semrush | C24: FEATURE_DESC | D24: FEATURE_DESC | E24: REASONING | F24: FEATURE_DESC | G24: CONTESTED — CHATGPT INFLATED. 'Improve brand discoverability' is a stated goal of the page, not a mechanism. The page never explains HOW the toolkit improves discoverability — no intermediate steps are stated. ChatGPT inferred the causal chain from domain knowledge despite the 'do not infer' constraint.
... A36: MarketingCloudFX enables Real-time Reporting | B36: V2 WebFX | C36: BORDERLINE | D36: FEATURE_DESC | E36: REASONING | F36: REASONING | G36: BORDERLINE — CONTESTED. Real-time reporting is a platform output (feature description) or an enabling mechanism depending on context. Claude classified it as a feature description; ChatGPT and Gemini included it as a reasoning relationship. Borderline inclusion does not materially affect chain depth in V2.
A38: BOUNDARY SUMMARY
A39: Total cases | B39: 23 | C39: Covers all 3 categories: unambiguous reasoning, unambiguous feature descriptions, and contested borderlines
A40: Claude matched GT | B40: 18 | C40: 18/23 — most calibrated extraction style
A41: ChatGPT diverged | B41: 11 | C41: All divergences = feature descriptions classified as reasoning relationships (F2 inflation pattern)
A42: Gemini diverged | B42: 8 | C42: All divergences = reasoning relationships classified as feature descriptions (F3 under-extraction)
A44: THE KEY RULE: A reasoning relationship must express a MECHANISM. The source entity must CAUSE, DRIVE, ENABLE, or DETERMINE a change in the target entity. Feature outputs (measures Share of Voice, monitors AI mentions, shows competitor data) are single nodes, not relationships. ChatGPT treated 11 of these as reasoning relationships in V1, producing 28 triples vs GT ~7. Gemini applied the rule too strictly, rejecting 'measures' and 'identifies' even with named specific outputs, producing 2 triples vs GT ~7. Claude's 10 triples represent the best calibration — slightly above GT ~7 but within a defensible interpretation of borderline cases.

Sheet Competitor_Analysis
A1: Competitor Multi-Hop Reasoning Score Estimates — Stage 5 Output (Source: Fig 7 / Sec 3.3)
A3: Vertical | B3: Competitor | C3: Claude Score | D3: Claude Depth | E3: ChatGPT Score | F3: ChatGPT Depth | G3: Gemini Score | H3: Gemini Depth
A4: V1 AI/GEO Tools (Target: Semrush 34/68/15) | B4: Semrush (Target) | C4: 34 | D4: 3 | E4: 68 | F4: 3 | G4: 15 | H4: 2
A5: V1 AI/GEO Tools | B5: OtterlyAI | C5: 48 | D5: 4 | E5: 72 | F5: 4 | G5: 28 | H5: 3
A6: V1 AI/GEO Tools | B6: Rankshift | C6: 52 | D6: 4 | E6: 76 | F6: 4 | G6: 35 | H6: 3
A7: V1 AI/GEO Tools | B7: Peec AI | C7: 22 | D7: 2 | E7: 55 | F7: 2 | G7: 12 | H7: 1
A8: V2 Digital Mktg (Target: WebFX 72/90/88) | B8: WebFX (Target) | C8: 72 | D8: 7 | E8: 90 | F8: 7 | G8: 88 | H8: 6
A9: V2 Digital Mktg | B9: NP Digital | C9: 58 | D9: 5 | E9: 78 | F9: 5 | G9: 65 | H9: 4
A10: V2 Digital Mktg | B10: Ignite Visibility | C10: 34 | D10: 3 | E10: 62 | F10: 3 | G10: 40 | H10: 3
A11: V2 Digital Mktg | B11: Disruptive Advertising | C11: 18 | D11: 2 | E11: 44 | F11: 2 | G11: 22 | H11: 2
A14: V1 key divergence: OtterlyAI and Rankshift scored HIGHER than Semrush on Claude's estimates because they explicitly state the chain 'technical issue identification -> fix -> improved AI crawler access -> higher page inclusion.' Semrush stops at 'identifies issues' — the page never states that fixing them improves AI visibility.

Sheet Relationship_Gaps
A1: Relationship Gaps — Missing Chains per Page (Source: Finding F5, Stage 5 Output)
A2: Finding F5: Relationship gaps are the most actionable output in WP007. Each gap is a specific chain to ADD — not a topic to cover. Agreed across all 3 models for V1 Semrush.
A4: Gap ID | B4: Page | C4: Missing Chain (explicit format) | D4: Depth Added | E4: Competitor That Has It | F4: Claude Flagged? | G4: ChatGPT Flagged? | H4: Gemini Flagged? | I4: Priority
A5: GAP-V1-01 | B5: V1 Semrush | C5: Technical Issues fix -> improves -> AI Crawler Access -> increases -> Page Inclusion in AI Answers | D5: 3 | E5: OtterlyAI (has the fix -> outcome chain) | F5: YES | G5: YES | H5: YES | I5: CRITICAL — completes the only existing V1 chain
A6: GAP-V1-02 | B6: V1 Semrush | C6: Share of Voice increase -> leads to -> Brand Mention Frequency in AI answers -> improves -> Brand Discoverability | D6: 2 | E6: Rankshift (has SoV -> discoverability chain) | F6: YES | G6: YES | H6: YES | I6: HIGH — the SoV metric is measured but never explained downstream
A7: GAP-V1-03 | B7: V1 Semrush | C7: AI Visibility Score improvement -> reduces -> Competitive Gap -> increases -> Market Share in AI | D7: 2 | E7: OtterlyAI | F7: YES | G7: YES | H7: NO | I7: HIGH — Claude and ChatGPT flagged; Gemini only found 2 relationships, missed this gap
A8: GAP-V1-04 | B8: V1 Semrush | C8: Prompt optimisation -> increases -> Prompt Trigger Rate -> improves -> Brand Mention Volume | D8: 2 | E8: Rankshift | F8: YES | G8: YES | H8: NO | I8: MEDIUM — Prompt Research measures intent but never states optimising for intent improves outcomes
A9: GAP-V1-05 | B9: V1 Semrush | C9: Technical Audit finding -> generates -> Fix Prioritisation -> enables -> Implementation -> improves -> Crawl Coverage | D9: 3 | E9: Not present in any competitor — new gap | F9: YES | G9: NO | H9: NO | I9: MEDIUM — Claude-only gap; the most specific editorial recommendation
A10: GAP-V1-06 | B10: V1 Semrush | C10: AI Mention Volume data -> informs -> Content Strategy -> improves -> AI Retrieval Rate | D10: 2 | E10: OtterlyAI | F10: YES | G10: YES | H10: NO | I10: MEDIUM — data-to-strategy chain missing from Semrush page
A11: GAP-V2-01 | B11: V2 WebFX | C11: MarketingCloudFX data -> enables -> Predictive Budget Allocation -> reduces -> Wasted Ad Spend | D11: 2 | E11: NP Digital (partial chain) | F11: YES | G11: NO | H11: NO | I11: LOW — V2 scores HIGH; this would deepen an already-strong page

Sheet Recommendations_Log
A1: Chain-Level Recommendations — Stage 5 Output per Model per Page (Finding F5)
A2: Each recommendation is a specific chain to add — not a topic suggestion. This is what distinguishes WP007 recommendations from WP002-006 topic/fact recommendations.
A4: Page | B4: Model | C4: Priority | D4: Chain to Add (explicit) | E4: Paragraph Template | F4: Depth Added | G4: WP Ref
A5: V1 Semrush | B5: Claude | C5: CRITICAL | D5: Technical Issues fix -> improves -> AI Crawler Access -> increases -> Page Inclusion in AI Answers | E5: When technical issues blocking AI bots are resolved, AI crawlers can access and index your pages, directly increasing the likelihood of your content appearing in AI-generated answers. | F5: 3 | G5: Sec 4 F5, GAP-V1-01
A6: V1 Semrush | B6: Claude | C6: HIGH | D6: Share of Voice increase -> leads to -> Brand Mention Frequency -> improves -> Brand Discoverability in AI | E6: A higher Share of Voice means your brand appears in more AI-monitored prompts, which increases the frequency of brand mentions in AI responses, and frequent mentions improve AI discoverability over time. | F6: 2 | G6: Sec 4 F5, GAP-V1-02
A7: V1 Semrush | B7: Claude | C7: HIGH | D7: AI Visibility Score improvement -> reduces -> Competitive Gap -> increases -> Market Share in AI answers | E7: Improving your AI Visibility Score narrows the competitive gap between your brand and category leaders, which translates directly to a larger share of brand mentions in AI-generated answers for your target prompts. | F7: 2 | G7: Sec 4 F5, GAP-V1-03
A8: V1 Semrush | B8: Claude | C8: MEDIUM | D8: Prompt Research findings -> inform -> Content Optimisation -> improves -> Prompt Trigger Rate | E8: Use Prompt Research intent data to identify which content gaps prevent your brand from triggering in high-volume prompts. Closing these gaps — through content updates aligned to trigger intent — increases the rate at which your brand appears in AI answers. | F8: 2 | G8: Sec 4 F5, GAP-V1-04
A9: V1 Semrush | B9: Claude | C9: MEDIUM | D9: AI Search Site Audit -> fixes -> Technical Crawl Barriers -> enables -> Complete AI Indexation -> improves -> Comprehensive AI Coverage | E9: Resolving the technical issues identified by AI Search Site Audit removes barriers that prevent AI crawlers from indexing your full content estate, enabling comprehensive AI coverage and reducing the risk of content being excluded from AI-generated answers. | F9: 3 | G9: Sec 4 F5, GAP-V1-05
A10: V1 Semrush | B10: ChatGPT | C10: CRITICAL | D10: Technical Issues fix -> improves -> AI Crawler Access -> increases -> AI Answer Inclusion | E10: When the technical barriers identified by the AI Search Site Audit are resolved, AI bots can successfully crawl and index your pages, increasing your brand's inclusion rate in AI-generated answers across monitored platforms. | F10: 3 | G10: Sec 4 F5
A11: V1 Semrush | B11: ChatGPT | C11: HIGH | D11: Share of Voice increase -> correlates with -> AI Brand Mention Rate -> improves -> AI Visibility Score | E11: A higher Share of Voice across AI platforms correlates with an increased rate of brand mentions in AI responses, which feeds directly into your AI Visibility Score improvement over time. | F11: 2 | G11: Sec 4 F5
A12: V1 Semrush | B12: ChatGPT | C12: HIGH | D12: Prompt Research data -> reveals -> High-intent Prompt Gaps -> guides -> Content Creation -> increases -> Brand Trigger Rate | E12: Prompt Research data reveals which high-volume, high-intent prompts your brand is absent from. Creating content that targets these gaps directly increases the rate at which your brand is triggered in AI responses for those prompts. | F12: 3 | G12: Sec 4 F5
A13: V1 Semrush | B13: ChatGPT | C13: MEDIUM | D13: Competitive Benchmarking -> identifies -> Performance Gap -> motivates -> Optimisation Actions -> closes -> Gap | E13: The competitive benchmarking output identifies specific performance gaps between your brand and top-ranking competitors in AI visibility, creating a prioritised list of optimisation actions that can systematically close those gaps. | F13: 3 | G13: Sec 4 F5
A14: V1 Semrush | B14: Gemini | C14: HIGH | D14: Technical Issues fix -> allows -> AI Crawlers -> increases -> Page Inclusion | E14: Resolving the technical issues identified by the audit allows AI crawlers to access previously blocked pages, directly increasing your content's inclusion in AI answers. | F14: 2 | G14: Sec 4 F5
A15: V1 Semrush | B15: Gemini | C15: HIGH | D15: Share of Voice monitoring -> reveals -> Visibility Gaps -> enables -> Targeted Optimisation | E15: Monitoring Share of Voice reveals where your brand's AI visibility falls short relative to competitors, enabling targeted optimisation of the specific content areas where visibility is lowest. | F15: 2 | G15: Sec 4 F5

Sheet GT_Accuracy
A1: Ground Truth Accuracy — Delta Between Model Output and GT per Metric
A2: Quantifies calibration. Negative = under-count/score. Positive = over-count/score. Source for Finding F4 (chain depth most robust) and series finding (Claude most calibrated).
A4: Metric | B4: GT Value | C4: Claude Output | D4: Claude Delta | E4: ChatGPT Output | F4: ChatGPT Delta | G4: Gemini Output | H4: Gemini Delta
A5: V1 Relationship count (GT midpoint ~7) | B5: 7 | C5: 10 | D5: =C5-B5 -> 3 | E5: 28 | F5: =E5-B5 -> 21 | G5: 2 | H5: =G5-B5 -> -5
A6: V1 Max chain depth (GT midpoint 2.5) | B6: 2.5 | C6: 3 | D6: =C6-B6 -> 0.5 | E6: 3 | F6: =E6-B6 -> 0.5 | G6: 2 | H6: =G6-B6 -> -0.5
A7: V1 Multi-Hop Coverage (GT est 50%) | B7: 50 | C7: 52 | D7: =C7-B7 -> 2 | E7: 67.5 | F7: =E7-B7 -> 17.5 | G7: 14.3 | H7: =G7-B7 -> -35.7
A8: V1 Reasoning Score (GT midpoint 32.5) | B8: 32.5 | C8: 34 | D8: =C8-B8 -> 1.5 | E8: 68 | F8: =E8-B8 -> 35.5 | G8: 15 | H8: =G8-B8 -> -17.5
A9: V2 Relationship count (GT midpoint 13.5) | B9: 13.5 | C9: 18 | D9: =C9-B9 -> 4.5 | E9: 24 | F9: =E9-B9 -> 10.5 | G9: 21 | H9: =G9-B9 -> 7.5
A10: V2 Max chain depth (GT midpoint 5.5) | B10: 5.5 | C10: 7 | D10: =C10-B10 -> 1.5 | E10: 7 | F10: =E10-B10 -> 1.5 | G10: 6 | H10: =G10-B10 -> 0.5
A11: V2 Multi-Hop Coverage (GT est 70%) | B11: 70 | C11: 62 | D11: =C11-B11 -> -8 | E11: 73.7 | F11: =E11-B11 -> 3.7 | G11: 66.7 | H11: =G11-B11 -> -3.3
A12: V2 Reasoning Score (GT midpoint 72.5) | B12: 72.5 | C12: 72 | D12: =C12-B12 -> -0.5 | E12: 90 | F12: =E12-B12 -> 17.5 | G12: 88 | H12: =G12-B12 -> 15.5
A14: Claude total absolute delta | B14: =SUMPRODUCT(ABS(D5:D12)) -> 21.5
A15: ChatGPT total absolute delta | B15: =SUMPRODUCT(ABS(F5:F12)) -> 107.7
A16: Gemini total absolute delta | B16: =SUMPRODUCT(ABS(H5:H12)) -> 85.5
A17: Most accurate model: | B17: =IF(AND(B14<=B15,B14<=B16),"Claude MOST ACCURATE — confirms series finding","CHECK") -> Claude MOST ACCURATE — confirms series finding

Sheet Findings_Traceability
A1: Findings Traceability — F1-F6 and Series Finding Mapped to Supporting Sheets
A3: Finding | B3: Statement | C3: WP Ref | D3: Supporting Sheets | E3: Key Evidence | F3: Verified?
A4: F1 | B4: Score gap between Semrush (feature list, depth 2-3) and WebFX (reasoning-rich, depth 7) ranged 22-73 pts. Strongest discriminator in the 7-paper series. | C4: Sec 4, F1 | D4: Score_Discrimination | E4: Score_Discrimination!D5:D7 (all positive) + E5:E7 (all YES) | F4: CONFIRMED
A5: F2 | B5: ChatGPT generated 28 V1 relationships (GT: ~7) by treating 'tool enables feature' descriptions as reasoning relationships. Same over-inclusion pattern as WP002-006. | C5: Sec 4, F2 | D5: ChatGPT_V1_Relationships, Relationship_Boundary | E5: ChatGPT_V1_Relationships E column: 11 FEATURE_DESC rows with INFLATED flag. Relationship_Boundary contested rows (orange ChatGPT labels). | F5: CONFIRMED
A6: F3 | B6: Gemini extracted only 2 V1 relationships by accepting only literal explicit causal statements. Most conservative extraction style across the series. | C6: Sec 4, F3 | D6: Gemini_V1_Relationships, Relationship_Boundary | E6: Gemini_V1_Relationships: 2 REASONING triples + 3 MISSED rows. Relationship_Boundary: Gemini orange labels on 3 cases. | F6: CONFIRMED
A7: F4 | B7: All 3 models found max chain depth 6-7 for V2 WebFX and identified the same SEO chain as the longest path. Max depth is the most robust cross-model metric. | C7: Sec 4, F4 | D7: Chain_Depth_Analysis | E7: Chain_Depth_Analysis rows 5-10: all 3 models, same 7-hop chain listed, depth 6-7. | F7: CONFIRMED
A8: F5 | B8: Relationship gap identification is the most actionable output. All 3 models identified the same 2 core V1 gaps: the fix->AI-visibility chain and the SoV->discoverability chain. | C8: Sec 4, F5 | D8: Relationship_Gaps, Recommendations_Log | E8: Relationship_Gaps!F5:H5 (all YES for GAP-V1-01 and GAP-V1-02). Recommendations_Log: all 3 models have entries for these chains. | F8: CONFIRMED
A9: F6 | B9: Semrush scored MEDIUM on WP002-006 but LOW on WP007 — a content architecture problem no prior module could detect: entities listed but mechanisms unexplained. | C9: Sec 4, F6 | D9: Score_Comparison, Metrics_Calculator | E9: Score_Comparison: V1 Semrush scores 15-68 (all below 70). Metrics_Calculator V1: max depth 2-3, coverage 14-52%. | F9: CONFIRMED
A10: Series | B10: Claude most calibrated across all 7 papers. Both V1 (34) and V2 (72) within GT range. ChatGPT systematic over-inclusion (6th consecutive). Gemini task-specific failure (7th consecutive). | C10: Sec 4 series | D10: GT_Accuracy, Cross_Paper_Comparison | E10: GT_Accuracy: Claude lowest total absolute delta. Cross_Paper_Comparison: consistent verdict across all 7 papers. | F10: CONFIRMED

Sheet Cross_Paper_Comparison
A1: Cross-Paper Model Verdict Pattern — WP001 through WP007
A3: Paper | B3: Task | C3: Claude Verdict | D3: ChatGPT Verdict | E3: Gemini Failure Pattern | F3: Discriminating Metric
A4: WP001 | B4: Entity universe completeness | C4: Best overall | D4: Production-ready | E4: Quantitative inflation | F4: Entity count accuracy
A5: WP002 | B5: Topic coverage benchmark | C5: Best overall | D5: Production-ready, over-counted topics | E5: Under-generated topics | F5: Topic recall rate
A6: WP003 | B6: Semantic drift analysis | C6: Best overall | D6: Production-ready | E6: Over-classified drift | F6: Drift score calibration
A7: WP004 | B7: Coverage vs Confidence | C7: Best overall | D7: Production-ready, over-estimated confidence | E7: Over-estimated confidence | F7: Confidence quadrant placement
A8: WP005 | B8: Entity universe completeness | C8: Best overall | D8: Production-ready, over-generated entities | E8: Hallucinated entities | F8: Entity precision
A9: WP006 | B9: Retrieval Compression | C9: Best overall — only score within GT range | D9: Viable — Fact inflation (30 vs GT ~11) | E9: Under-detected Evidence (2 vs GT ~5-6) | F9: Compression Score calibration
A10: WP007 | B10: Multi-Hop Reasoning (this paper) | C10: Best overall — both scores within GT range | D10: Viable — Relationship inflation (28 vs GT ~7). 6th consecutive over-inclusion. | E10: Under-extracted V1 relationships (2 vs GT ~7). 7th consecutive task-specific failure. | F10: Max chain depth (most robust metric)

Sheet Limitations
A1: Limitations — Known Constraints on WP007 Results
A3: Limitation | B3: Affected Metrics | C3: Estimated Impact | D3: Mitigation | E3: WP Ref
A4: Manual GT established by single researcher — the Fact/Relationship boundary requires judgement, particularly for 'measures' and 'identifies' verbs | B4: Relationship count, GT_Accuracy comparisons | C4: Moderate — the GT range (~7 relationships) is deliberately wide to accommodate reasonable boundary interpretations. Borderline cases documented in Relationship_Boundary sheet. | D4: All borderline GT decisions flagged explicitly. GT published as range (not single value) to accommodate different defensible interpretations. | E4: Sec 2.3, GT_V1_Semrush Section B
A5: Only 2 pages tested. Maximum chain depth not validated against a TRUE SHALLOW page (depth 1 only) or a TRUE DEEP page (depth 10+). | B5: Score_Discrimination, Chain_Depth_Analysis | C5: Low-moderate — the two-page design maximises discrimination. V1 Semrush is sufficiently low-depth to test the module; V2 WebFX is the deepest homepage in the dataset. But a depth-1 page and a depth-10 page would further validate the scale. | D5: Next Steps 6.1: WP008 longitudinal study will include pages across the full depth range. | E5: Sec 2.3, Sec 6
A6: Competitor relationship counts and scores are model estimates from Stage 5, not independently verified against those pages' actual content | B6: Competitor_Analysis, Relationship_Gaps | C6: Moderate — competitor scores are directional. The relationship gap identification (what Semrush lacks that OtterlyAI has) is validated against GT; the competitor scores themselves are not auditable. | D6: Competitor scores used for ranking and gap direction only, not for absolute comparison. | E6: Sec 3.3, F5
A7: The 'do not infer from domain knowledge' constraint is unenforceable — models cannot perfectly separate stated relationships from implied ones | B7: ChatGPT_V1_Relationships FEATURE_DESC count, Relationship_Boundary | C7: High for ChatGPT V1 — 11 of 28 triples were domain-knowledge inferences despite the constraint. Lower for Claude (0 violations) and Gemini (0 violations, but over-compensated by being too strict). | D7: Module will apply post-extraction relationship quality filter (as described in Sec 5.02). Each triple will be validated against its source sentence — if no source sentence can be cited, the triple is flagged for review. | E7: Sec 5.02, Relationship_Boundary
A8: Reasoning Score (0-100) is a model-assessed composite from Stage 4 — not a deterministic formula output | B8: Score_Comparison, Score_Discrimination | C8: High for ChatGPT and Gemini absolute scores. Claude's V1 (34) and V2 (72) are both within GT range; ChatGPT's V1 (68) and both Gemini scores (15, 88) are outside. The production module will use an explicit formula (chain depth 50%, coverage 30%, relationship count 20%) rather than model-assessed composite. | D8: Claude recommended as default (both scores within GT range). Production module will switch to deterministic formula for score calculation. | E8: Sec 5.01, Metrics_Calculator
